Workbook

Sheet README
A1: Finvasia PT-R&R Platform - Corrected Source Data
A2: Prepared 29-Sep-2026, extended 08-Oct-2026, from: Organizational_Chart (23-Aug-26), Project_Tracker (Rest, Shoonya), R_R_Parameters_2, RACI, RCA
A4: As-of date used for overdue checks | B4: 46294
A6: Sheet | B6: What it contains
A7: Employee_Master | B7: Every box from the 17 visible org-chart sheets as one row. Proposed record IDs (EMP-/POS-), cleaned name and designation, reporting manager, proposed login role, and data-quality flags. The 2 hidden sheets (Prodduct, Product-Shoonya) are outdated copies and were NOT imported.
A8: Name_Collisions | B8: Names shared by more than one record. Each must be confirmed against HRMS before import.
A9: Departments | B9: Canonical department list, head, live headcount, proposed performance category, and the tracker aliases that map to it.
A10: Category_Weights | B10: Corrected metric weights per team category. Every column must total 100% (check row).
A11: Tracker_Cleaned | B11: Original 115 tracker rows split to one row per task x assignee, with resolved Employee IDs, mapped statuses, classified blockers and derived timing (formulas).
A12: Project_Register | B12: One row per project with proposed PRJ IDs and live task counts.
A13: OnTime_Recalc | B13: On-time rate recalculated with the corrected eligibility rules, beside the value the old sheet produced.
A14: Issue_Register | B14: Every issue found in the five source files, with severity and the fix applied.
A15: Workflow_Templates | B15: RACI.xlsx turned into a reusable "Email campaign" project template: one row per step with R / A / C / I, checklist, reviewer, required evidence, SLA in business days and effort. Conflicts between the two versions in the source are flagged.
A16: Risk_Register | B16: Risks from RACI.xlsx, one per row, linked to the template step, with criticality, dependencies, assumptions, mitigation and new owner / status / review-date fields.
A17: RCA_Register | B17: Incident root-cause log built from RCA.xlsx (which had headers only). Fill one row per incident; grey columns are formulas. Header comments show which source column each field came from. Row 2 is an example to replace or delete.
... A20: ID note | B20: EMP-/POS-/PRJ- IDs are placeholders so the data can be linked now. Replace EMP IDs with official HRMS employee codes before go-live; the HRMS column is provided for that.

Sheet Employee_Master
A1: Record ID | B1: HRMS Emp Code (fill) | C1: Record Type | D1: Full Name | E1: Designation | F1: Department | G1: Level in Chart | H1: Reporting Manager ID | I1: Reporting Manager | J1: Direct Reports | K1: Proposed Platform Role | L1: Flags / To Confirm | M1: Original Chart Text
A2: POS-0001 | C2: Vacant Position | D2: (vacant) | E2: Managing Director | F2: AI | G2: 1 | J2: =COUNTIF($H$2:$H$326,A2) -> 7 | K2: None (vacant) | L2: Vacant / unnamed position | M2: Managing Director
A3: EMP-0002 | C3: Employee | D3: Anudesh Saini | E3: Machine Learning Engineer | F3: AI | G3: 2 | H3: POS-0001 | I3: Managing Director | J3: =COUNTIF($H$2:$H$326,A3) -> 4 | K3: Manager | M3: Anudesh Saini (Machine Learning Engineer)
A4: EMP-0003 | C4: Employee | D4: Mukund Madhav | E4: Data Engineer | F4: AI | G4: 3 | H4: EMP-0002 | I4: Anudesh Saini | J4: =COUNTIF($H$2:$H$326,A4) -> 1 | K4: Manager | M4: Mukund Madhav (Data Engineer)
A5: EMP-0004 | C5: Employee | D5: Piyush Chhabra | E5: Data Engineer | F5: AI | G5: 4 | H5: EMP-0003 | I5: Mukund Madhav | J5: =COUNTIF($H$2:$H$326,A5) -> 0 | K5: None (employee record) | M5: Piyush Chhabra (Data Engineer)
A6: EMP-0005 | C6: Employee | D6: Chetan Sharma | E6: AI Engineer | F6: AI | G6: 3 | H6: EMP-0002 | I6: Anudesh Saini | J6: =COUNTIF($H$2:$H$326,A6) -> 2 | K6: Manager | M6: Chetan Sharma (AI Engineer)
A7: EMP-0006 | C7: Employee | D7: Divyanshu | E7: Jr. ML Ops Engineer | F7: AI | G7: 4 | H7: EMP-0005 | I7: Chetan Sharma | J7: =COUNTIF($H$2:$H$326,A7) -> 0 | K7: None (employee record) | L7: Single name only - add surname | M7: Divyanshu (Jr. ML Ops Engineer)
A8: EMP-0007 | C8: Employee | D8: Nikhal Kumar Rana | E8: Associate AI Engineer | F8: AI | G8: 4 | H8: EMP-0005 | I8: Chetan Sharma | J8: =COUNTIF($H$2:$H$326,A8) -> 0 | K8: None (employee record) | M8: Nikhal Kumar Rana (Associate AI Engineer)
A9: EMP-0008 | C9: Employee | D9: Ankit Sharma | E9: Data Analyst | F9: AI | G9: 3 | H9: EMP-0002 | I9: Anudesh Saini | J9: =COUNTIF($H$2:$H$326,A9) -> 0 | K9: None (employee record) | M9: Ankit Sharma (Data Analyst)
A10: EMP-0009 | C10: Employee | D10: Rajat Sharma | E10: Sr. AI Engineer | F10: AI | G10: 3 | H10: EMP-0002 | I10: Anudesh Saini | J10: =COUNTIF($H$2:$H$326,A10) -> 3 | K10: Manager | M10: Rajat Sharma (Sr. AI Engineer)
A11: EMP-0010 | C11: Employee | D11: Sameep Rohilla | E11: Jr. AI Engineer | F11: AI | G11: 4 | H11: EMP-0009 | I11: Rajat Sharma | J11: =COUNTIF($H$2:$H$326,A11) -> 0 | K11: None (employee record) | M11: Sameep Rohilla (Jr. AI Engineer)
A12: EMP-0011 | C12: Employee | D12: Ishan Singla | E12: Jr. ML Ops Engineer | F12: AI | G12: 4 | H12: EMP-0009 | I12: Rajat Sharma | J12: =COUNTIF($H$2:$H$326,A12) -> 0 | K12: None (employee record) | M12: Ishan Singla (Jr. ML Ops Engineer)
A13: EMP-0012 | C13: Employee | D13: Kunal Mehra | E13: Jr. AI Engineer | F13: AI | G13: 4 | H13: EMP-0009 | I13: Rajat Sharma | J13: =COUNTIF($H$2:$H$326,A13) -> 0 | K13: None (employee record) | M13: Kunal Mehra (Jr. AI Engineer)
A14: POS-0001 | C14: Vacant Position | D14: (vacant) | E14: Managing Director | F14: Product | G14: 1 | J14: =COUNTIF($H$2:$H$326,A14) -> 7 | K14: None (vacant) | L14: Vacant / unnamed position | M14: Managing Director
A15: EMP-0014 | C15: Employee | D15: Vishal Sharma | E15: Lead QA | F15: Product | G15: 2 | H15: POS-0001 | I15: Managing Director | J15: =COUNTIF($H$2:$H$326,A15) -> 1 | K15: Team Lead | M15: Vishal Sharma (Lead QA)
A16: EMP-0015 | C16: Employee | D16: Amit Kumar | E16: Sr. QA Engineer | F16: Product | G16: 3 | H16: EMP-0014 | I16: Vishal Sharma | J16: =COUNTIF($H$2:$H$326,A16) -> 4 | K16: Manager | L16: Name shared with another record - confirm identity | M16: Amit Kumar (Sr. QA Engineer)
A17: EMP-0016 | C17: Employee | D17: Pankaj Kumar | E17: QA Engineer | F17: Product | G17: 4 | H17: EMP-0015 | I17: Amit Kumar | J17: =COUNTIF($H$2:$H$326,A17) -> 0 | K17: None (employee record) | M17: Pankaj Kumar (QA Engineer)
A18: EMP-0017 | C18: Employee | D18: Deepti Sharma | E18: QA Engineer | F18: Product | G18: 4 | H18: EMP-0015 | I18: Amit Kumar | J18: =COUNTIF($H$2:$H$326,A18) -> 0 | K18: None (employee record) | M18: Deepti Sharma (QA Engineer)
A19: EMP-0018 | C19: Employee | D19: Navdeep Thakur | E19: QA Engineer | F19: Product | G19: 4 | H19: EMP-0015 | I19: Amit Kumar | J19: =COUNTIF($H$2:$H$326,A19) -> 0 | K19: None (employee record) | M19: Navdeep Thakur (QA Engineer)
A20: EMP-0019 | C20: Employee | D20: Vipul Mahajan | E20: QA Engineer | F20: Product | G20: 4 | H20: EMP-0015 | I20: Amit Kumar | J20: =COUNTIF($H$2:$H$326,A20) -> 0 | K20: None (employee record) | M20: Vipul Mahajan (QA Engineer)
A21: EMP-0020 | C21: Employee | D21: Deepinder Singh | E21: Sr. Project Manager | F21: Product | G21: 2 | H21: POS-0001 | I21: Managing Director | J21: =COUNTIF($H$2:$H$326,A21) -> 16 | K21: Manager | M21: Deepinder Singh (Sr. Project Manager)
A22: EMP-0021 | C22: Employee | D22: Rajan Kumar | E22: Project Manager | F22: Product | G22: 3 | H22: EMP-0020 | I22: Deepinder Singh | J22: =COUNTIF($H$2:$H$326,A22) -> 1 | K22: Manager | M22: Rajan Kumar (Project Manager)
A23: EMP-0022 | C23: Employee | D23: Geetankshi | E23: Associate Project Coordinator | F23: Product | G23: 4 | H23: EMP-0021 | I23: Rajan Kumar | J23: =COUNTIF($H$2:$H$326,A23) -> 0 | K23: None (employee record) | L23: Single name only - add surname | M23: Geetankshi (Associate Project coordinater)
A24: EMP-0023 | C24: Employee | D24: Sparsh Choudhary | E24: Sr. Software Engineer | F24: Product | G24: 3 | H24: EMP-0020 | I24: Deepinder Singh | J24: =COUNTIF($H$2:$H$326,A24) -> 0 | K24: None (employee record) | M24: Sparsh Choudhary (Sr. Software Engineer)
A25: EMP-0024 | C25: Employee | D25: Sumit Roy | E25: Associate Product Manager | F25: Product | G25: 3 | H25: EMP-0020 | I25: Deepinder Singh | J25: =COUNTIF($H$2:$H$326,A25) -> 5 | K25: Manager | M25: Sumit Roy (Associate Product Manager)
A26: EMP-0025 | C26: Employee | D26: Manisha Kumari | E26: Business Analyst | F26: Product | G26: 4 | H26: EMP-0024 | I26: Sumit Roy | J26: =COUNTIF($H$2:$H$326,A26) -> 0 | K26: None (employee record) | M26: Manisha Kumari (Business Analyst)
A27: EMP-0026 | C27: Employee | D27: Sukriti | E27: Business Analyst | F27: Product | G27: 4 | H27: EMP-0024 | I27: Sumit Roy | J27: =COUNTIF($H$2:$H$326,A27) -> 0 | K27: None (employee record) | L27: Single name only - add surname | M27: Sukriti (Business Analyst)
A28: EMP-0027 | C28: Employee | D28: Aryan Raj | E28: Business Analyst | F28: Product | G28: 4 | H28: EMP-0024 | I28: Sumit Roy | J28: =COUNTIF($H$2:$H$326,A28) -> 0 | K28: None (employee record) | M28: Aryan Raj (Business Analyst)
A29: EMP-0028 | C29: Employee | D29: Siddhant Sharma | E29: Team Lead-API | F29: Product | G29: 4 | H29: EMP-0024 | I29: Sumit Roy | J29: =COUNTIF($H$2:$H$326,A29) -> 0 | K29: None (employee record) | M29: Siddhant Sharma (Team Lead-API)
A30: EMP-0029 | C30: Employee | D30: Saurav Sharma | E30: API Integration Analyst | F30: Product | G30: 4 | H30: EMP-0024 | I30: Sumit Roy | J30: =COUNTIF($H$2:$H$326,A30) -> 2 | K30: Manager | M30: Saurav Sharma (API Integration Analyst)
A31: EMP-0030 | C31: Employee | D31: Avinash Rai | E31: API Support & Tech. Analyst | F31: Product | G31: 5 | H31: EMP-0029 | I31: Saurav Sharma | J31: =COUNTIF($H$2:$H$326,A31) -> 0 | K31: None (employee record) | L31: Chart text malformed (fixed) | M31: Avinash Rai (API Support & Tech. Analyst))
A32: EMP-0031 | C32: Employee | D32: Ashok Sharma | E32: API Support & Tech. Analyst | F32: Product | G32: 5 | H32: EMP-0029 | I32: Saurav Sharma | J32: =COUNTIF($H$2:$H$326,A32) -> 0 | K32: None (employee record) | L32: Chart text malformed (fixed) | M32: Ashok Sharma (API Support & Tech. Analyst))
A33: EMP-0032 | C33: Employee | D33: Ravi Beniwal | E33: Software Engineer | F33: Product | G33: 3 | H33: EMP-0020 | I33: Deepinder Singh | J33: =COUNTIF($H$2:$H$326,A33) -> 0 | K33: None (employee record) | M33: Ravi Beniwal (Software Engineer)
A34: EMP-0033 | C34: Employee | D34: Rakhi | E34: Sr. Software Engineer | F34: Product | G34: 3 | H34: EMP-0020 | I34: Deepinder Singh | J34: =COUNTIF($H$2:$H$326,A34) -> 0 | K34: None (employee record) | L34: Single name only - add surname | M34: Rakhi (Sr. Software Engineer)
A35: EMP-0034 | C35: Employee | D35: Lucky Bawa | E35: Sr. Software Engineer | F35: Product | G35: 3 | H35: EMP-0020 | I35: Deepinder Singh | J35: =COUNTIF($H$2:$H$326,A35) -> 0 | K35: None (employee record) | M35: Lucky Bawa (Sr. Software Engineer)
A36: EMP-0035 | C36: Employee | D36: Virendra Nishad | E36: Software Engineer | F36: Product | G36: 3 | H36: EMP-0020 | I36: Deepinder Singh | J36: =COUNTIF($H$2:$H$326,A36) -> 0 | K36: None (employee record) | M36: Virendra Nishad (Software Engineer)
A37: EMP-0036 | C37: Employee | D37: Pawan Kumar | E37: Software Engineer | F37: Product | G37: 3 | H37: EMP-0020 | I37: Deepinder Singh | J37: =COUNTIF($H$2:$H$326,A37) -> 0 | K37: None (employee record) | L37: Name shared with another record - confirm identity | M37: Pawan Kumar (Sofwtare Engineer)
A38: EMP-0037 | C38: Employee | D38: Ankush | E38: Sr. Software Engineer | F38: Product | G38: 3 | H38: EMP-0020 | I38: Deepinder Singh | J38: =COUNTIF($H$2:$H$326,A38) -> 0 | K38: None (employee record) | L38: Single name only - add surname | M38: Ankush (Sr. Software Engineer)
A39: EMP-0038 | C39: Employee | D39: Muskan | E39: Software Engineer | F39: Product | G39: 3 | H39: EMP-0020 | I39: Deepinder Singh | J39: =COUNTIF($H$2:$H$326,A39) -> 0 | K39: None (employee record) | L39: Name shared with another record - confirm identity; Single name only - add surname | M39: Muskan (Sofwate Engineer)
A40: EMP-0039 | C40: Employee | D40: Avinash | E40: Software Engineer | F40: Product | G40: 3 | H40: EMP-0020 | I40: Deepinder Singh | J40: =COUNTIF($H$2:$H$326,A40) -> 0 | K40: None (employee record) | L40: Single name only - add surname | M40: Avinash (Software Engineer)
A41: EMP-0040 | C41: Employee | D41: Kartik Sharma | E41: Software Engineer | F41: Product | G41: 3 | H41: EMP-0020 | I41: Deepinder Singh | J41: =COUNTIF($H$2:$H$326,A41) -> 0 | K41: None (employee record) | M41: Kartik Sharma (Software Engineer)
A42: EMP-0041 | C42: Employee | D42: Ankit | E42: Software Engineer | F42: Product | G42: 3 | H42: EMP-0020 | I42: Deepinder Singh | J42: =COUNTIF($H$2:$H$326,A42) -> 0 | K42: None (employee record) | L42: Name shared with another record - confirm identity; Single name only - add surname | M42: Ankit (Software Engineer)
A43: EMP-0042 | C43: Employee | D43: Shivam | E43: Software Engineer | F43: Product | G43: 3 | H43: EMP-0020 | I43: Deepinder Singh | J43: =COUNTIF($H$2:$H$326,A43) -> 0 | K43: None (employee record) | L43: Single name only - add surname | M43: Shivam (Software Engineer)
A44: EMP-0043 | C44: Employee | D44: Paramjit Singh | E44: Word Press Developer | F44: Product | G44: 3 | H44: EMP-0020 | I44: Deepinder Singh | J44: =COUNTIF($H$2:$H$326,A44) -> 0 | K44: None (employee record) | M44: Paramjit Singh(Word Press Developer)
A45: EMP-0044 | C45: Employee | D45: Mayank Kumar | E45: Software Engineer | F45: Product | G45: 3 | H45: EMP-0020 | I45: Deepinder Singh | J45: =COUNTIF($H$2:$H$326,A45) -> 0 | K45: None (employee record) | M45: Mayank Kumar (Software Engineer)
A46: EMP-0045 | C46: Employee | D46: Randhir Kumar | E46: Sr. Project Manager | F46: Product | G46: 2 | H46: POS-0001 | I46: Managing Director | J46: =COUNTIF($H$2:$H$326,A46) -> 2 | K46: Manager | M46: Randhir Kumar (Sr. Project Manager)
A47: EMP-0046 | C47: Employee | D47: Jatin Vashisht | E47: iOS Manager | F47: Product | G47: 3 | H47: EMP-0045 | I47: Randhir Kumar | J47: =COUNTIF($H$2:$H$326,A47) -> 5 | K47: Manager | L47: Chart text malformed (fixed) | M47: Jatin Vashisht (iOS Manager:
A48: EMP-0047 | C48: Employee | D48: Akshay A Walia | E48: Sr. Software Engineer | F48: Product | G48: 4 | H48: EMP-0046 | I48: Jatin Vashisht | J48: =COUNTIF($H$2:$H$326,A48) -> 0 | K48: None (employee record) | M48: Akshay A Walia (Sr. Software Engineer)
A49: EMP-0048 | C49: Employee | D49: Saksham | E49: Software Engineer | F49: Product | G49: 4 | H49: EMP-0046 | I49: Jatin Vashisht | J49: =COUNTIF($H$2:$H$326,A49) -> 0 | K49: None (employee record) | L49: Single name only - add surname | M49: Saksham (Software Engineer)
A50: EMP-0049 | C50: Employee | D50: Vinay Dhayani | E50: Software Engineer | F50: Product | G50: 4 | H50: EMP-0046 | I50: Jatin Vashisht | J50: =COUNTIF($H$2:$H$326,A50) -> 0 | K50: None (employee record) | M50: Vinay Dhayani (Software Engineer)
A51: EMP-0050 | C51: Employee | D51: Akash Bansal | E51: Software Engineer | F51: Product | G51: 4 | H51: EMP-0046 | I51: Jatin Vashisht | J51: =COUNTIF($H$2:$H$326,A51) -> 1 | K51: Manager | L51: Chart text malformed (fixed) | M51: Akash Bansal Software Engineer)
A52: EMP-0051 | C52: Employee | D52: Payal Dhiman | E52: Software Engineer | F52: Product | G52: 5 | H52: EMP-0050 | I52: Akash Bansal | J52: =COUNTIF($H$2:$H$326,A52) -> 0 | K52: None (employee record) | M52: Payal Dhiman (Software Engineer)
A53: EMP-0052 | C53: Employee | D53: Tushar Verma | E53: Software Engineer | F53: Product | G53: 4 | H53: EMP-0046 | I53: Jatin Vashisht | J53: =COUNTIF($H$2:$H$326,A53) -> 0 | K53: None (employee record) | L53: Chart text malformed (fixed) | M53: Tushar Verma Software Engineer)
A54: EMP-0053 | C54: Employee | D54: Rupinder Kaur | E54: Android Manager | F54: Product | G54: 3 | H54: EMP-0045 | I54: Randhir Kumar | J54: =COUNTIF($H$2:$H$326,A54) -> 5 | K54: Manager | M54: Rupinder Kaur (Android Manager)
A55: EMP-0054 | C55: Employee | D55: Keshav Bansal | E55: Sr Software Engineer | F55: Product | G55: 4 | H55: EMP-0053 | I55: Rupinder Kaur | J55: =COUNTIF($H$2:$H$326,A55) -> 0 | K55: None (employee record) | M55: Keshav Bansal (Sr Software Engineer)
A56: EMP-0055 | C56: Employee | D56: Ankit Singh | E56: Software Engineer | F56: Product | G56: 4 | H56: EMP-0053 | I56: Rupinder Kaur | J56: =COUNTIF($H$2:$H$326,A56) -> 0 | K56: None (employee record) | M56: Ankit SIngh ( Software Engineer)
A57: EMP-0056 | C57: Employee | D57: Manthan Mahajan | E57: Software Engineer | F57: Product | G57: 4 | H57: EMP-0053 | I57: Rupinder Kaur | J57: =COUNTIF($H$2:$H$326,A57) -> 0 | K57: None (employee record) | M57: Manthan Mahajan (Software Engineer)
A58: EMP-0057 | C58: Employee | D58: Sumit Kumar | E58: Sr. Software Engineer | F58: Product | G58: 4 | H58: EMP-0053 | I58: Rupinder Kaur | J58: =COUNTIF($H$2:$H$326,A58) -> 1 | K58: Manager | M58: Sumit Kumar (Sr. Software Engineer)
A59: EMP-0058 | C59: Employee | D59: Jaspreet Singh | E59: Software Engineer | F59: Product | G59: 5 | H59: EMP-0057 | I59: Sumit Kumar | J59: =COUNTIF($H$2:$H$326,A59) -> 0 | K59: None (employee record) | M59: Jaspreet Singh (Software Engineer)
A60: EMP-0059 | C60: Employee | D60: Arun Chauhan | E60: Android Developer | F60: Product | G60: 4 | H60: EMP-0053 | I60: Rupinder Kaur | J60: =COUNTIF($H$2:$H$326,A60) -> 0 | K60: None (employee record) | M60: Arun Chauhan (Android Developer)
A61: EMP-0060 | C61: Employee | D61: Kapil Kumar | E61: Sr. BA | F61: Product | G61: 2 | H61: POS-0001 | I61: Managing Director | J61: =COUNTIF($H$2:$H$326,A61) -> 6 | K61: Manager | M61: Kapil Kumar (Sr. BA)
A62: EMP-0061 | C62: Employee | D62: Deepali Mittal | E62: BA | F62: Product | G62: 3 | H62: EMP-0060 | I62: Kapil Kumar | J62: =COUNTIF($H$2:$H$326,A62) -> 1 | K62: Manager | M62: Deepali Mittal (BA)
A63: EMP-0062 | C63: Employee | D63: Hani Tomar | E63: BA | F63: Product | G63: 4 | H63: EMP-0061 | I63: Deepali Mittal | J63: =COUNTIF($H$2:$H$326,A63) -> 0 | K63: None (employee record) | M63: Hani Tomar (BA)
A64: EMP-0063 | C64: Employee | D64: Surabhi Abrol | E64: BA | F64: Product | G64: 3 | H64: EMP-0060 | I64: Kapil Kumar | J64: =COUNTIF($H$2:$H$326,A64) -> 1 | K64: Manager | M64: Surabhi Abrol (BA)
A65: EMP-0064 | C65: Employee | D65: Ansh Arora | E65: Associate BA | F65: Product | G65: 4 | H65: EMP-0063 | I65: Surabhi Abrol | J65: =COUNTIF($H$2:$H$326,A65) -> 0 | K65: None (employee record) | M65: Ansh Arora (Associate BA)
... A67: EMP-0066 | C67: Employee | D67: Rafay Saifi | E67: BA | F67: Product | G67: 3 | H67: EMP-0060 | I67: Kapil Kumar | J67: =COUNTIF($H$2:$H$326,A67) -> 0 | K67: None (employee record) | M67: Rafay Saifi (BA)
A68: EMP-0067 | C68: Employee | D68: Sonia | E68: BA | F68: Product | G68: 3 | H68: EMP-0060 | I68: Kapil Kumar | J68: =COUNTIF($H$2:$H$326,A68) -> 0 | K68: None (employee record) | L68: Single name only - add surname | M68: Sonia (BA)
A69: EMP-0068 | C69: Employee | D69: Prashant Nabaghan | E69: Sr. PM | F69: Product | G69: 3 | H69: EMP-0060 | I69: Kapil Kumar | J69: =COUNTIF($H$2:$H$326,A69) -> 1 | K69: Manager | M69: Prashant Nabaghan (Sr. PM)
A70: EMP-0069 | C70: Employee | D70: Aashish Rohhidas | E70: BA | F70: Product | G70: 4 | H70: EMP-0068 | I70: Prashant Nabaghan | J70: =COUNTIF($H$2:$H$326,A70) -> 0 | K70: None (employee record) | M70: Aashish Rohhidas (BA)
A71: EMP-0070 | C71: Employee | D71: Parvinder Singh Chopra | E71: Solution Architect | F71: Product | G71: 2 | H71: POS-0001 | I71: Managing Director | J71: =COUNTIF($H$2:$H$326,A71) -> 4 | K71: Manager | M71: Parvinder Singh Chopra (Solution Architech)
A72: EMP-0071 | C72: Employee | D72: Gurpreet Singh | E72: Project Lead | F72: Product | G72: 3 | H72: EMP-0070 | I72: Parvinder Singh Chopra | J72: =COUNTIF($H$2:$H$326,A72) -> 0 | K72: None (employee record) | L72: Name shared with another record - confirm identity | M72: Gurpreet Singh (Project Lead)
A73: EMP-0072 | C73: Employee | D73: Chhatarshal Singh | E73: Team Lead Developer | F73: Product | G73: 3 | H73: EMP-0070 | I73: Parvinder Singh Chopra | J73: =COUNTIF($H$2:$H$326,A73) -> 6 | K73: Team Lead | M73: Chhatarshal Singh (Team Lead Developer)
A74: EMP-0073 | C74: Employee | D74: Kamal Kumar | E74: Software Engineer | F74: Product | G74: 4 | H74: EMP-0072 | I74: Chhatarshal Singh | J74: =COUNTIF($H$2:$H$326,A74) -> 0 | K74: None (employee record) | M74: Kamal Kumar (Software Engineer)
A75: EMP-0074 | C75: Employee | D75: Preeti Thakur | E75: Software Engineer | F75: Product | G75: 4 | H75: EMP-0072 | I75: Chhatarshal Singh | J75: =COUNTIF($H$2:$H$326,A75) -> 0 | K75: None (employee record) | M75: Preeti Thakur (Software Engineer)
A76: EMP-0075 | C76: Employee | D76: Rohit Chauhan | E76: Software Engineer | F76: Product | G76: 4 | H76: EMP-0072 | I76: Chhatarshal Singh | J76: =COUNTIF($H$2:$H$326,A76) -> 0 | K76: None (employee record) | M76: Rohit Chauhan (Software Engineer)
A77: EMP-0076 | C77: Employee | D77: Savita | E77: Software Engineer | F77: Product | G77: 4 | H77: EMP-0072 | I77: Chhatarshal Singh | J77: =COUNTIF($H$2:$H$326,A77) -> 0 | K77: None (employee record) | L77: Single name only - add surname | M77: Savita (Software Engineer)
A78: EMP-0077 | C78: Employee | D78: Puneet Sharma | E78: Software Engineer | F78: Product | G78: 4 | H78: EMP-0072 | I78: Chhatarshal Singh | J78: =COUNTIF($H$2:$H$326,A78) -> 0 | K78: None (employee record) | M78: Puneet Sharma (Software Engineer)
A79: EMP-0078 | C79: Employee | D79: Rupanshi Bhandari | E79: Software Engineer | F79: Product | G79: 4 | H79: EMP-0072 | I79: Chhatarshal Singh | J79: =COUNTIF($H$2:$H$326,A79) -> 0 | K79: None (employee record) | L79: Chart text malformed (fixed) | M79: Rupanshi Bhandari ((Software Engineer)
A80: EMP-0079 | C80: Employee | D80: Mukesh Kumar | E80: Dev Ops Engineer | F80: Product | G80: 3 | H80: EMP-0070 | I80: Parvinder Singh Chopra | J80: =COUNTIF($H$2:$H$326,A80) -> 0 | K80: None (employee record) | L80: Name shared with another record - confirm identity | M80: Mukesh Kumar (Dev Ops Engineer)
A81: EMP-0080 | C81: Employee | D81: Jyoti | E81: Sr. Devops | F81: Product | G81: 3 | H81: EMP-0070 | I81: Parvinder Singh Chopra | J81: =COUNTIF($H$2:$H$326,A81) -> 0 | K81: None (employee record) | L81: Single name only - add surname | M81: Jyoti (Sr. Devops)
A82: EMP-0081 | C82: Employee | D82: Pradeep Thakur | E82: Lead UI/UX Designer | F82: Product | G82: 2 | H82: POS-0001 | I82: Managing Director | J82: =COUNTIF($H$2:$H$326,A82) -> 3 | K82: Team Lead | M82: Pradeep Thakur (Lead UI/UX Designer)
A83: EMP-0082 | C83: Employee | D83: Sachin Barnwal | E83: UI/UX Designer | F83: Product | G83: 3 | H83: EMP-0081 | I83: Pradeep Thakur | J83: =COUNTIF($H$2:$H$326,A83) -> 0 | K83: None (employee record) | M83: Sachin Barnwal (UI/UX Designer)
A84: EMP-0083 | C84: Employee | D84: Maninder Singh | E84: Sr. UI/UX Designer | F84: Product | G84: 3 | H84: EMP-0081 | I84: Pradeep Thakur | J84: =COUNTIF($H$2:$H$326,A84) -> 0 | K84: None (employee record) | L84: Name shared with another record - confirm identity | M84: Maninder Singh (Sr. UI/UX Designer)
A85: EMP-0084 | C85: Employee | D85: Harsh | E85: UI/UX Designer | F85: Product | G85: 3 | H85: EMP-0081 | I85: Pradeep Thakur | J85: =COUNTIF($H$2:$H$326,A85) -> 0 | K85: None (employee record) | L85: Single name only - add surname | M85: Harsh (UI/UX Designer)
A86: EMP-0085 | C86: Employee | D86: Balneet Birah | E86: VP-HR | F86: HR | G86: 1 | J86: =COUNTIF($H$2:$H$326,A86) -> 2 | K86: HOD | M86: Balneet Birah (VP-HR)
A87: EMP-0086 | C87: Employee | D87: Rakesh Guleria | E87: AVP-HR | F87: HR | G87: 2 | H87: EMP-0085 | I87: Balneet Birah | J87: =COUNTIF($H$2:$H$326,A87) -> 7 | K87: Manager | M87: Rakesh Guleria (AVP-HR)
A88: EMP-0087 | C88: Employee | D88: Hidayat Khan | E88: AM - HR OPS | F88: HR | G88: 3 | H88: EMP-0086 | I88: Rakesh Guleria | J88: =COUNTIF($H$2:$H$326,A88) -> 1 | K88: Manager | M88: Hidayat Khan (AM - HR OPS)
A89: POS-0088 | C89: Vacant Position | D89: (vacant) | E89: Vacant position (empty box in chart) | F89: HR | G89: 4 | H89: EMP-0087 | I89: Hidayat Khan | J89: =COUNTIF($H$2:$H$326,A89) -> 0 | K89: None (vacant) | L89: Vacant / unnamed position
A90: EMP-0089 | C90: Employee | D90: Parul | E90: CSR Manager | F90: HR | G90: 3 | H90: EMP-0086 | I90: Rakesh Guleria | J90: =COUNTIF($H$2:$H$326,A90) -> 0 | K90: None (employee record) | L90: Single name only - add surname | M90: Parul (CSR Manager)
A91: EMP-0090 | C91: Employee | D91: Robin Sharma | E91: TL OPS | F91: HR | G91: 3 | H91: EMP-0086 | I91: Rakesh Guleria | J91: =COUNTIF($H$2:$H$326,A91) -> 0 | K91: None (employee record) | M91: Robin Sharma (TL OPS)
A92: EMP-0091 | C92: Employee | D92: Amrit Kaur | E92: Team Lead | F92: HR | G92: 3 | H92: EMP-0086 | I92: Rakesh Guleria | J92: =COUNTIF($H$2:$H$326,A92) -> 0 | K92: None (employee record) | M92: Amrit Kaur (Team Lead)
A93: EMP-0092 | C93: Employee | D93: Prabhleen Kaur | E93: Sr. TA | F93: HR | G93: 3 | H93: EMP-0086 | I93: Rakesh Guleria | J93: =COUNTIF($H$2:$H$326,A93) -> 0 | K93: None (employee record) | M93: Prabhleen Kaur (Sr. TA)
A94: EMP-0093 | C94: Employee | D94: Himani Sharma | E94: AM-TA | F94: HR | G94: 3 | H94: EMP-0086 | I94: Rakesh Guleria | J94: =COUNTIF($H$2:$H$326,A94) -> 1 | K94: Manager | M94: Himani Sharma (AM-TA)
A95: EMP-0094 | C95: Employee | D95: Jitender Thakur | E95: TA | F95: HR | G95: 4 | H95: EMP-0093 | I95: Himani Sharma | J95: =COUNTIF($H$2:$H$326,A95) -> 0 | K95: None (employee record) | L95: Name shared with another record - confirm identity | M95: Jitender Thakur (TA)
A96: EMP-0095 | C96: Employee | D96: Nidhi Zulka | E96: HR Manager:MB | F96: HR | G96: 3 | H96: EMP-0086 | I96: Rakesh Guleria | J96: =COUNTIF($H$2:$H$326,A96) -> 0 | K96: None (employee record) | M96: Nidhi Zulka (HR Manager:MB)
A97: EMP-0096 | C97: Employee | D97: Deepjot Tiwari | E97: Manager L&D | F97: HR | G97: 2 | H97: EMP-0085 | I97: Balneet Birah | J97: =COUNTIF($H$2:$H$326,A97) -> 1 | K97: Manager | M97: Deepjot Tiwari ( Manager L&D)
A98: EMP-0097 | C98: Employee | D98: Aman Thapa | E98: Executive L&D | F98: HR | G98: 3 | H98: EMP-0096 | I98: Deepjot Tiwari | J98: =COUNTIF($H$2:$H$326,A98) -> 0 | K98: None (employee record) | M98: Aman Thapa ( Executive L&D)
A99: EMP-0098 | C99: Employee | D99: Aunj Ohri | E99: VP Accounts | F99: Accounts | G99: 1 | J99: =COUNTIF($H$2:$H$326,A99) -> 2 | K99: HOD | M99: Aunj Ohri (VP Accounts)
A100: EMP-0099 | C100: Employee | D100: Pushpinder Singh | E100: AVP - Accounts | F100: Accounts | G100: 2 | H100: EMP-0098 | I100: Aunj Ohri | J100: =COUNTIF($H$2:$H$326,A100) -> 5 | K100: Manager | M100: Pushpinder Singh (AVP - Accounts)
A101: EMP-0100 | C101: Employee | D101: Ravi Kumar | E101: AM- Accounts | F101: Accounts | G101: 3 | H101: EMP-0099 | I101: Pushpinder Singh | J101: =COUNTIF($H$2:$H$326,A101) -> 3 | K101: Manager | M101: Ravi Kumar (AM- Accounts)
...

Sheet Name_Collisions
A1: Name | B1: Record ID | C1: Designation | D1: Department | E1: Reporting Manager | F1: Likely same person? | G1: Resolution (fill)
A2: Amit Kumar | B2: EMP-0015 | C2: Sr. QA Engineer | D2: Product | E2: Vishal Sharma | F2: No - different role/department
A3: Amit Kumar | B3: EMP-0266 | C3: Manager | D3: Sales | E3: Gurjot Singh | F3: No - different role/department
A4: Amritpal Singh | B4: EMP-0240 | C4: CS Executive | D4: Client Support | E4: Neeru Arya | F4: Possibly duplicate entry
A5: Amritpal Singh | B5: EMP-0252 | C5: CS Executive | D5: Client Support | E5: Angel Sharma | F5: Possibly duplicate entry
A6: Ankit | B6: EMP-0041 | C6: Software Engineer | D6: Product | E6: Deepinder Singh | F6: No - different role/department
A7: Ankit | B7: EMP-0223 | C7: CS Executive | D7: Client Support | E7: Ramandeep Kaur | F7: No - different role/department
A8: Gurpreet Singh | B8: EMP-0071 | C8: Project Lead | D8: Product | E8: Parvinder Singh Chopra | F8: No - different role/department
A9: Gurpreet Singh | B9: EMP-0161 | C9: Manager | D9: IT | E9: Patel Rajesh | F9: No - different role/department
A10: Hardeep Singh | B10: EMP-0198 | C10: AM Compliance | D10: Compliance | E10: Akanksha Chhabra | F10: No - different role/department
A11: Hardeep Singh | B11: EMP-0250 | C11: CS Executive | D11: Client Support | E11: Angel Sharma | F11: No - different role/department
A12: Jitender Thakur | B12: EMP-0094 | C12: TA | D12: HR | E12: Himani Sharma | F12: No - different role/department
A13: Jitender Thakur | B13: EMP-0179 | C13: BO Executive | D13: Operations & BO | E13: Kanav Verma | F13: No - different role/department
... A24: Pawan Kumar | B24: EMP-0036 | C24: Software Engineer | D24: Product | E24: Deepinder Singh | F24: No - different role/department
A25: Pawan Kumar | B25: EMP-0109 | C25: AVP-Operations | D25: Demat | F25: No - different role/department
A26: Pawan Kumar | B26: EMP-0109 | C26: AVP-Operations | D26: Operations & BO | F26: No - different role/department
A27: Pawan Kumar | B27: EMP-0109 | C27: AVP-Operations | D27: Compliance | F27: No - different role/department
A28: Rajesh Kumar | B28: EMP-0155 | C28: Sr. SEO Specialist | D28: Digital Marketing | E28: Ramneek | F28: No - different role/department
A29: Rajesh Kumar | B29: EMP-0280 | C29: Sr. Manager | D29: Sales | E29: Gurjot Singh | F29: No - different role/department
A30: Ramandeep Kaur | B30: EMP-0222 | C30: Sr. CS Executive | D30: Client Support | E30: Sahil Sharma | F30: No - different role/department
A31: Ramandeep Kaur | B31: EMP-0283 | C31: Sales Executive | D31: Sales | E31: Sakshi Sharma | F31: No - different role/department
A32: Sakshi Sharma | B32: EMP-0258 | C32: CS Executive | D32: jUMPP CS & Sales | E32: Priyanka Rana | F32: No - different role/department
A33: Sakshi Sharma | B33: EMP-0281 | C33: Team Lead | D33: Sales | E33: Rajesh Kumar | F33: No - different role/department
A34: Salim Khan | B34: EMP-0206 | C34: RMS Executive | D34: RMS & Dealer | E34: Naveen Kumar | F34: Possibly duplicate entry
A35: Salim Khan | B35: EMP-0208 | C35: RMS Executive | D35: RMS & Dealer | E35: Naveen Kumar | F35: Possibly duplicate entry

Sheet Departments
A1: Department | B1: Head Record ID | C1: Head | D1: Headcount (employees) | E1: Vacant Positions | F1: Proposed Category | G1: Tracker Name Aliases | H1: Notes
A2: Sales | B2: EMP-0265 | C2: Gurjot Singh | D2: =COUNTIFS(Employee_Master!$F:$F,A2,Employee_Master!$C:$C,"Employee") -> 37 | E2: =COUNTIFS(Employee_Master!$F:$F,A2,Employee_Master!$C:$C,"Vacant Position") -> 0 | F2: Core Revenue | G2: Sales | H2: Direct revenue targets.
A3: Insurance | B3: POS-0310 | C3: Head Insurance | D3: =COUNTIFS(Employee_Master!$F:$F,A3,Employee_Master!$C:$C,"Employee") -> 4 | E3: =COUNTIFS(Employee_Master!$F:$F,A3,Employee_Master!$C:$C,"Vacant Position") -> 1 | F3: Core Revenue | H3: Insurance sales targets.
A4: NBFC | B4: EMP-0302 | C4: Sachin Ghambir | D4: =COUNTIFS(Employee_Master!$F:$F,A4,Employee_Master!$C:$C,"Employee") -> 8 | E4: =COUNTIFS(Employee_Master!$F:$F,A4,Employee_Master!$C:$C,"Vacant Position") -> 0 | F4: Core Revenue | H4: Sales sub-team is Core Revenue; Credit, Collection and Ops sub-teams should be overridden to Revenue-Enabling at team level.
A5: jUMPP CS & Sales | B5: EMP-0254 | C5: Kapil Sachdev | D5: =COUNTIFS(Employee_Master!$F:$F,A5,Employee_Master!$C:$C,"Employee") -> 11 | E5: =COUNTIFS(Employee_Master!$F:$F,A5,Employee_Master!$C:$C,"Vacant Position") -> 0 | F5: Core Revenue | H5: Sales team = Core Revenue; CS team overridden to Customer Service.
A6: Product | B6: POS-0001 | C6: Managing Director | D6: =COUNTIFS(Employee_Master!$F:$F,A6,Employee_Master!$C:$C,"Employee") -> 71 | E6: =COUNTIFS(Employee_Master!$F:$F,A6,Employee_Master!$C:$C,"Vacant Position") -> 1 | F6: Revenue-Enabling | G6: Product | H6: Delivery on time is the primary measure.
A7: AI | B7: POS-0001 | C7: Managing Director | D7: =COUNTIFS(Employee_Master!$F:$F,A7,Employee_Master!$C:$C,"Employee") -> 11 | E7: =COUNTIFS(Employee_Master!$F:$F,A7,Employee_Master!$C:$C,"Vacant Position") -> 1 | F7: Revenue-Enabling
A8: Operations & BO | B8: EMP-0109 | C8: Pawan Kumar | D8: =COUNTIFS(Employee_Master!$F:$F,A8,Employee_Master!$C:$C,"Employee") -> 29 | E8: =COUNTIFS(Employee_Master!$F:$F,A8,Employee_Master!$C:$C,"Vacant Position") -> 0 | F8: Revenue-Enabling | G8: Operations; Back ofc & Operations
A9: Demat | B9: EMP-0109 | C9: Pawan Kumar | D9: =COUNTIFS(Employee_Master!$F:$F,A9,Employee_Master!$C:$C,"Employee") -> 8 | E9: =COUNTIFS(Employee_Master!$F:$F,A9,Employee_Master!$C:$C,"Vacant Position") -> 0 | F9: Revenue-Enabling
A10: RMS & Dealer | B10: EMP-0203 | C10: Ayushman Dey | D10: =COUNTIFS(Employee_Master!$F:$F,A10,Employee_Master!$C:$C,"Employee") -> 16 | E10: =COUNTIFS(Employee_Master!$F:$F,A10,Employee_Master!$C:$C,"Vacant Position") -> 0 | F10: Revenue-Enabling | H10: Dealer sub-team may be moved to Core Revenue if dealers carry brokerage targets.
A11: Compliance | B11: EMP-0109 | C11: Pawan Kumar | D11: =COUNTIFS(Employee_Master!$F:$F,A11,Employee_Master!$C:$C,"Employee") -> 6 | E11: =COUNTIFS(Employee_Master!$F:$F,A11,Employee_Master!$C:$C,"Vacant Position") -> 1 | F11: Revenue-Enabling | G11: Compliance | H11: Compliance is the core output, so the 20% compliance weight fits.
A12: Digital Marketing | B12: EMP-0117 | C12: Ramneek | D12: =COUNTIFS(Employee_Master!$F:$F,A12,Employee_Master!$C:$C,"Employee") -> 40 | E12: =COUNTIFS(Employee_Master!$F:$F,A12,Employee_Master!$C:$C,"Vacant Position") -> 0 | F12: Revenue-Enabling | H12: Acquisition/brand targets feed Achievement %.
A13: Client Support | B13: EMP-0219 | C13: Kapil Abrol | D13: =COUNTIFS(Employee_Master!$F:$F,A13,Employee_Master!$C:$C,"Employee") -> 35 | E13: =COUNTIFS(Employee_Master!$F:$F,A13,Employee_Master!$C:$C,"Vacant Position") -> 0 | F13: Customer Service (new) | G13: Customer Support | H13: CSAT is the primary measure; no original category weighted it correctly.
A14: IT | B14: EMP-0157 | C14: Patel Rajesh | D14: =COUNTIFS(Employee_Master!$F:$F,A14,Employee_Master!$C:$C,"Employee") -> 12 | E14: =COUNTIFS(Employee_Master!$F:$F,A14,Employee_Master!$C:$C,"Vacant Position") -> 0 | F14: Support | G14: IT / Tech
A15: HR | B15: EMP-0085 | C15: Balneet Birah | D15: =COUNTIFS(Employee_Master!$F:$F,A15,Employee_Master!$C:$C,"Employee") -> 12 | E15: =COUNTIFS(Employee_Master!$F:$F,A15,Employee_Master!$C:$C,"Vacant Position") -> 1 | F15: Support | G15: Human Resources; Learning & Development | H15: L&D is a sub-team under HR.
A16: Accounts | B16: EMP-0098 | C16: Aunj Ohri | D16: =COUNTIFS(Employee_Master!$F:$F,A16,Employee_Master!$C:$C,"Employee") -> 11 | E16: =COUNTIFS(Employee_Master!$F:$F,A16,Employee_Master!$C:$C,"Vacant Position") -> 0 | F16: Support | G16: Finance
A17: Admin | B17: EMP-0315 | C17: Dheeraj Dhiwan | D17: =COUNTIFS(Employee_Master!$F:$F,A17,Employee_Master!$C:$C,"Employee") -> 6 | E17: =COUNTIFS(Employee_Master!$F:$F,A17,Employee_Master!$C:$C,"Vacant Position") -> 0 | F17: Support
A18: Front Desk | B18: POS-0321 | C18: Department Head (not named in chart) | D18: =COUNTIFS(Employee_Master!$F:$F,A18,Employee_Master!$C:$C,"Employee") -> 2 | E18: =COUNTIFS(Employee_Master!$F:$F,A18,Employee_Master!$C:$C,"Vacant Position") -> 1 | F18: Support | H18: No head named in chart.
A19: Total | D19: =SUM(D2:D18) -> 319 | E19: =SUM(E2:E18) -> 6
A20: Note: Pawan Kumar (EMP-0109) heads Demat, Operations & BO and Compliance, and the Managing Director heads Product and AI, so the same head ID appears more than once. Headcount counts rows per department; a person who appears in two department charts is counted in both.

Sheet Category_Weights
A1: Metric | B1: Core Revenue | C1: Revenue-Enabling | D1: Support | E1: Customer Service (new) | F1: Change vs R&R_Parameters_2
A2: On-Time Rate | B2: 0.2 | C2: 0.3 | D2: 0.2 | E2: 0.2
A3: Achievement % | B3: 0.3 | C3: 0.25 | D3: 0 | E3: 0.15
A4: Compliance | B4: 0 | C4: 0.2 | D4: 0.1 | E4: 0.1
A5: CSAT | B5: 0.25 | C5: 0 | D5: 0 | E5: 0.3
A6: Quality | B6: 0.15 | C6: 0.15 | D6: 0.25 | E6: 0.25
A7: Productivity | B7: 0 | C7: 0 | D7: 0 | E7: 0 | F7: Defined but unweighted in all categories; used as an R&R tie-breaker and award input. Set a weight here to activate it.
A8: Collaboration | B8: 0.1 | C8: 0.1 | D8: 0.25 | E8: 0 | F8: "Culture" in Core Revenue is mapped to Collaboration (Culture was never defined).
A9: Innovation & Process Improvement | B9: 0 | C9: 0 | D9: 0.2 | E9: 0
A10: Total (must be 100%) | B10: =SUM(B2:B9) -> 1 | C10: =SUM(C2:C9) -> 1 | D10: =SUM(D2:D9) -> 1 | E10: =SUM(E2:E9) -> 1
A11: Check | B11: =IF(ROUND(B10,4)=1,"OK","FIX") -> OK | C11: =IF(ROUND(C10,4)=1,"OK","FIX") -> OK | D11: =IF(ROUND(D10,4)=1,"OK","FIX") -> OK | E11: =IF(ROUND(E10,4)=1,"OK","FIX") -> OK
A13: The 60% Quantifiable / 40% Qualitative split in R_R_Parameters_2 is retired: its listed sub-weights summed to 75-100% and 50-65%. Category weights above are the single source of truth. Customer Service is a proposed new category and needs management approval.

Sheet Tracker_Cleaned
A1: Src Row | B1: Project ID | C1: Project | D1: Task ID | E1: Task / Deliverable | F1: Assignee (as typed) | G1: Emp ID | H1: Assignee (resolved) | I1: Match Note | J1: Assignment Role | K1: Contribution % | L1: Department | M1: Project Owner | N1: Priority | O1: Start Date | P1: Target Date | Q1: Completed Date | R1: Original Status | S1: Mapped Status | T1: Timing (auto) | U1: Blocker Type | V1: Delay Reason | W1: Validated? | X1: Excludable if Late? | Y1: On-Time Eligible (auto) | Z1: Data Quality Flags
A2: 4 | B2: PRJ-001 | C2: Loan Changes (Advance Salary) | D2: PRJ-001-T01 | E2: Loan Changes (Advance Salary) | F2: Sachin | G2: EMP-0082 | H2: Sachin Barnwal | I2: Context: UI/UX under Pradeep Thakur | J2: Owner | K2: 1 | L2: Product | M2: Pradeep Thakur | N2: High | O2: 46258 | P2: 46258 | Q2: 46258 | R2: Completed | S2: Completed | T2: =IF(P2="","No deadline",IF(Q2<>"",IF(Q2>P2,"Late","On time"),IF(README!$B$4>P2,"Overdue","Open"))) -> On time | Y2: =IF(AND(S2="Completed",P2<>"",Q2<>""),IF(AND(T2="Late",X2="Yes",W2="Yes"),"Excluded (validated delay)","Yes"),"No") -> Yes
A3: 5 | B3: PRJ-002 | C3: Trade.Shoonya Global Dashboard (Corporate actions) | D3: PRJ-002-T01 | E3: Trade.Shoonya Global Dashboard (Corporate actions) | F3: Sachin | G3: EMP-0082 | H3: Sachin Barnwal | I3: Context: UI/UX under Pradeep Thakur | J3: Owner | K3: 1 | L3: Product | M3: Pradeep Thakur | N3: High | O3: 46238 | P3: 46254 | Q3: 46254 | R3: Completed | S3: Completed | T3: =IF(P3="","No deadline",IF(Q3<>"",IF(Q3>P3,"Late","On time"),IF(README!$B$4>P3,"Overdue","Open"))) -> On time | Y3: =IF(AND(S3="Completed",P3<>"",Q3<>""),IF(AND(T3="Late",X3="Yes",W3="Yes"),"Excluded (validated delay)","Yes"),"No") -> Yes
A4: 6 | B4: PRJ-003 | C4: Mobile-Trade.Shoonya Global Dashboard (Corporate actions) | D4: PRJ-003-T01 | E4: Mobile-Trade.Shoonya Global Dashboard (Corporate actions) | F4: Sachin | G4: EMP-0082 | H4: Sachin Barnwal | I4: Context: UI/UX under Pradeep Thakur | J4: Owner | K4: 1 | L4: Product | M4: Pradeep Thakur | N4: High | O4: 46253 | P4: 46255 | Q4: 46255 | R4: Completed | S4: Completed | T4: =IF(P4="","No deadline",IF(Q4<>"",IF(Q4>P4,"Late","On time"),IF(README!$B$4>P4,"Overdue","Open"))) -> On time | Y4: =IF(AND(S4="Completed",P4<>"",Q4<>""),IF(AND(T4="Late",X4="Yes",W4="Yes"),"Excluded (validated delay)","Yes"),"No") -> Yes
A5: 7 | B5: PRJ-004 | C5: Shoonya R&R | D5: PRJ-004-T01 | E5: Shoonya R&R | F5: Sachin | G5: EMP-0082 | H5: Sachin Barnwal | I5: Context: UI/UX under Pradeep Thakur | J5: Owner | K5: 1 | L5: Product | M5: Pradeep Thakur | N5: High | O5: 46241 | P5: 46262 | Q5: 46242 | R5: On Hold | S5: On Hold | T5: =IF(P5="","No deadline",IF(Q5<>"",IF(Q5>P5,"Late","On time"),IF(README!$B$4>P5,"Overdue","Open"))) -> On time | U5: Management reprioritisation | V5: Working on MF | W5: Yes | X5: Yes | Y5: =IF(AND(S5="Completed",P5<>"",Q5<>""),IF(AND(T5="Late",X5="Yes",W5="Yes"),"Excluded (validated delay)","Yes"),"No") -> No | Z5: Has completed date but status is On Hold; Completed date kept for reference; not counted as completed
A6: 8 | B6: PRJ-005 | C6: Trade Shoonya: Dark theme | D6: PRJ-005-T01 | E6: Trade Shoonya: Dark theme | F6: Sachin | G6: EMP-0082 | H6: Sachin Barnwal | I6: Context: UI/UX under Pradeep Thakur | J6: Owner | K6: 1 | L6: Product | M6: Pradeep Thakur | N6: Medium | O6: 46275 | P6: 46283 | R6: On Hold | S6: On Hold | T6: =IF(P6="","No deadline",IF(Q6<>"",IF(Q6>P6,"Late","On time"),IF(README!$B$4>P6,"Overdue","Open"))) -> Overdue | U6: Management reprioritisation | V6: Working on R&R and MF | W6: Yes | X6: Yes | Y6: =IF(AND(S6="Completed",P6<>"",Q6<>""),IF(AND(T6="Late",X6="Yes",W6="Yes"),"Excluded (validated delay)","Yes"),"No") -> No
A7: 9 | B7: PRJ-006 | C7: Jumpp R&R | D7: PRJ-006-T01 | E7: Jumpp R&R | F7: Harsh | G7: EMP-0084 | H7: Harsh | I7: Context: UI/UX under Pradeep Thakur | J7: Owner | K7: 1 | L7: Product | M7: Pradeep Thakur | N7: High | O7: 46244 | P7: 46248 | R7: In Review | S7: In Review | T7: =IF(P7="","No deadline",IF(Q7<>"",IF(Q7>P7,"Late","On time"),IF(README!$B$4>P7,"Overdue","Open"))) -> Overdue | U7: Rework (own team feedback) | V7: Inernal feedback incorporated | W7: Yes | X7: No | Y7: =IF(AND(S7="Completed",P7<>"",Q7<>""),IF(AND(T7="Late",X7="Yes",W7="Yes"),"Excluded (validated delay)","Yes"),"No") -> No
A8: 10 | B8: PRJ-007 | C8: Rewards Journey UI (Milestones or Campaign) | D8: PRJ-007-T01 | E8: Rewards Journey UI (Milestones or Campaign) | F8: Harsh | G8: EMP-0084 | H8: Harsh | I8: Context: UI/UX under Pradeep Thakur | J8: Owner | K8: 1 | L8: Product | M8: Pradeep Thakur | N8: High | O8: 46254 | P8: 46258 | Q8: 46260 | R8: In Review | S8: In Review | T8: =IF(P8="","No deadline",IF(Q8<>"",IF(Q8>P8,"Late","On time"),IF(README!$B$4>P8,"Overdue","Open"))) -> Late | Y8: =IF(AND(S8="Completed",P8<>"",Q8<>""),IF(AND(T8="Late",X8="Yes",W8="Yes"),"Excluded (validated delay)","Yes"),"No") -> No | Z8: Has completed date but status is In Review; Completed date kept for reference; not counted as completed
A9: 11 | B9: PRJ-008 | C9: Digital Silver | D9: PRJ-008-T01 | E9: Digital Silver | F9: Maninder | G9: EMP-0083 | H9: Maninder Singh | I9: Context: Sr. UI/UX (not the SEO Maninder Singh) | J9: Owner | K9: 1 | L9: Product | M9: Pradeep Thakur | N9: High | O9: 46249 | P9: 46258 | R9: In Review | S9: In Review | T9: =IF(P9="","No deadline",IF(Q9<>"",IF(Q9>P9,"Late","On time"),IF(README!$B$4>P9,"Overdue","Open"))) -> Overdue | Y9: =IF(AND(S9="Completed",P9<>"",Q9<>""),IF(AND(T9="Late",X9="Yes",W9="Yes"),"Excluded (validated delay)","Yes"),"No") -> No
A10: 12 | B10: PRJ-009 | C10: Digital Silver SIP | D10: PRJ-009-T01 | E10: Digital Silver SIP | F10: Maninder | G10: EMP-0083 | H10: Maninder Singh | I10: Context: Sr. UI/UX (not the SEO Maninder Singh) | J10: Owner | K10: 1 | L10: Product | M10: Pradeep Thakur | N10: High | O10: 46250 | P10: 46259 | R10: In Review | S10: In Review | T10: =IF(P10="","No deadline",IF(Q10<>"",IF(Q10>P10,"Late","On time"),IF(README!$B$4>P10,"Overdue","Open"))) -> Overdue | Y10: =IF(AND(S10="Completed",P10<>"",Q10<>""),IF(AND(T10="Late",X10="Yes",W10="Yes"),"Excluded (validated delay)","Yes"),"No") -> No
A11: 13 | B11: PRJ-010 | C11: Digital Gold SIP | D11: PRJ-010-T01 | E11: Digital Gold SIP | F11: Maninder | G11: EMP-0083 | H11: Maninder Singh | I11: Context: Sr. UI/UX (not the SEO Maninder Singh) | J11: Owner | K11: 1 | L11: Product | M11: Pradeep Thakur | N11: High | O11: 46251 | P11: 46260 | R11: In Review | S11: In Review | T11: =IF(P11="","No deadline",IF(Q11<>"",IF(Q11>P11,"Late","On time"),IF(README!$B$4>P11,"Overdue","Open"))) -> Overdue | Y11: =IF(AND(S11="Completed",P11<>"",Q11<>""),IF(AND(T11="Late",X11="Yes",W11="Yes"),"Excluded (validated delay)","Yes"),"No") -> No
A12: 14 | B12: PRJ-011 | C12: Physical Silver | D12: PRJ-011-T01 | E12: Physical Silver | F12: Maninder | G12: EMP-0083 | H12: Maninder Singh | I12: Context: Sr. UI/UX (not the SEO Maninder Singh) | J12: Owner | K12: 1 | L12: Product | M12: Pradeep Thakur | N12: High | O12: 46252 | P12: 46261 | R12: In Review | S12: In Review | T12: =IF(P12="","No deadline",IF(Q12<>"",IF(Q12>P12,"Late","On time"),IF(README!$B$4>P12,"Overdue","Open"))) -> Overdue | Y12: =IF(AND(S12="Completed",P12<>"",Q12<>""),IF(AND(T12="Late",X12="Yes",W12="Yes"),"Excluded (validated delay)","Yes"),"No") -> No
A13: 15 | B13: PRJ-012 | C13: Physical Gold | D13: PRJ-012-T01 | E13: Physical Gold | F13: Maninder | G13: EMP-0083 | H13: Maninder Singh | I13: Context: Sr. UI/UX (not the SEO Maninder Singh) | J13: Owner | K13: 1 | L13: Product | M13: Pradeep Thakur | N13: High | O13: 46253 | P13: 46262 | R13: In Review | S13: In Review | T13: =IF(P13="","No deadline",IF(Q13<>"",IF(Q13>P13,"Late","On time"),IF(README!$B$4>P13,"Overdue","Open"))) -> Overdue | Y13: =IF(AND(S13="Completed",P13<>"",Q13<>""),IF(AND(T13="Late",X13="Yes",W13="Yes"),"Excluded (validated delay)","Yes"),"No") -> No
A14: 16 | B14: PRJ-013 | C14: Jumpp Website 1.1 | D14: PRJ-013-T01 | E14: Jumpp Website 1.1 | F14: Maninder | G14: EMP-0083 | H14: Maninder Singh | I14: Context: Sr. UI/UX (not the SEO Maninder Singh) | J14: Owner | K14: 1 | L14: Product | M14: Pradeep Thakur | N14: High | O14: 46174 | P14: 46265 | Q14: 46255 | R14: On Hold | S14: On Hold | T14: =IF(P14="","No deadline",IF(Q14<>"",IF(Q14>P14,"Late","On time"),IF(README!$B$4>P14,"Overdue","Open"))) -> On time | U14: Internal dependency (other team review) | V14: DM team feedbacks | W14: Yes | X14: Yes | Y14: =IF(AND(S14="Completed",P14<>"",Q14<>""),IF(AND(T14="Late",X14="Yes",W14="Yes"),"Excluded (validated delay)","Yes"),"No") -> No | Z14: Has completed date but status is On Hold; Completed date kept for reference; not counted as completed
A15: 17 | B15: PRJ-014 | C15: Insurance Chatbot | D15: PRJ-014-T01 | E15: Insurance Chatbot | F15: Maninder | G15: EMP-0083 | H15: Maninder Singh | I15: Context: Sr. UI/UX (not the SEO Maninder Singh) | J15: Owner | K15: 1 | L15: Product | M15: Pradeep Thakur | N15: High | O15: 46261 | P15: 46272 | R15: Ongoing | S15: In Progress | T15: =IF(P15="","No deadline",IF(Q15<>"",IF(Q15>P15,"Late","On time"),IF(README!$B$4>P15,"Overdue","Open"))) -> Overdue | Y15: =IF(AND(S15="Completed",P15<>"",Q15<>""),IF(AND(T15="Late",X15="Yes",W15="Yes"),"Excluded (validated delay)","Yes"),"No") -> No
A16: 18 | B16: PRJ-015 | C16: Shoonya Website Enhancements | D16: PRJ-015-T01 | E16: Shoonya Website Enhancements | F16: Maninder | G16: EMP-0083 | H16: Maninder Singh | I16: Context: Sr. UI/UX (not the SEO Maninder Singh) | J16: Owner | K16: 1 | L16: Product | M16: Pradeep Thakur | N16: High | O16: 46261 | P16: 46261 | R16: On Hold | S16: On Hold | T16: =IF(P16="","No deadline",IF(Q16<>"",IF(Q16>P16,"Late","On time"),IF(README!$B$4>P16,"Overdue","Open"))) -> Overdue | U16: Management reprioritisation | V16: Due to jUMPP task | W16: Yes | X16: Yes | Y16: =IF(AND(S16="Completed",P16<>"",Q16<>""),IF(AND(T16="Late",X16="Yes",W16="Yes"),"Excluded (validated delay)","Yes"),"No") -> No
A17: 19 | B17: PRJ-016 | C17: Onboarding Pan Skip Transition History UI (Need to be updated) | D17: PRJ-016-T01 | E17: Onboarding Pan Skip Transition History UI (Need to be updated) | F17: Harsh | G17: EMP-0084 | H17: Harsh | I17: Context: UI/UX under Pradeep Thakur | J17: Owner | K17: 1 | L17: Product | M17: Pradeep Thakur | N17: High | O17: 46259 | P17: 46259 | Q17: 46259 | R17: Completed | S17: Completed | T17: =IF(P17="","No deadline",IF(Q17<>"",IF(Q17>P17,"Late","On time"),IF(README!$B$4>P17,"Overdue","Open"))) -> On time | Y17: =IF(AND(S17="Completed",P17<>"",Q17<>""),IF(AND(T17="Late",X17="Yes",W17="Yes"),"Excluded (validated delay)","Yes"),"No") -> Yes
A18: 20 | B18: PRJ-017 | C18: SensAI | D18: PRJ-017-T01 | E18: SensAI | F18: Sachin | G18: EMP-0082 | H18: Sachin Barnwal | I18: Context: UI/UX under Pradeep Thakur | J18: Owner | K18: 1 | L18: Product | M18: Pradeep Thakur | N18: High | O18: 46245 | P18: 46248 | Q18: 46266 | R18: On Hold | S18: On Hold | T18: =IF(P18="","No deadline",IF(Q18<>"",IF(Q18>P18,"Late","On time"),IF(README!$B$4>P18,"Overdue","Open"))) -> Late | U18: Management reprioritisation | V18: Working on R&R and MF | W18: Yes | X18: Yes | Y18: =IF(AND(S18="Completed",P18<>"",Q18<>""),IF(AND(T18="Late",X18="Yes",W18="Yes"),"Excluded (validated delay)","Yes"),"No") -> No | Z18: Has completed date but status is On Hold; Completed date kept for reference; not counted as completed
A19: 21 | B19: PRJ-018 | C19: Shoonya Bonds- Entry points and graphics UI | D19: PRJ-018-T01 | E19: Shoonya Bonds- Entry points and graphics UI | F19: Sachin | G19: EMP-0082 | H19: Sachin Barnwal | I19: Context: UI/UX under Pradeep Thakur | J19: Owner | K19: 1 | L19: Product | M19: Pradeep Thakur | N19: High | O19: 46237 | P19: 46237 | R19: Completed | S19: In Review | T19: =IF(P19="","No deadline",IF(Q19<>"",IF(Q19>P19,"Late","On time"),IF(README!$B$4>P19,"Overdue","Open"))) -> Overdue | Y19: =IF(AND(S19="Completed",P19<>"",Q19<>""),IF(AND(T19="Late",X19="Yes",W19="Yes"),"Excluded (validated delay)","Yes"),"No") -> No | Z19: Completed without completed date; Moved to In Review until completion date is recorded
A20: 22 | B20: PRJ-019 | C20: Shoonya MF | D20: PRJ-019-T01 | E20: Shoonya MF | F20: Sachin | G20: EMP-0082 | H20: Sachin Barnwal | I20: Context: UI/UX under Pradeep Thakur | J20: Owner | K20: 1 | L20: Product | M20: Pradeep Thakur | N20: High | O20: 46205 | P20: 46234 | Q20: 46266 | R20: In Review | S20: In Review | T20: =IF(P20="","No deadline",IF(Q20<>"",IF(Q20>P20,"Late","On time"),IF(README!$B$4>P20,"Overdue","Open"))) -> Late | U20: Requirement change | V20: Recived update requirement based on MF: API | W20: Yes | X20: Yes | Y20: =IF(AND(S20="Completed",P20<>"",Q20<>""),IF(AND(T20="Late",X20="Yes",W20="Yes"),"Excluded (validated delay)","Yes"),"No") -> No | Z20: Has completed date but status is In Review; Completed date kept for reference; not counted as completed
A21: 23 | B21: PRJ-020 | C21: Algo Trading mobile app | D21: PRJ-020-T01 | E21: Algo Trading mobile app | F21: Sachin | G21: EMP-0082 | H21: Sachin Barnwal | I21: Context: UI/UX under Pradeep Thakur | J21: Owner | K21: 1 | L21: Product | M21: Pradeep Thakur | N21: High | O21: 46244 | P21: 46248 | R21: In Review | S21: In Review | T21: =IF(P21="","No deadline",IF(Q21<>"",IF(Q21>P21,"Late","On time"),IF(README!$B$4>P21,"Overdue","Open"))) -> Overdue | Y21: =IF(AND(S21="Completed",P21<>"",Q21<>""),IF(AND(T21="Late",X21="Yes",W21="Yes"),"Excluded (validated delay)","Yes"),"No") -> No
A22: 24 | B22: PRJ-021 | C22: App Tour | D22: PRJ-021-T01 | E22: App Tour | F22: Harsh | G22: EMP-0084 | H22: Harsh | I22: Context: UI/UX under Pradeep Thakur | J22: Owner | K22: 1 | L22: Product | M22: Pradeep Thakur | N22: High | O22: 46197 | P22: 46197 | R22: In Review | S22: In Review | T22: =IF(P22="","No deadline",IF(Q22<>"",IF(Q22>P22,"Late","On time"),IF(README!$B$4>P22,"Overdue","Open"))) -> Overdue | Y22: =IF(AND(S22="Completed",P22<>"",Q22<>""),IF(AND(T22="Late",X22="Yes",W22="Yes"),"Excluded (validated delay)","Yes"),"No") -> No
A23: 25 | B23: PRJ-022 | C23: Widgets | D23: PRJ-022-T01 | E23: Widgets | F23: Harsh | G23: EMP-0084 | H23: Harsh | I23: Context: UI/UX under Pradeep Thakur | J23: Owner | K23: 1 | L23: Product | M23: Pradeep Thakur | N23: High | O23: 46197 | P23: 46197 | R23: In Review | S23: In Review | T23: =IF(P23="","No deadline",IF(Q23<>"",IF(Q23>P23,"Late","On time"),IF(README!$B$4>P23,"Overdue","Open"))) -> Overdue | Y23: =IF(AND(S23="Completed",P23<>"",Q23<>""),IF(AND(T23="Late",X23="Yes",W23="Yes"),"Excluded (validated delay)","Yes"),"No") -> No
A24: 26 | B24: PRJ-023 | C24: MTF Interest Charges updated | D24: PRJ-023-T01 | E24: MTF Interest Rate changes in KORP | F24: Vinay | G24: EMP-0170 | H24: Vinay Thakur | I24: Context: Ops Executive | J24: Owner | K24: 1 | L24: Operations & BO | M24: Pawan | N24: High | O24: 46235 | P24: 46266 | R24: Delayed | S24: Blocked | T24: =IF(P24="","No deadline",IF(Q24<>"",IF(Q24>P24,"Late","On time"),IF(README!$B$4>P24,"Overdue","Open"))) -> Overdue | U24: Internal dependency (Product/Development) | V24: Product team Delay | X24: Yes | Y24: =IF(AND(S24="Completed",P24<>"",Q24<>""),IF(AND(T24="Late",X24="Yes",W24="Yes"),"Excluded (validated delay)","Yes"),"No") -> No | Z24: "Delayed" is now derived from dates, not a status
A25: 27 | B25: PRJ-024 | C25: Bond | D25: PRJ-024-T01 | E25: Bond Back office intigration with Exchnages | F25: Pawan | G25: EMP-0109 | H25: Pawan Kumar | I25: Context: AVP-Operations (not the Software Engineer) | J25: Owner | K25: 1 | L25: Operations & BO | M25: Pawan | N25: High | O25: 46252 | R25: Ongoing | S25: In Progress | T25: =IF(P25="","No deadline",IF(Q25<>"",IF(Q25>P25,"Late","On time"),IF(README!$B$4>P25,"Overdue","Open"))) -> No deadline | U25: Internal dependency (Product/Development) | V25: Product team working | X25: Yes | Y25: =IF(AND(S25="Completed",P25<>"",Q25<>""),IF(AND(T25="Late",X25="Yes",W25="Yes"),"Excluded (validated delay)","Yes"),"No") -> No | Z25: Target date missing
A26: 28 | B26: PRJ-025 | C26: Refer and Reward | D26: PRJ-025-T01 | E26: for new client refer reward in KORP | F26: pawan | G26: EMP-0109 | H26: Pawan Kumar | I26: Context: AVP-Operations (not the Software Engineer) | J26: Owner | K26: 1 | L26: Operations & BO | M26: Pawan | N26: Medium | O26: 46244 | R26: Ongoing | S26: In Progress | T26: =IF(P26="","No deadline",IF(Q26<>"",IF(Q26>P26,"Late","On time"),IF(README!$B$4>P26,"Overdue","Open"))) -> No deadline | U26: Internal dependency (Product/Development) | V26: Product team working | X26: Yes | Y26: =IF(AND(S26="Completed",P26<>"",Q26<>""),IF(AND(T26="Late",X26="Yes",W26="Yes"),"Excluded (validated delay)","Yes"),"No") -> No | Z26: Target date missing
A27: 29 | B27: PRJ-026 | C27: Account opening journey with (AI) incorporation | D27: PRJ-026-T01 | E27: New account opening journey with (AI) incorporation | F27: Vivek | G27: EMP-0174 | H27: Vivek Sharma | I27: Exact first-name match in Ops & BO | J27: Owner | K27: 1 | L27: Operations & BO | M27: Pawan | N27: High | O27: 46126 | Q27: 46308 | R27: Delayed | S27: Blocked | T27: =IF(P27="","No deadline",IF(Q27<>"",IF(Q27>P27,"Late","On time"),IF(README!$B$4>P27,"Overdue","Open"))) -> No deadline | U27: Internal dependency (Product/Development) | V27: launch of p2 delayed this project | X27: Yes | Y27: =IF(AND(S27="Completed",P27<>"",Q27<>""),IF(AND(T27="Late",X27="Yes",W27="Yes"),"Excluded (validated delay)","Yes"),"No") -> No | Z27: Target date missing; Completed date is in the future; Has completed date but status is Delayed; "Delayed" is now derived from dates, not a status
A28: 30 | B28: PRJ-026 | C28: Account opening journey with (AI) incorporation | D28: PRJ-026-T01 | E28: New account opening journey with (AI) incorporation | F28: Jaidev | G28: EMP-0181 | H28: Jai Dev Singh | I28: Spelling differs (Jaidev vs Jai Dev) | J28: Owner | K28: 1 | L28: Operations & BO | M28: Vivek | N28: High | O28: 46126 | Q28: 46308 | R28: Delayed | S28: Blocked | T28: =IF(P28="","No deadline",IF(Q28<>"",IF(Q28>P28,"Late","On time"),IF(README!$B$4>P28,"Overdue","Open"))) -> No deadline | U28: Internal dependency (Product/Development) | V28: launch of p2 delayed this project | X28: Yes | Y28: =IF(AND(S28="Completed",P28<>"",Q28<>""),IF(AND(T28="Late",X28="Yes",W28="Yes"),"Excluded (validated delay)","Yes"),"No") -> No | Z28: Target date missing; Completed date is in the future; Has completed date but status is Delayed; "Delayed" is now derived from dates, not a status
A29: 31 | B29: PRJ-027 | C29: (AI) integrated Module for Prism Dashboard (BO) | D29: PRJ-027-T01 | E29: BO Daily MIS | F29: Vivek | G29: EMP-0174 | H29: Vivek Sharma | I29: Exact first-name match in Ops & BO | J29: Owner | K29: 1 | L29: Operations & BO | M29: Pawan | N29: Medium | O29: 46237 | P29: 46265 | R29: Ongoing | S29: In Progress | T29: =IF(P29="","No deadline",IF(Q29<>"",IF(Q29>P29,"Late","On time"),IF(README!$B$4>P29,"Overdue","Open"))) -> Overdue | Y29: =IF(AND(S29="Completed",P29<>"",Q29<>""),IF(AND(T29="Late",X29="Yes",W29="Yes"),"Excluded (validated delay)","Yes"),"No") -> No
A30: 32 | B30: PRJ-027 | C30: (AI) integrated Module for Prism Dashboard (BO) | D30: PRJ-027-T01 | E30: BO Daily MIS | F30: Jaidev | G30: EMP-0181 | H30: Jai Dev Singh | I30: Spelling differs (Jaidev vs Jai Dev) | J30: Owner | K30: 1 | L30: Operations & BO | M30: Vivek | N30: Medium | O30: 46237 | P30: 46265 | R30: Ongoing | S30: In Progress | T30: =IF(P30="","No deadline",IF(Q30<>"",IF(Q30>P30,"Late","On time"),IF(README!$B$4>P30,"Overdue","Open"))) -> Overdue | Y30: =IF(AND(S30="Completed",P30<>"",Q30<>""),IF(AND(T30="Late",X30="Yes",W30="Yes"),"Excluded (validated delay)","Yes"),"No") -> No
A31: 33 | B31: PRJ-027 | C31: (AI) integrated Module for Prism Dashboard (BO) | D31: PRJ-027-T01 | E31: BO Daily MIS | F31: Kanav | G31: EMP-0175 | H31: Kanav Verma | I31: Exact first-name match | J31: Owner | K31: 1 | L31: Operations & BO | M31: Vivek | N31: Medium | O31: 46237 | P31: 46265 | R31: Ongoing | S31: In Progress | T31: =IF(P31="","No deadline",IF(Q31<>"",IF(Q31>P31,"Late","On time"),IF(README!$B$4>P31,"Overdue","Open"))) -> Overdue | Y31: =IF(AND(S31="Completed",P31<>"",Q31<>""),IF(AND(T31="Late",X31="Yes",W31="Yes"),"Excluded (validated delay)","Yes"),"No") -> No
A32: 34 | B32: PRJ-027 | C32: (AI) integrated Module for Prism Dashboard (BO) | D32: PRJ-027-T01 | E32: BO Daily MIS | F32: Akash | G32: EMP-0187 | H32: Akashdeep | I32: Probable: Akashdeep (BO Team Lead) - confirm | J32: Owner | K32: 1 | L32: Operations & BO | M32: Vivek | N32: Medium | O32: 46237 | P32: 46265 | R32: Ongoing | S32: In Progress | T32: =IF(P32="","No deadline",IF(Q32<>"",IF(Q32>P32,"Late","On time"),IF(README!$B$4>P32,"Overdue","Open"))) -> Overdue | Y32: =IF(AND(S32="Completed",P32<>"",Q32<>""),IF(AND(T32="Late",X32="Yes",W32="Yes"),"Excluded (validated delay)","Yes"),"No") -> No
A33: 35 | B33: PRJ-028 | C33: Quick Pledge/Unpledge | D33: PRJ-028-T01 | E33: Auto process for Pledge/Unpledge | F33: Yogesh | G33: EMP-0110 | H33: Yogesh | I33: Exact match | J33: Owner | K33: 1 | L33: Operations & BO | M33: Pawan | N33: High | O33: 46203 | P33: 46276 | R33: Ongoing | S33: In Progress | T33: =IF(P33="","No deadline",IF(Q33<>"",IF(Q33>P33,"Late","On time"),IF(README!$B$4>P33,"Overdue","Open"))) -> Overdue | U33: Internal dependency (Product/Development) | V33: Product team working | X33: Yes | Y33: =IF(AND(S33="Completed",P33<>"",Q33<>""),IF(AND(T33="Late",X33="Yes",W33="Yes"),"Excluded (validated delay)","Yes"),"No") -> No
A34: 36 | B34: PRJ-028 | C34: Quick Pledge/Unpledge | D34: PRJ-028-T01 | E34: Auto process for Pledge/Unpledge | F34: Atul | G34: EMP-0112 | H34: Atul Kumar | I34: Context: reports to Yogesh (Demat) | J34: Owner | K34: 1 | L34: Operations & BO | M34: Yogesh | N34: High | O34: 46203 | P34: 46276 | R34: Ongoing | S34: In Progress | T34: =IF(P34="","No deadline",IF(Q34<>"",IF(Q34>P34,"Late","On time"),IF(README!$B$4>P34,"Overdue","Open"))) -> Overdue | U34: Internal dependency (Product/Development) | V34: Product team working | X34: Yes | Y34: =IF(AND(S34="Completed",P34<>"",Q34<>""),IF(AND(T34="Late",X34="Yes",W34="Yes"),"Excluded (validated delay)","Yes"),"No") -> No
A35: 37 | B35: PRJ-029 | C35: Buyback Feature Implementation | D35: PRJ-029-T01 | E35: Auto process for Buyback | F35: Yogesh | G35: EMP-0110 | H35: Yogesh | I35: Exact match | J35: Owner | K35: 1 | L35: Operations & BO | M35: Pawan | N35: Medium | O35: 46235 | R35: Ongoing | S35: In Progress | T35: =IF(P35="","No deadline",IF(Q35<>"",IF(Q35>P35,"Late","On time"),IF(README!$B$4>P35,"Overdue","Open"))) -> No deadline | U35: Internal dependency (Product/Development) | V35: Product team working | X35: Yes | Y35: =IF(AND(S35="Completed",P35<>"",Q35<>""),IF(AND(T35="Late",X35="Yes",W35="Yes"),"Excluded (validated delay)","Yes"),"No") -> No | Z35: Target date missing
A36: 38 | B36: PRJ-029 | C36: Buyback Feature Implementation | D36: PRJ-029-T01 | E36: Auto process for Buyback | F36: Atul | G36: EMP-0112 | H36: Atul Kumar | I36: Context: reports to Yogesh (Demat) | J36: Owner | K36: 1 | L36: Operations & BO | M36: Yogesh | N36: Medium | O36: 46235 | R36: Ongoing | S36: In Progress | T36: =IF(P36="","No deadline",IF(Q36<>"",IF(Q36>P36,"Late","On time"),IF(README!$B$4>P36,"Overdue","Open"))) -> No deadline | U36: Internal dependency (Product/Development) | V36: Product team working | X36: Yes | Y36: =IF(AND(S36="Completed",P36<>"",Q36<>""),IF(AND(T36="Late",X36="Yes",W36="Yes"),"Excluded (validated delay)","Yes"),"No") -> No | Z36: Target date missing
A37: 39 | B37: PRJ-030 | C37: SenS-AI 1.1 Enhancement | D37: PRJ-030-T01 | E37: Development of Module in Mobile app | F37: Saksham | G37: EMP-0048 | H37: Saksham | I37: Exact match | J37: Contributor | K37: 0.2 | L37: Product | N37: High | P37: 46268 | R37: Delayed | S37: Blocked | T37: =IF(P37="","No deadline",IF(Q37<>"",IF(Q37>P37,"Late","On time"),IF(README!$B$4>P37,"Overdue","Open"))) -> Overdue | U37: Management reprioritisation | V37: due to an urgent requirement, we are releasing changes to MTF 3x the app is in review and once that app is released, we will publish SensAI | X37: Yes | Y37: =IF(AND(S37="Completed",P37<>"",Q37<>""),IF(AND(T37="Late",X37="Yes",W37="Yes"),"Excluded (validated delay)","Yes"),"No") -> No | Z37: Project owner missing; "Delayed" is now derived from dates, not a status; Multiple assignees in one cell - split; confirm owner and contribution %
A38: 39 | B38: PRJ-030 | C38: SenS-AI 1.1 Enhancement | D38: PRJ-030-T01 | E38: Development of Module in Mobile app | F38: Jaspreet | G38: EMP-0058 | H38: Jaspreet Singh | I38: Exact first-name match | J38: Contributor | K38: 0.2 | L38: Product | N38: High | P38: 46268 | R38: Delayed | S38: Blocked | T38: =IF(P38="","No deadline",IF(Q38<>"",IF(Q38>P38,"Late","On time"),IF(README!$B$4>P38,"Overdue","Open"))) -> Overdue | U38: Management reprioritisation | V38: due to an urgent requirement, we are releasing changes to MTF 3x the app is in review and once that app is released, we will publish SensAI | X38: Yes | Y38: =IF(AND(S38="Completed",P38<>"",Q38<>""),IF(AND(T38="Late",X38="Yes",W38="Yes"),"Excluded (validated delay)","Yes"),"No") -> No | Z38: Project owner missing; "Delayed" is now derived from dates, not a status; Multiple assignees in one cell - split; confirm owner and contribution %
A39: 39 | B39: PRJ-030 | C39: SenS-AI 1.1 Enhancement | D39: PRJ-030-T01 | E39: Development of Module in Mobile app | F39: Jatin | G39: EMP-0046 | H39: Jatin Vashisht | I39: Exact first-name match | J39: Contributor | K39: 0.2 | L39: Product | N39: High | P39: 46268 | R39: Delayed | S39: Blocked | T39: =IF(P39="","No deadline",IF(Q39<>"",IF(Q39>P39,"Late","On time"),IF(README!$B$4>P39,"Overdue","Open"))) -> Overdue | U39: Management reprioritisation | V39: due to an urgent requirement, we are releasing changes to MTF 3x the app is in review and once that app is released, we will publish SensAI | X39: Yes | Y39: =IF(AND(S39="Completed",P39<>"",Q39<>""),IF(AND(T39="Late",X39="Yes",W39="Yes"),"Excluded (validated delay)","Yes"),"No") -> No | Z39: Project owner missing; "Delayed" is now derived from dates, not a status; Multiple assignees in one cell - split; confirm owner and contribution %
A40: 39 | B40: PRJ-030 | C40: SenS-AI 1.1 Enhancement | D40: PRJ-030-T01 | E40: Development of Module in Mobile app | F40: Aryan | G40: EMP-0027 | H40: Aryan Raj | I40: Exact first-name match | J40: Contributor | K40: 0.2 | L40: Product | N40: High | P40: 46268 | R40: Delayed | S40: Blocked | T40: =IF(P40="","No deadline",IF(Q40<>"",IF(Q40>P40,"Late","On time"),IF(README!$B$4>P40,"Overdue","Open"))) -> Overdue | U40: Management reprioritisation | V40: due to an urgent requirement, we are releasing changes to MTF 3x the app is in review and once that app is released, we will publish SensAI | X40: Yes | Y40: =IF(AND(S40="Completed",P40<>"",Q40<>""),IF(AND(T40="Late",X40="Yes",W40="Yes"),"Excluded (validated delay)","Yes"),"No") -> No | Z40: Project owner missing; "Delayed" is now derived from dates, not a status; Multiple assignees in one cell - split; confirm owner and contribution %
A41: 39 | B41: PRJ-030 | C41: SenS-AI 1.1 Enhancement | D41: PRJ-030-T01 | E41: Development of Module in Mobile app | F41: sumit roy | G41: EMP-0024 | H41: Sumit Roy | I41: Exact match | J41: Contributor | K41: 0.2 | L41: Product | N41: High | P41: 46268 | R41: Delayed | S41: Blocked | T41: =IF(P41="","No deadline",IF(Q41<>"",IF(Q41>P41,"Late","On time"),IF(README!$B$4>P41,"Overdue","Open"))) -> Overdue | U41: Management reprioritisation | V41: due to an urgent requirement, we are releasing changes to MTF 3x the app is in review and once that app is released, we will publish SensAI | X41: Yes | Y41: =IF(AND(S41="Completed",P41<>"",Q41<>""),IF(AND(T41="Late",X41="Yes",W41="Yes"),"Excluded (validated delay)","Yes"),"No") -> No | Z41: Project owner missing; "Delayed" is now derived from dates, not a status; Multiple assignees in one cell - split; confirm owner and contribution %
A42: 40 | B42: PRJ-031 | C42: fno Edge | D42: PRJ-031-T01 | E42: integration of fnoedge sdk | F42: sumit kumar | G42: EMP-0057 | H42: Sumit Kumar | I42: Exact match | J42: Contributor | K42: 0.25 | L42: Product | N42: High | P42: 46261 | R42: Completed | S42: In Review | T42: =IF(P42="","No deadline",IF(Q42<>"",IF(Q42>P42,"Late","On time"),IF(README!$B$4>P42,"Overdue","Open"))) -> Overdue | Y42: =IF(AND(S42="Completed",P42<>"",Q42<>""),IF(AND(T42="Late",X42="Yes",W42="Yes"),"Excluded (validated delay)","Yes"),"No") -> No | Z42: Project owner missing; Completed without completed date; Moved to In Review until completion date is recorded; Multiple assignees in one cell - split; confirm owner and contribution %
A43: 40 | B43: PRJ-031 | C43: fno Edge | D43: PRJ-031-T01 | E43: integration of fnoedge sdk | F43: tushar | G43: EMP-0052 | H43: Tushar Verma | I43: Exact first-name match | J43: Contributor | K43: 0.25 | L43: Product | N43: High | P43: 46261 | R43: Completed | S43: In Review | T43: =IF(P43="","No deadline",IF(Q43<>"",IF(Q43>P43,"Late","On time"),IF(README!$B$4>P43,"Overdue","Open"))) -> Overdue | Y43: =IF(AND(S43="Completed",P43<>"",Q43<>""),IF(AND(T43="Late",X43="Yes",W43="Yes"),"Excluded (validated delay)","Yes"),"No") -> No | Z43: Project owner missing; Completed without completed date; Moved to In Review until completion date is recorded; Multiple assignees in one cell - split; confirm owner and contribution %
A44: 40 | B44: PRJ-031 | C44: fno Edge | D44: PRJ-031-T01 | E44: integration of fnoedge sdk | F44: Jatin | G44: EMP-0046 | H44: Jatin Vashisht | I44: Exact first-name match | J44: Contributor | K44: 0.25 | L44: Product | N44: High | P44: 46261 | R44: Completed | S44: In Review | T44: =IF(P44="","No deadline",IF(Q44<>"",IF(Q44>P44,"Late","On time"),IF(README!$B$4>P44,"Overdue","Open"))) -> Overdue | Y44: =IF(AND(S44="Completed",P44<>"",Q44<>""),IF(AND(T44="Late",X44="Yes",W44="Yes"),"Excluded (validated delay)","Yes"),"No") -> No | Z44: Project owner missing; Completed without completed date; Moved to In Review until completion date is recorded; Multiple assignees in one cell - split; confirm owner and contribution %
A45: 40 | B45: PRJ-031 | C45: fno Edge | D45: PRJ-031-T01 | E45: integration of fnoedge sdk | F45: Sumit Roy | G45: EMP-0024 | H45: Sumit Roy | I45: Exact match | J45: Contributor | K45: 0.25 | L45: Product | N45: High | P45: 46261 | R45: Completed | S45: In Review | T45: =IF(P45="","No deadline",IF(Q45<>"",IF(Q45>P45,"Late","On time"),IF(README!$B$4>P45,"Overdue","Open"))) -> Overdue | Y45: =IF(AND(S45="Completed",P45<>"",Q45<>""),IF(AND(T45="Late",X45="Yes",W45="Yes"),"Excluded (validated delay)","Yes"),"No") -> No | Z45: Project owner missing; Completed without completed date; Moved to In Review until completion date is recorded; Multiple assignees in one cell - split; confirm owner and contribution %
A46: 41 | B46: PRJ-032 | C46: Automating the current PRISM process | D46: PRJ-032-T01 | E46: automating the onboarding process by ingrating AI APIs | F46: Shivam | G46: EMP-0042 | H46: Shivam | I46: Exact match | J46: Contributor | K46: 0.33333333 | L46: Product | N46: Medium | P46: 46308 | R46: Ongoing | S46: In Progress | T46: =IF(P46="","No deadline",IF(Q46<>"",IF(Q46>P46,"Late","On time"),IF(README!$B$4>P46,"Overdue","Open"))) -> Open | Y46: =IF(AND(S46="Completed",P46<>"",Q46<>""),IF(AND(T46="Late",X46="Yes",W46="Yes"),"Excluded (validated delay)","Yes"),"No") -> No | Z46: Project owner missing; Multiple assignees in one cell - split; confirm owner and contribution %
A47: 41 | B47: PRJ-032 | C47: Automating the current PRISM process | D47: PRJ-032-T01 | E47: automating the onboarding process by ingrating AI APIs | F47: Ankit | G47: EMP-0041 | H47: Ankit | I47: Probable: Ankit (Software Engineer, Product) - 2 records named Ankit | J47: Contributor | K47: 0.33333333 | L47: Product | N47: Medium | P47: 46308 | R47: Ongoing | S47: In Progress | T47: =IF(P47="","No deadline",IF(Q47<>"",IF(Q47>P47,"Late","On time"),IF(README!$B$4>P47,"Overdue","Open"))) -> Open | Y47: =IF(AND(S47="Completed",P47<>"",Q47<>""),IF(AND(T47="Late",X47="Yes",W47="Yes"),"Excluded (validated delay)","Yes"),"No") -> No | Z47: Project owner missing; Multiple assignees in one cell - split; confirm owner and contribution %
A48: 41 | B48: PRJ-032 | C48: Automating the current PRISM process | D48: PRJ-032-T01 | E48: automating the onboarding process by ingrating AI APIs | F48: Manisha | G48: EMP-0025 | H48: Manisha Kumari | I48: Exact first-name match | J48: Contributor | K48: 0.33333333 | L48: Product | N48: Medium | P48: 46308 | R48: Ongoing | S48: In Progress | T48: =IF(P48="","No deadline",IF(Q48<>"",IF(Q48>P48,"Late","On time"),IF(README!$B$4>P48,"Overdue","Open"))) -> Open | Y48: =IF(AND(S48="Completed",P48<>"",Q48<>""),IF(AND(T48="Late",X48="Yes",W48="Yes"),"Excluded (validated delay)","Yes"),"No") -> No | Z48: Project owner missing; Multiple assignees in one cell - split; confirm owner and contribution %
A49: 42 | B49: PRJ-033 | C49: MTF Margin increase | D49: PRJ-033-T01 | E49: content changes to web page & Mobile apps | F49: Ankit Grin | H49: Ankit Grin | I49: NOT IN ORG CHART - add to master | J49: Contributor | K49: 0.33333333 | L49: Product | N49: High | O49: 46268 | P49: 46270 | R49: Ongoing | S49: In Progress | T49: =IF(P49="","No deadline",IF(Q49<>"",IF(Q49>P49,"Late","On time"),IF(README!$B$4>P49,"Overdue","Open"))) -> Overdue | Y49: =IF(AND(S49="Completed",P49<>"",Q49<>""),IF(AND(T49="Late",X49="Yes",W49="Yes"),"Excluded (validated delay)","Yes"),"No") -> No | Z49: Project owner missing; Multiple assignees in one cell - split; confirm owner and contribution %; Assignee not in org chart
A50: 42 | B50: PRJ-033 | C50: MTF Margin increase | D50: PRJ-033-T01 | E50: content changes to web page & Mobile apps | F50: sumit kumar | G50: EMP-0057 | H50: Sumit Kumar | I50: Exact match | J50: Contributor | K50: 0.33333333 | L50: Product | N50: High | O50: 46268 | P50: 46270 | R50: Ongoing | S50: In Progress | T50: =IF(P50="","No deadline",IF(Q50<>"",IF(Q50>P50,"Late","On time"),IF(README!$B$4>P50,"Overdue","Open"))) -> Overdue | Y50: =IF(AND(S50="Completed",P50<>"",Q50<>""),IF(AND(T50="Late",X50="Yes",W50="Yes"),"Excluded (validated delay)","Yes"),"No") -> No | Z50: Project owner missing; Multiple assignees in one cell - split; confirm owner and contribution %
A51: 42 | B51: PRJ-033 | C51: MTF Margin increase | D51: PRJ-033-T01 | E51: content changes to web page & Mobile apps | F51: tushar | G51: EMP-0052 | H51: Tushar Verma | I51: Exact first-name match | J51: Contributor | K51: 0.33333333 | L51: Product | N51: High | O51: 46268 | P51: 46270 | R51: Ongoing | S51: In Progress | T51: =IF(P51="","No deadline",IF(Q51<>"",IF(Q51>P51,"Late","On time"),IF(README!$B$4>P51,"Overdue","Open"))) -> Overdue | Y51: =IF(AND(S51="Completed",P51<>"",Q51<>""),IF(AND(T51="Late",X51="Yes",W51="Yes"),"Excluded (validated delay)","Yes"),"No") -> No | Z51: Project owner missing; Multiple assignees in one cell - split; confirm owner and contribution %
A52: 43 | B52: PRJ-034 | C52: Build API / Algo Trading landing page (Shoonya) | D52: PRJ-034-T01 | E52: development of web page in shoonya website | F52: Ankit Grin | H52: Ankit Grin | I52: NOT IN ORG CHART - add to master | J52: Contributor | K52: 0.5 | L52: Product | N52: High | O52: 46268 | P52: 46268 | R52: Delayed | S52: In Progress | T52: =IF(P52="","No deadline",IF(Q52<>"",IF(Q52>P52,"Late","On time"),IF(README!$B$4>P52,"Overdue","Open"))) -> Overdue | Y52: =IF(AND(S52="Completed",P52<>"",Q52<>""),IF(AND(T52="Late",X52="Yes",W52="Yes"),"Excluded (validated delay)","Yes"),"No") -> No | Z52: Project owner missing; "Delayed" is now derived from dates, not a status; Multiple assignees in one cell - split; confirm owner and contribution %; Assignee not in org chart
A53: 43 | B53: PRJ-034 | C53: Build API / Algo Trading landing page (Shoonya) | D53: PRJ-034-T01 | E53: development of web page in shoonya website | F53: Aryan | G53: EMP-0027 | H53: Aryan Raj | I53: Exact first-name match | J53: Contributor | K53: 0.5 | L53: Product | N53: High | O53: 46268 | P53: 46268 | R53: Delayed | S53: In Progress | T53: =IF(P53="","No deadline",IF(Q53<>"",IF(Q53>P53,"Late","On time"),IF(README!$B$4>P53,"Overdue","Open"))) -> Overdue | Y53: =IF(AND(S53="Completed",P53<>"",Q53<>""),IF(AND(T53="Late",X53="Yes",W53="Yes"),"Excluded (validated delay)","Yes"),"No") -> No | Z53: Project owner missing; "Delayed" is now derived from dates, not a status; Multiple assignees in one cell - split; confirm owner and contribution %
A54: 44 | B54: PRJ-035 | C54: Backend will push market data as user attributes for all users, updated 4 times daily, enabling automated and broadcast push notifications | D54: PRJ-035-T01 | E54: api integration for pushing the notifications | F54: Amandeep | H54: Amandeep | I54: NOT IN ORG CHART - add to master | J54: Contributor | K54: 0.33333333 | L54: Product | N54: High | O54: 46253 | P54: 46268 | R54: Ongoing | S54: In Progress | T54: =IF(P54="","No deadline",IF(Q54<>"",IF(Q54>P54,"Late","On time"),IF(README!$B$4>P54,"Overdue","Open"))) -> Overdue | Y54: =IF(AND(S54="Completed",P54<>"",Q54<>""),IF(AND(T54="Late",X54="Yes",W54="Yes"),"Excluded (validated delay)","Yes"),"No") -> No | Z54: Project owner missing; Multiple assignees in one cell - split; confirm owner and contribution %; Assignee not in org chart
A55: 44 | B55: PRJ-035 | C55: Backend will push market data as user attributes for all users, updated 4 times daily, enabling automated and broadcast push notifications | D55: PRJ-035-T01 | E55: api integration for pushing the notifications | F55: Sukriti | G55: EMP-0026 | H55: Sukriti | I55: Exact match | J55: Contributor | K55: 0.33333333 | L55: Product | N55: High | O55: 46253 | P55: 46268 | R55: Ongoing | S55: In Progress | T55: =IF(P55="","No deadline",IF(Q55<>"",IF(Q55>P55,"Late","On time"),IF(README!$B$4>P55,"Overdue","Open"))) -> Overdue | Y55: =IF(AND(S55="Completed",P55<>"",Q55<>""),IF(AND(T55="Late",X55="Yes",W55="Yes"),"Excluded (validated delay)","Yes"),"No") -> No | Z55: Project owner missing; Multiple assignees in one cell - split; confirm owner and contribution %
A56: 44 | B56: PRJ-035 | C56: Backend will push market data as user attributes for all users, updated 4 times daily, enabling automated and broadcast push notifications | D56: PRJ-035-T01 | E56: api integration for pushing the notifications | F56: Sumit Kumar | G56: EMP-0057 | H56: Sumit Kumar | I56: Exact match | J56: Contributor | K56: 0.33333333 | L56: Product | N56: High | O56: 46253 | P56: 46268 | R56: Ongoing | S56: In Progress | T56: =IF(P56="","No deadline",IF(Q56<>"",IF(Q56>P56,"Late","On time"),IF(README!$B$4>P56,"Overdue","Open"))) -> Overdue | Y56: =IF(AND(S56="Completed",P56<>"",Q56<>""),IF(AND(T56="Late",X56="Yes",W56="Yes"),"Excluded (validated delay)","Yes"),"No") -> No | Z56: Project owner missing; Multiple assignees in one cell - split; confirm owner and contribution %
A57: 45 | B57: PRJ-036 | C57: CRM Sourcing, Testing & Implementation | D57: PRJ-036-T01 | E57: Sourcing; KPI setup; dashboards; | F57: Angel Sharma | G57: EMP-0220 | H57: Angel Sharma | I57: Exact match | J57: Contributor | K57: 0.33333333 | L57: Client Support | M57: Kapil Abrol | O57: 46087 | P57: 46184 | R57: Ongoing | S57: In Progress | T57: =IF(P57="","No deadline",IF(Q57<>"",IF(Q57>P57,"Late","On time"),IF(README!$B$4>P57,"Overdue","Open"))) -> Overdue | Y57: =IF(AND(S57="Completed",P57<>"",Q57<>""),IF(AND(T57="Late",X57="Yes",W57="Yes"),"Excluded (validated delay)","Yes"),"No") -> No | Z57: Priority missing (mandatory); Open > 6 months - review; Multiple assignees in one cell - split; confirm owner and contribution %
A58: 45 | B58: PRJ-036 | C58: CRM Sourcing, Testing & Implementation | D58: PRJ-036-T01 | E58: Sourcing; KPI setup; dashboards; | F58: Sahil Sharma | G58: EMP-0221 | H58: Sahil Sharma | I58: Exact match | J58: Contributor | K58: 0.33333333 | L58: Client Support | M58: Kapil Abrol | O58: 46087 | P58: 46184 | R58: Ongoing | S58: In Progress | T58: =IF(P58="","No deadline",IF(Q58<>"",IF(Q58>P58,"Late","On time"),IF(README!$B$4>P58,"Overdue","Open"))) -> Overdue | Y58: =IF(AND(S58="Completed",P58<>"",Q58<>""),IF(AND(T58="Late",X58="Yes",W58="Yes"),"Excluded (validated delay)","Yes"),"No") -> No | Z58: Priority missing (mandatory); Open > 6 months - review; Multiple assignees in one cell - split; confirm owner and contribution %
A59: 45 | B59: PRJ-036 | C59: CRM Sourcing, Testing & Implementation | D59: PRJ-036-T01 | E59: Sourcing; KPI setup; dashboards; | F59: Adity Chhiba | G59: EMP-0237 | H59: Adity Chiba | I59: Spelling differs (Chhiba vs Chiba) | J59: Contributor | K59: 0.33333333 | L59: Client Support | M59: Kapil Abrol | O59: 46087 | P59: 46184 | R59: Ongoing | S59: In Progress | T59: =IF(P59="","No deadline",IF(Q59<>"",IF(Q59>P59,"Late","On time"),IF(README!$B$4>P59,"Overdue","Open"))) -> Overdue | Y59: =IF(AND(S59="Completed",P59<>"",Q59<>""),IF(AND(T59="Late",X59="Yes",W59="Yes"),"Excluded (validated delay)","Yes"),"No") -> No | Z59: Priority missing (mandatory); Open > 6 months - review; Multiple assignees in one cell - split; confirm owner and contribution %
A60: 46 | B60: PRJ-036 | C60: CRM Sourcing, Testing & Implementation | D60: PRJ-036-T02 | E60: CSAT optimization; bot integration; | F60: Angel Sharma | G60: EMP-0220 | H60: Angel Sharma | I60: Exact match | J60: Contributor | K60: 0.33333333 | L60: Client Support | M60: Kapil Abrol | O60: 46087 | R60: Ongoing | S60: In Progress | T60: =IF(P60="","No deadline",IF(Q60<>"",IF(Q60>P60,"Late","On time"),IF(README!$B$4>P60,"Overdue","Open"))) -> No deadline | Y60: =IF(AND(S60="Completed",P60<>"",Q60<>""),IF(AND(T60="Late",X60="Yes",W60="Yes"),"Excluded (validated delay)","Yes"),"No") -> No | Z60: Target date missing; Priority missing (mandatory); Open > 6 months - review; Multiple assignees in one cell - split; confirm owner and contribution %
A61: 46 | B61: PRJ-036 | C61: CRM Sourcing, Testing & Implementation | D61: PRJ-036-T02 | E61: CSAT optimization; bot integration; | F61: Sahil Sharma | G61: EMP-0221 | H61: Sahil Sharma | I61: Exact match | J61: Contributor | K61: 0.33333333 | L61: Client Support | M61: Kapil Abrol | O61: 46087 | R61: Ongoing | S61: In Progress | T61: =IF(P61="","No deadline",IF(Q61<>"",IF(Q61>P61,"Late","On time"),IF(README!$B$4>P61,"Overdue","Open"))) -> No deadline | Y61: =IF(AND(S61="Completed",P61<>"",Q61<>""),IF(AND(T61="Late",X61="Yes",W61="Yes"),"Excluded (validated delay)","Yes"),"No") -> No | Z61: Target date missing; Priority missing (mandatory); Open > 6 months - review; Multiple assignees in one cell - split; confirm owner and contribution %
A62: 46 | B62: PRJ-036 | C62: CRM Sourcing, Testing & Implementation | D62: PRJ-036-T02 | E62: CSAT optimization; bot integration; | F62: Adity Chhiba | G62: EMP-0237 | H62: Adity Chiba | I62: Spelling differs (Chhiba vs Chiba) | J62: Contributor | K62: 0.33333333 | L62: Client Support | M62: Kapil Abrol | O62: 46087 | R62: Ongoing | S62: In Progress | T62: =IF(P62="","No deadline",IF(Q62<>"",IF(Q62>P62,"Late","On time"),IF(README!$B$4>P62,"Overdue","Open"))) -> No deadline | Y62: =IF(AND(S62="Completed",P62<>"",Q62<>""),IF(AND(T62="Late",X62="Yes",W62="Yes"),"Excluded (validated delay)","Yes"),"No") -> No | Z62: Target date missing; Priority missing (mandatory); Open > 6 months - review; Multiple assignees in one cell - split; confirm owner and contribution %
A63: 47 | B63: PRJ-036 | C63: CRM Sourcing, Testing & Implementation | D63: PRJ-036-T03 | E63: APIs; CRM implementation; channel-wise RTM | F63: Angel Sharma | G63: EMP-0220 | H63: Angel Sharma | I63: Exact match | J63: Contributor | K63: 0.33333333 | L63: Client Support | M63: Kapil Abrol | O63: 46087 | R63: Ongoing | S63: In Progress | T63: =IF(P63="","No deadline",IF(Q63<>"",IF(Q63>P63,"Late","On time"),IF(README!$B$4>P63,"Overdue","Open"))) -> No deadline | Y63: =IF(AND(S63="Completed",P63<>"",Q63<>""),IF(AND(T63="Late",X63="Yes",W63="Yes"),"Excluded (validated delay)","Yes"),"No") -> No | Z63: Target date missing; Priority missing (mandatory); Open > 6 months - review; Multiple assignees in one cell - split; confirm owner and contribution %
A64: 47 | B64: PRJ-036 | C64: CRM Sourcing, Testing & Implementation | D64: PRJ-036-T03 | E64: APIs; CRM implementation; channel-wise RTM | F64: Sahil Sharma | G64: EMP-0221 | H64: Sahil Sharma | I64: Exact match | J64: Contributor | K64: 0.33333333 | L64: Client Support | M64: Kapil Abrol | O64: 46087 | R64: Ongoing | S64: In Progress | T64: =IF(P64="","No deadline",IF(Q64<>"",IF(Q64>P64,"Late","On time"),IF(README!$B$4>P64,"Overdue","Open"))) -> No deadline | Y64: =IF(AND(S64="Completed",P64<>"",Q64<>""),IF(AND(T64="Late",X64="Yes",W64="Yes"),"Excluded (validated delay)","Yes"),"No") -> No | Z64: Target date missing; Priority missing (mandatory); Open > 6 months - review; Multiple assignees in one cell - split; confirm owner and contribution %
A65: 47 | B65: PRJ-036 | C65: CRM Sourcing, Testing & Implementation | D65: PRJ-036-T03 | E65: APIs; CRM implementation; channel-wise RTM | F65: Adity Chhiba | G65: EMP-0237 | H65: Adity Chiba | I65: Spelling differs (Chhiba vs Chiba) | J65: Contributor | K65: 0.33333333 | L65: Client Support | M65: Kapil Abrol | O65: 46087 | R65: Ongoing | S65: In Progress | T65: =IF(P65="","No deadline",IF(Q65<>"",IF(Q65>P65,"Late","On time"),IF(README!$B$4>P65,"Overdue","Open"))) -> No deadline | Y65: =IF(AND(S65="Completed",P65<>"",Q65<>""),IF(AND(T65="Late",X65="Yes",W65="Yes"),"Excluded (validated delay)","Yes"),"No") -> No | Z65: Target date missing; Priority missing (mandatory); Open > 6 months - review; Multiple assignees in one cell - split; confirm owner and contribution %
A66: 48 | B66: PRJ-037 | C66: AI Bots Testing & Implementation | D66: PRJ-037-T01 | E66: Calling bot; chat bot; email bot; FAQs; | F66: Angel Sharma | G66: EMP-0220 | H66: Angel Sharma | I66: Exact match | J66: Contributor | K66: 0.33333333 | L66: Client Support | M66: Kapil Abrol | O66: 46167 | R66: Ongoing | S66: In Progress | T66: =IF(P66="","No deadline",IF(Q66<>"",IF(Q66>P66,"Late","On time"),IF(README!$B$4>P66,"Overdue","Open"))) -> No deadline | Y66: =IF(AND(S66="Completed",P66<>"",Q66<>""),IF(AND(T66="Late",X66="Yes",W66="Yes"),"Excluded (validated delay)","Yes"),"No") -> No | Z66: Target date missing; Priority missing (mandatory); Multiple assignees in one cell - split; confirm owner and contribution %
A67: 48 | B67: PRJ-037 | C67: AI Bots Testing & Implementation | D67: PRJ-037-T01 | E67: Calling bot; chat bot; email bot; FAQs; | F67: Sahil Sharma | G67: EMP-0221 | H67: Sahil Sharma | I67: Exact match | J67: Contributor | K67: 0.33333333 | L67: Client Support | M67: Kapil Abrol | O67: 46167 | R67: Ongoing | S67: In Progress | T67: =IF(P67="","No deadline",IF(Q67<>"",IF(Q67>P67,"Late","On time"),IF(README!$B$4>P67,"Overdue","Open"))) -> No deadline | Y67: =IF(AND(S67="Completed",P67<>"",Q67<>""),IF(AND(T67="Late",X67="Yes",W67="Yes"),"Excluded (validated delay)","Yes"),"No") -> No | Z67: Target date missing; Priority missing (mandatory); Multiple assignees in one cell - split; confirm owner and contribution %
A68: 48 | B68: PRJ-037 | C68: AI Bots Testing & Implementation | D68: PRJ-037-T01 | E68: Calling bot; chat bot; email bot; FAQs; | F68: Adity Chhiba | G68: EMP-0237 | H68: Adity Chiba | I68: Spelling differs (Chhiba vs Chiba) | J68: Contributor | K68: 0.33333333 | L68: Client Support | M68: Kapil Abrol | O68: 46167 | R68: Ongoing | S68: In Progress | T68: =IF(P68="","No deadline",IF(Q68<>"",IF(Q68>P68,"Late","On time"),IF(README!$B$4>P68,"Overdue","Open"))) -> No deadline | Y68: =IF(AND(S68="Completed",P68<>"",Q68<>""),IF(AND(T68="Late",X68="Yes",W68="Yes"),"Excluded (validated delay)","Yes"),"No") -> No | Z68: Target date missing; Priority missing (mandatory); Multiple assignees in one cell - split; confirm owner and contribution %
A69: 49 | B69: PRJ-037 | C69: AI Bots Testing & Implementation | D69: PRJ-037-T02 | E69: BRDs and documentation; database upload; | F69: Angel Sharma | G69: EMP-0220 | H69: Angel Sharma | I69: Exact match | J69: Contributor | K69: 0.33333333 | L69: Client Support | M69: Kapil Abrol | O69: 46167 | R69: Ongoing | S69: In Progress | T69: =IF(P69="","No deadline",IF(Q69<>"",IF(Q69>P69,"Late","On time"),IF(README!$B$4>P69,"Overdue","Open"))) -> No deadline | Y69: =IF(AND(S69="Completed",P69<>"",Q69<>""),IF(AND(T69="Late",X69="Yes",W69="Yes"),"Excluded (validated delay)","Yes"),"No") -> No | Z69: Target date missing; Priority missing (mandatory); Multiple assignees in one cell - split; confirm owner and contribution %
A70: 49 | B70: PRJ-037 | C70: AI Bots Testing & Implementation | D70: PRJ-037-T02 | E70: BRDs and documentation; database upload; | F70: Sahil Sharma | G70: EMP-0221 | H70: Sahil Sharma | I70: Exact match | J70: Contributor | K70: 0.33333333 | L70: Client Support | M70: Kapil Abrol | O70: 46167 | R70: Ongoing | S70: In Progress | T70: =IF(P70="","No deadline",IF(Q70<>"",IF(Q70>P70,"Late","On time"),IF(README!$B$4>P70,"Overdue","Open"))) -> No deadline | Y70: =IF(AND(S70="Completed",P70<>"",Q70<>""),IF(AND(T70="Late",X70="Yes",W70="Yes"),"Excluded (validated delay)","Yes"),"No") -> No | Z70: Target date missing; Priority missing (mandatory); Multiple assignees in one cell - split; confirm owner and contribution %
A71: 49 | B71: PRJ-037 | C71: AI Bots Testing & Implementation | D71: PRJ-037-T02 | E71: BRDs and documentation; database upload; | F71: Adity Chhiba | G71: EMP-0237 | H71: Adity Chiba | I71: Spelling differs (Chhiba vs Chiba) | J71: Contributor | K71: 0.33333333 | L71: Client Support | M71: Kapil Abrol | O71: 46167 | R71: Ongoing | S71: In Progress | T71: =IF(P71="","No deadline",IF(Q71<>"",IF(Q71>P71,"Late","On time"),IF(README!$B$4>P71,"Overdue","Open"))) -> No deadline | Y71: =IF(AND(S71="Completed",P71<>"",Q71<>""),IF(AND(T71="Late",X71="Yes",W71="Yes"),"Excluded (validated delay)","Yes"),"No") -> No | Z71: Target date missing; Priority missing (mandatory); Multiple assignees in one cell - split; confirm owner and contribution %
... A113: 70 | B113: PRJ-044 | C113: Chart issues | D113: PRJ-044-T03 | E113: Implementation sign off | F113: Sahil Sharma | G113: EMP-0221 | H113: Sahil Sharma | I113: Exact match | J113: Owner | K113: 1 | L113: Client Support | M113: Kapil Abrol | O113: 45874 | R113: Ongoing | S113: In Progress | T113: =IF(P113="","No deadline",IF(Q113<>"",IF(Q113>P113,"Late","On time"),IF(README!$B$4>P113,"Overdue","Open"))) -> No deadline | Y113: =IF(AND(S113="Completed",P113<>"",Q113<>""),IF(AND(T113="Late",X113="Yes",W113="Yes"),"Excluded (validated delay)","Yes"),"No") -> No | Z113: Target date missing; Priority missing (mandatory); Open > 6 months - review
A114: 71 | B114: PRJ-045 | C114: Introduction of Time-Based Validity Order Types | D114: PRJ-045-T01 | E114: Design, Testing | F114: Sahil Sharma | G114: EMP-0221 | H114: Sahil Sharma | I114: Exact match | J114: Contributor | K114: 0.5 | L114: Client Support | M114: Kapil Abrol | O114: 46072 | R114: Delayed | S114: Blocked | T114: =IF(P114="","No deadline",IF(Q114<>"",IF(Q114>P114,"Late","On time"),IF(README!$B$4>P114,"Overdue","Open"))) -> No deadline | U114: Internal dependency (Product/Development) | V114: Pending at development P2 | X114: Yes | Y114: =IF(AND(S114="Completed",P114<>"",Q114<>""),IF(AND(T114="Late",X114="Yes",W114="Yes"),"Excluded (validated delay)","Yes"),"No") -> No | Z114: Target date was "-" - cleared; Target date missing; Priority missing (mandatory); Open > 6 months - review; "Delayed" is now derived from dates, not a status; Multiple assignees in one cell - split; confirm owner and contribution %
A115: 71 | B115: PRJ-045 | C115: Introduction of Time-Based Validity Order Types | D115: PRJ-045-T01 | E115: Design, Testing | F115: Aaina | G115: EMP-0224 | H115: Aaina Ghill | I115: First name only | J115: Contributor | K115: 0.5 | L115: Client Support | M115: Kapil Abrol | O115: 46072 | R115: Delayed | S115: Blocked | T115: =IF(P115="","No deadline",IF(Q115<>"",IF(Q115>P115,"Late","On time"),IF(README!$B$4>P115,"Overdue","Open"))) -> No deadline | U115: Internal dependency (Product/Development) | V115: Pending at development P2 | X115: Yes | Y115: =IF(AND(S115="Completed",P115<>"",Q115<>""),IF(AND(T115="Late",X115="Yes",W115="Yes"),"Excluded (validated delay)","Yes"),"No") -> No | Z115: Target date was "-" - cleared; Target date missing; Priority missing (mandatory); Open > 6 months - review; "Delayed" is now derived from dates, not a status; Multiple assignees in one cell - split; confirm owner and contribution %
A116: 72 | B116: PRJ-045 | C116: Introduction of Time-Based Validity Order Types | D116: PRJ-045-T02 | E116: Co-ordination with product | F116: Sahil Sharma | G116: EMP-0221 | H116: Sahil Sharma | I116: Exact match | J116: Contributor | K116: 0.5 | L116: Client Support | M116: Kapil Abrol | O116: 46072 | R116: Delayed | S116: Blocked | T116: =IF(P116="","No deadline",IF(Q116<>"",IF(Q116>P116,"Late","On time"),IF(README!$B$4>P116,"Overdue","Open"))) -> No deadline | U116: Internal dependency (Product/Development) | V116: Pending at development P2 | X116: Yes | Y116: =IF(AND(S116="Completed",P116<>"",Q116<>""),IF(AND(T116="Late",X116="Yes",W116="Yes"),"Excluded (validated delay)","Yes"),"No") -> No | Z116: Target date was "-" - cleared; Target date missing; Priority missing (mandatory); Open > 6 months - review; "Delayed" is now derived from dates, not a status; Multiple assignees in one cell - split; confirm owner and contribution %
A117: 72 | B117: PRJ-045 | C117: Introduction of Time-Based Validity Order Types | D117: PRJ-045-T02 | E117: Co-ordination with product | F117: Aaina | G117: EMP-0224 | H117: Aaina Ghill | I117: First name only | J117: Contributor | K117: 0.5 | L117: Client Support | M117: Kapil Abrol | O117: 46072 | R117: Delayed | S117: Blocked | T117: =IF(P117="","No deadline",IF(Q117<>"",IF(Q117>P117,"Late","On time"),IF(README!$B$4>P117,"Overdue","Open"))) -> No deadline | U117: Internal dependency (Product/Development) | V117: Pending at development P2 | X117: Yes | Y117: =IF(AND(S117="Completed",P117<>"",Q117<>""),IF(AND(T117="Late",X117="Yes",W117="Yes"),"Excluded (validated delay)","Yes"),"No") -> No | Z117: Target date was "-" - cleared; Target date missing; Priority missing (mandatory); Open > 6 months - review; "Delayed" is now derived from dates, not a status; Multiple assignees in one cell - split; confirm owner and contribution %
A118: 73 | B118: PRJ-045 | C118: Introduction of Time-Based Validity Order Types | D118: PRJ-045-T03 | E118: Implementation sign off | F118: Sahil Sharma | G118: EMP-0221 | H118: Sahil Sharma | I118: Exact match | J118: Contributor | K118: 0.5 | L118: Client Support | M118: Kapil Abrol | O118: 46072 | R118: Delayed | S118: Blocked | T118: =IF(P118="","No deadline",IF(Q118<>"",IF(Q118>P118,"Late","On time"),IF(README!$B$4>P118,"Overdue","Open"))) -> No deadline | U118: Internal dependency (Product/Development) | V118: Pending at development P2 | X118: Yes | Y118: =IF(AND(S118="Completed",P118<>"",Q118<>""),IF(AND(T118="Late",X118="Yes",W118="Yes"),"Excluded (validated delay)","Yes"),"No") -> No | Z118: Target date was "-" - cleared; Target date missing; Priority missing (mandatory); Open > 6 months - review; "Delayed" is now derived from dates, not a status; Multiple assignees in one cell - split; confirm owner and contribution %
A119: 73 | B119: PRJ-045 | C119: Introduction of Time-Based Validity Order Types | D119: PRJ-045-T03 | E119: Implementation sign off | F119: Aaina | G119: EMP-0224 | H119: Aaina Ghill | I119: First name only | J119: Contributor | K119: 0.5 | L119: Client Support | M119: Kapil Abrol | O119: 46072 | R119: Delayed | S119: Blocked | T119: =IF(P119="","No deadline",IF(Q119<>"",IF(Q119>P119,"Late","On time"),IF(README!$B$4>P119,"Overdue","Open"))) -> No deadline | U119: Internal dependency (Product/Development) | V119: Pending at development P2 | X119: Yes | Y119: =IF(AND(S119="Completed",P119<>"",Q119<>""),IF(AND(T119="Late",X119="Yes",W119="Yes"),"Excluded (validated delay)","Yes"),"No") -> No | Z119: Target date was "-" - cleared; Target date missing; Priority missing (mandatory); Open > 6 months - review; "Delayed" is now derived from dates, not a status; Multiple assignees in one cell - split; confirm owner and contribution %
A120: 74 | B120: PRJ-046 | C120: Incorrect update on App Store for Brokerage Charges | D120: PRJ-046-T01 | E120: Design, Testing | F120: Adity Chhiba | G120: EMP-0237 | H120: Adity Chiba | I120: Spelling differs (Chhiba vs Chiba) | J120: Owner | K120: 1 | L120: Client Support | M120: Kapil Abrol | O120: 46037 | R120: Delayed | S120: In Progress | T120: =IF(P120="","No deadline",IF(Q120<>"",IF(Q120>P120,"Late","On time"),IF(README!$B$4>P120,"Overdue","Open"))) -> No deadline | Y120: =IF(AND(S120="Completed",P120<>"",Q120<>""),IF(AND(T120="Late",X120="Yes",W120="Yes"),"Excluded (validated delay)","Yes"),"No") -> No | Z120: Target date was "-" - cleared; Target date missing; Priority missing (mandatory); Open > 6 months - review; "Delayed" is now derived from dates, not a status
A121: 75 | B121: PRJ-046 | C121: Incorrect update on App Store for Brokerage Charges | D121: PRJ-046-T02 | E121: Co-ordination with product | F121: Adity Chhiba | G121: EMP-0237 | H121: Adity Chiba | I121: Spelling differs (Chhiba vs Chiba) | J121: Owner | K121: 1 | L121: Client Support | M121: Kapil Abrol | O121: 46037 | R121: Delayed | S121: In Progress | T121: =IF(P121="","No deadline",IF(Q121<>"",IF(Q121>P121,"Late","On time"),IF(README!$B$4>P121,"Overdue","Open"))) -> No deadline | Y121: =IF(AND(S121="Completed",P121<>"",Q121<>""),IF(AND(T121="Late",X121="Yes",W121="Yes"),"Excluded (validated delay)","Yes"),"No") -> No | Z121: Target date was "-" - cleared; Target date missing; Priority missing (mandatory); Open > 6 months - review; "Delayed" is now derived from dates, not a status
A122: 76 | B122: PRJ-046 | C122: Incorrect update on App Store for Brokerage Charges | D122: PRJ-046-T03 | E122: Implementation sign off | F122: Adity Chhiba | G122: EMP-0237 | H122: Adity Chiba | I122: Spelling differs (Chhiba vs Chiba) | J122: Owner | K122: 1 | L122: Client Support | M122: Kapil Abrol | O122: 46037 | R122: Delayed | S122: In Progress | T122: =IF(P122="","No deadline",IF(Q122<>"",IF(Q122>P122,"Late","On time"),IF(README!$B$4>P122,"Overdue","Open"))) -> No deadline | Y122: =IF(AND(S122="Completed",P122<>"",Q122<>""),IF(AND(T122="Late",X122="Yes",W122="Yes"),"Excluded (validated delay)","Yes"),"No") -> No | Z122: Target date was "-" - cleared; Target date missing; Priority missing (mandatory); Open > 6 months - review; "Delayed" is now derived from dates, not a status
A123: 77 | B123: PRJ-047 | C123: Daily & Monthly PNL Report | D123: PRJ-047-T01 | E123: Design, Testing | F123: Adity | G123: EMP-0237 | H123: Adity Chiba | I123: First name only | J123: Contributor | K123: 0.5 | L123: Client Support | M123: Kapil Abrol | O123: 46099 | R123: Not Started | S123: Not Started | T123: =IF(P123="","No deadline",IF(Q123<>"",IF(Q123>P123,"Late","On time"),IF(README!$B$4>P123,"Overdue","Open"))) -> No deadline | U123: Internal dependency (Product/Development) | V123: Pending at development P2 | X123: Yes | Y123: =IF(AND(S123="Completed",P123<>"",Q123<>""),IF(AND(T123="Late",X123="Yes",W123="Yes"),"Excluded (validated delay)","Yes"),"No") -> No | Z123: Target date missing; Priority missing (mandatory); Open > 6 months - review; Multiple assignees in one cell - split; confirm owner and contribution %
A124: 77 | B124: PRJ-047 | C124: Daily & Monthly PNL Report | D124: PRJ-047-T01 | E124: Design, Testing | F124: Sahil Sharma | G124: EMP-0221 | H124: Sahil Sharma | I124: Exact match | J124: Contributor | K124: 0.5 | L124: Client Support | M124: Kapil Abrol | O124: 46099 | R124: Not Started | S124: Not Started | T124: =IF(P124="","No deadline",IF(Q124<>"",IF(Q124>P124,"Late","On time"),IF(README!$B$4>P124,"Overdue","Open"))) -> No deadline | U124: Internal dependency (Product/Development) | V124: Pending at development P2 | X124: Yes | Y124: =IF(AND(S124="Completed",P124<>"",Q124<>""),IF(AND(T124="Late",X124="Yes",W124="Yes"),"Excluded (validated delay)","Yes"),"No") -> No | Z124: Target date missing; Priority missing (mandatory); Open > 6 months - review; Multiple assignees in one cell - split; confirm owner and contribution %
A125: 78 | B125: PRJ-047 | C125: Daily & Monthly PNL Report | D125: PRJ-047-T02 | E125: Co-ordination with product | F125: Adity | G125: EMP-0237 | H125: Adity Chiba | I125: First name only | J125: Contributor | K125: 0.5 | L125: Client Support | M125: Kapil Abrol | O125: 46099 | R125: Not Started | S125: Not Started | T125: =IF(P125="","No deadline",IF(Q125<>"",IF(Q125>P125,"Late","On time"),IF(README!$B$4>P125,"Overdue","Open"))) -> No deadline | U125: Internal dependency (Product/Development) | V125: Pending at development P2 | X125: Yes | Y125: =IF(AND(S125="Completed",P125<>"",Q125<>""),IF(AND(T125="Late",X125="Yes",W125="Yes"),"Excluded (validated delay)","Yes"),"No") -> No | Z125: Target date missing; Priority missing (mandatory); Open > 6 months - review; Multiple assignees in one cell - split; confirm owner and contribution %
A126: 78 | B126: PRJ-047 | C126: Daily & Monthly PNL Report | D126: PRJ-047-T02 | E126: Co-ordination with product | F126: Sahil Sharma | G126: EMP-0221 | H126: Sahil Sharma | I126: Exact match | J126: Contributor | K126: 0.5 | L126: Client Support | M126: Kapil Abrol | O126: 46099 | R126: Not Started | S126: Not Started | T126: =IF(P126="","No deadline",IF(Q126<>"",IF(Q126>P126,"Late","On time"),IF(README!$B$4>P126,"Overdue","Open"))) -> No deadline | U126: Internal dependency (Product/Development) | V126: Pending at development P2 | X126: Yes | Y126: =IF(AND(S126="Completed",P126<>"",Q126<>""),IF(AND(T126="Late",X126="Yes",W126="Yes"),"Excluded (validated delay)","Yes"),"No") -> No | Z126: Target date missing; Priority missing (mandatory); Open > 6 months - review; Multiple assignees in one cell - split; confirm owner and contribution %
A127: 79 | B127: PRJ-047 | C127: Daily & Monthly PNL Report | D127: PRJ-047-T03 | E127: Implementation sign off | F127: Adity | G127: EMP-0237 | H127: Adity Chiba | I127: First name only | J127: Contributor | K127: 0.5 | L127: Client Support | M127: Kapil Abrol | O127: 46099 | R127: Not Started | S127: Not Started | T127: =IF(P127="","No deadline",IF(Q127<>"",IF(Q127>P127,"Late","On time"),IF(README!$B$4>P127,"Overdue","Open"))) -> No deadline | U127: Internal dependency (Product/Development) | V127: Pending at development P2 | X127: Yes | Y127: =IF(AND(S127="Completed",P127<>"",Q127<>""),IF(AND(T127="Late",X127="Yes",W127="Yes"),"Excluded (validated delay)","Yes"),"No") -> No | Z127: Target date missing; Priority missing (mandatory); Open > 6 months - review; Multiple assignees in one cell - split; confirm owner and contribution %
A128: 79 | B128: PRJ-047 | C128: Daily & Monthly PNL Report | D128: PRJ-047-T03 | E128: Implementation sign off | F128: Sahil Sharma | G128: EMP-0221 | H128: Sahil Sharma | I128: Exact match | J128: Contributor | K128: 0.5 | L128: Client Support | M128: Kapil Abrol | O128: 46099 | R128: Not Started | S128: Not Started | T128: =IF(P128="","No deadline",IF(Q128<>"",IF(Q128>P128,"Late","On time"),IF(README!$B$4>P128,"Overdue","Open"))) -> No deadline | U128: Internal dependency (Product/Development) | V128: Pending at development P2 | X128: Yes | Y128: =IF(AND(S128="Completed",P128<>"",Q128<>""),IF(AND(T128="Late",X128="Yes",W128="Yes"),"Excluded (validated delay)","Yes"),"No") -> No | Z128: Target date missing; Priority missing (mandatory); Open > 6 months - review; Multiple assignees in one cell - split; confirm owner and contribution %
A129: 80 | B129: PRJ-048 | C129: Frequency is not available for Mutual fund SIP | D129: PRJ-048-T01 | E129: Design, Testing | F129: Sahil Sharma | G129: EMP-0221 | H129: Sahil Sharma | I129: Exact match | J129: Owner | K129: 1 | L129: Client Support | M129: Kapil Abrol | O129: 46113 | R129: Delayed | S129: In Progress | T129: =IF(P129="","No deadline",IF(Q129<>"",IF(Q129>P129,"Late","On time"),IF(README!$B$4>P129,"Overdue","Open"))) -> No deadline | U129: Technical issue | V129: Frequecy option NA during weekends | X129: No | Y129: =IF(AND(S129="Completed",P129<>"",Q129<>""),IF(AND(T129="Late",X129="Yes",W129="Yes"),"Excluded (validated delay)","Yes"),"No") -> No | Z129: Target date missing; Priority missing (mandatory); Open > 6 months - review; "Delayed" is now derived from dates, not a status
A130: 81 | B130: PRJ-048 | C130: Frequency is not available for Mutual fund SIP | D130: PRJ-048-T02 | E130: Co-ordination with product | F130: Sahil Sharma | G130: EMP-0221 | H130: Sahil Sharma | I130: Exact match | J130: Owner | K130: 1 | L130: Client Support | M130: Kapil Abrol | O130: 46113 | R130: Delayed | S130: In Progress | T130: =IF(P130="","No deadline",IF(Q130<>"",IF(Q130>P130,"Late","On time"),IF(README!$B$4>P130,"Overdue","Open"))) -> No deadline | U130: Technical issue | V130: Frequecy option NA during weekends | X130: No | Y130: =IF(AND(S130="Completed",P130<>"",Q130<>""),IF(AND(T130="Late",X130="Yes",W130="Yes"),"Excluded (validated delay)","Yes"),"No") -> No | Z130: Target date missing; Priority missing (mandatory); Open > 6 months - review; "Delayed" is now derived from dates, not a status
A131: 82 | B131: PRJ-048 | C131: Frequency is not available for Mutual fund SIP | D131: PRJ-048-T03 | E131: Implementation sign off | F131: Sahil Sharma | G131: EMP-0221 | H131: Sahil Sharma | I131: Exact match | J131: Owner | K131: 1 | L131: Client Support | M131: Kapil Abrol | O131: 46113 | R131: Delayed | S131: In Progress | T131: =IF(P131="","No deadline",IF(Q131<>"",IF(Q131>P131,"Late","On time"),IF(README!$B$4>P131,"Overdue","Open"))) -> No deadline | U131: Technical issue | V131: Frequecy option NA during weekends | X131: No | Y131: =IF(AND(S131="Completed",P131<>"",Q131<>""),IF(AND(T131="Late",X131="Yes",W131="Yes"),"Excluded (validated delay)","Yes"),"No") -> No | Z131: Target date missing; Priority missing (mandatory); Open > 6 months - review; "Delayed" is now derived from dates, not a status
A132: 83 | B132: PRJ-049 | C132: Mismatch LTP on Shoonya - Options before 9.15am | D132: PRJ-049-T01 | E132: Design, Testing | F132: Sahil Sharma | G132: EMP-0221 | H132: Sahil Sharma | I132: Exact match | J132: Owner | K132: 1 | L132: Client Support | M132: Kapil Abrol | O132: 46133 | R132: Ongoing | S132: In Progress | T132: =IF(P132="","No deadline",IF(Q132<>"",IF(Q132>P132,"Late","On time"),IF(README!$B$4>P132,"Overdue","Open"))) -> No deadline | U132: Not a blocker - status note | Y132: =IF(AND(S132="Completed",P132<>"",Q132<>""),IF(AND(T132="Late",X132="Yes",W132="Yes"),"Excluded (validated delay)","Yes"),"No") -> No | Z132: Target date missing; Priority missing (mandatory)
A133: 84 | B133: PRJ-049 | C133: Mismatch LTP on Shoonya - Options before 9.15am | D133: PRJ-049-T02 | E133: Co-ordination with product | F133: Sahil Sharma | G133: EMP-0221 | H133: Sahil Sharma | I133: Exact match | J133: Owner | K133: 1 | L133: Client Support | M133: Kapil Abrol | O133: 46133 | R133: Ongoing | S133: In Progress | T133: =IF(P133="","No deadline",IF(Q133<>"",IF(Q133>P133,"Late","On time"),IF(README!$B$4>P133,"Overdue","Open"))) -> No deadline | U133: Not a blocker - status note | Y133: =IF(AND(S133="Completed",P133<>"",Q133<>""),IF(AND(T133="Late",X133="Yes",W133="Yes"),"Excluded (validated delay)","Yes"),"No") -> No | Z133: Target date missing; Priority missing (mandatory)
A134: 85 | B134: PRJ-049 | C134: Mismatch LTP on Shoonya - Options before 9.15am | D134: PRJ-049-T03 | E134: Implementation sign off | F134: Sahil Sharma | G134: EMP-0221 | H134: Sahil Sharma | I134: Exact match | J134: Owner | K134: 1 | L134: Client Support | M134: Kapil Abrol | O134: 46133 | R134: Ongoing | S134: In Progress | T134: =IF(P134="","No deadline",IF(Q134<>"",IF(Q134>P134,"Late","On time"),IF(README!$B$4>P134,"Overdue","Open"))) -> No deadline | U134: Not a blocker - status note | Y134: =IF(AND(S134="Completed",P134<>"",Q134<>""),IF(AND(T134="Late",X134="Yes",W134="Yes"),"Excluded (validated delay)","Yes"),"No") -> No | Z134: Target date missing; Priority missing (mandatory)
A135: 86 | B135: PRJ-050 | C135: EGR - EGR Segment Enablement on Shoonya Platform | D135: PRJ-050-T01 | E135: Design, Testing | F135: Adity Chhiba | G135: EMP-0237 | H135: Adity Chiba | I135: Spelling differs (Chhiba vs Chiba) | J135: Owner | K135: 1 | L135: Client Support | M135: Kapil Abrol | O135: 46154 | R135: Not Started | S135: Not Started | T135: =IF(P135="","No deadline",IF(Q135<>"",IF(Q135>P135,"Late","On time"),IF(README!$B$4>P135,"Overdue","Open"))) -> No deadline | Y135: =IF(AND(S135="Completed",P135<>"",Q135<>""),IF(AND(T135="Late",X135="Yes",W135="Yes"),"Excluded (validated delay)","Yes"),"No") -> No | Z135: Target date missing; Priority missing (mandatory)
A136: 87 | B136: PRJ-050 | C136: EGR - EGR Segment Enablement on Shoonya Platform | D136: PRJ-050-T02 | E136: Co-ordination with product | F136: Adity Chhiba | G136: EMP-0237 | H136: Adity Chiba | I136: Spelling differs (Chhiba vs Chiba) | J136: Owner | K136: 1 | L136: Client Support | M136: Kapil Abrol | O136: 46154 | R136: Not Started | S136: Not Started | T136: =IF(P136="","No deadline",IF(Q136<>"",IF(Q136>P136,"Late","On time"),IF(README!$B$4>P136,"Overdue","Open"))) -> No deadline | Y136: =IF(AND(S136="Completed",P136<>"",Q136<>""),IF(AND(T136="Late",X136="Yes",W136="Yes"),"Excluded (validated delay)","Yes"),"No") -> No | Z136: Target date missing; Priority missing (mandatory)
A137: 88 | B137: PRJ-050 | C137: EGR - EGR Segment Enablement on Shoonya Platform | D137: PRJ-050-T03 | E137: Implementation sign off | F137: Adity Chhiba | G137: EMP-0237 | H137: Adity Chiba | I137: Spelling differs (Chhiba vs Chiba) | J137: Owner | K137: 1 | L137: Client Support | M137: Kapil Abrol | O137: 46154 | R137: Not Started | S137: Not Started | T137: =IF(P137="","No deadline",IF(Q137<>"",IF(Q137>P137,"Late","On time"),IF(README!$B$4>P137,"Overdue","Open"))) -> No deadline | Y137: =IF(AND(S137="Completed",P137<>"",Q137<>""),IF(AND(T137="Late",X137="Yes",W137="Yes"),"Excluded (validated delay)","Yes"),"No") -> No | Z137: Target date missing; Priority missing (mandatory)
A138: 89 | B138: PRJ-051 | C138: Best Price Execution of Equity Trades | D138: PRJ-051-T01 | E138: Design, Testing | F138: Sahil Sharma | G138: EMP-0221 | H138: Sahil Sharma | I138: Exact match | J138: Contributor | K138: 0.5 | L138: Client Support | M138: Kapil Abrol | O138: 46161 | Q138: 46254 | R138: Ongoing | S138: In Progress | T138: =IF(P138="","No deadline",IF(Q138<>"",IF(Q138>P138,"Late","On time"),IF(README!$B$4>P138,"Overdue","Open"))) -> No deadline | U138: Not a blocker - status note | Y138: =IF(AND(S138="Completed",P138<>"",Q138<>""),IF(AND(T138="Late",X138="Yes",W138="Yes"),"Excluded (validated delay)","Yes"),"No") -> No | Z138: Target date missing; Priority missing (mandatory); Has completed date but status is Ongoing; Multiple assignees in one cell - split; confirm owner and contribution %
A139: 89 | B139: PRJ-051 | C139: Best Price Execution of Equity Trades | D139: PRJ-051-T01 | E139: Design, Testing | F139: Jaspal | G139: EMP-0230 | H139: Jaspal | I139: Context: Client Support Team Lead (not Jaspal Kaur, jUMPP) | J139: Contributor | K139: 0.5 | L139: Client Support | M139: Kapil Abrol | O139: 46161 | Q139: 46254 | R139: Ongoing | S139: In Progress | T139: =IF(P139="","No deadline",IF(Q139<>"",IF(Q139>P139,"Late","On time"),IF(README!$B$4>P139,"Overdue","Open"))) -> No deadline | U139: Not a blocker - status note | Y139: =IF(AND(S139="Completed",P139<>"",Q139<>""),IF(AND(T139="Late",X139="Yes",W139="Yes"),"Excluded (validated delay)","Yes"),"No") -> No | Z139: Target date missing; Priority missing (mandatory); Has completed date but status is Ongoing; Multiple assignees in one cell - split; confirm owner and contribution %
A140: 90 | B140: PRJ-051 | C140: Best Price Execution of Equity Trades | D140: PRJ-051-T02 | E140: Co-ordination with product | F140: Sahil Sharma | G140: EMP-0221 | H140: Sahil Sharma | I140: Exact match | J140: Contributor | K140: 0.5 | L140: Client Support | M140: Kapil Abrol | O140: 46161 | Q140: 46254 | R140: Ongoing | S140: In Progress | T140: =IF(P140="","No deadline",IF(Q140<>"",IF(Q140>P140,"Late","On time"),IF(README!$B$4>P140,"Overdue","Open"))) -> No deadline | U140: Not a blocker - status note | Y140: =IF(AND(S140="Completed",P140<>"",Q140<>""),IF(AND(T140="Late",X140="Yes",W140="Yes"),"Excluded (validated delay)","Yes"),"No") -> No | Z140: Target date missing; Priority missing (mandatory); Has completed date but status is Ongoing; Multiple assignees in one cell - split; confirm owner and contribution %
A141: 90 | B141: PRJ-051 | C141: Best Price Execution of Equity Trades | D141: PRJ-051-T02 | E141: Co-ordination with product | F141: Jaspal | G141: EMP-0230 | H141: Jaspal | I141: Context: Client Support Team Lead (not Jaspal Kaur, jUMPP) | J141: Contributor | K141: 0.5 | L141: Client Support | M141: Kapil Abrol | O141: 46161 | Q141: 46254 | R141: Ongoing | S141: In Progress | T141: =IF(P141="","No deadline",IF(Q141<>"",IF(Q141>P141,"Late","On time"),IF(README!$B$4>P141,"Overdue","Open"))) -> No deadline | U141: Not a blocker - status note | Y141: =IF(AND(S141="Completed",P141<>"",Q141<>""),IF(AND(T141="Late",X141="Yes",W141="Yes"),"Excluded (validated delay)","Yes"),"No") -> No | Z141: Target date missing; Priority missing (mandatory); Has completed date but status is Ongoing; Multiple assignees in one cell - split; confirm owner and contribution %
...

Sheet Project_Register
A1: Project ID | B1: Project | C1: Department | D1: Owner | E1: Priority | F1: Assignment Rows | G1: Completed | H1: Blocked | I1: Late/Overdue | J1: Missing Deadline | K1: Flags
A2: PRJ-001 | B2: Loan Changes (Advance Salary) | C2: Product | D2: Pradeep Thakur | E2: High | F2: =COUNTIF(Tracker_Cleaned!$B$2:$B$176,A2) -> 1 | G2: =COUNTIFS(Tracker_Cleaned!$B$2:$B$176,A2,Tracker_Cleaned!$S$2:$S$176,"Completed") -> 1 | H2: =COUNTIFS(Tracker_Cleaned!$B$2:$B$176,A2,Tracker_Cleaned!$S$2:$S$176,"Blocked") -> 0 | I2: =COUNTIFS(Tracker_Cleaned!$B$2:$B$176,A2,Tracker_Cleaned!$T$2:$T$176,"Late")+COUNTIFS(Tracker_Cleaned!$B$2:$B$176,A2,Tracker_Cleaned!$T$2:$T$176,"Overdue") -> 0 | J2: =COUNTIFS(Tracker_Cleaned!$B$2:$B$176,A2,Tracker_Cleaned!$T$2:$T$176,"No deadline") -> 0
A3: PRJ-002 | B3: Trade.Shoonya Global Dashboard (Corporate actions) | C3: Product | D3: Pradeep Thakur | E3: High | F3: =COUNTIF(Tracker_Cleaned!$B$2:$B$176,A3) -> 1 | G3: =COUNTIFS(Tracker_Cleaned!$B$2:$B$176,A3,Tracker_Cleaned!$S$2:$S$176,"Completed") -> 1 | H3: =COUNTIFS(Tracker_Cleaned!$B$2:$B$176,A3,Tracker_Cleaned!$S$2:$S$176,"Blocked") -> 0 | I3: =COUNTIFS(Tracker_Cleaned!$B$2:$B$176,A3,Tracker_Cleaned!$T$2:$T$176,"Late")+COUNTIFS(Tracker_Cleaned!$B$2:$B$176,A3,Tracker_Cleaned!$T$2:$T$176,"Overdue") -> 0 | J3: =COUNTIFS(Tracker_Cleaned!$B$2:$B$176,A3,Tracker_Cleaned!$T$2:$T$176,"No deadline") -> 0
A4: PRJ-003 | B4: Mobile-Trade.Shoonya Global Dashboard (Corporate actions) | C4: Product | D4: Pradeep Thakur | E4: High | F4: =COUNTIF(Tracker_Cleaned!$B$2:$B$176,A4) -> 1 | G4: =COUNTIFS(Tracker_Cleaned!$B$2:$B$176,A4,Tracker_Cleaned!$S$2:$S$176,"Completed") -> 1 | H4: =COUNTIFS(Tracker_Cleaned!$B$2:$B$176,A4,Tracker_Cleaned!$S$2:$S$176,"Blocked") -> 0 | I4: =COUNTIFS(Tracker_Cleaned!$B$2:$B$176,A4,Tracker_Cleaned!$T$2:$T$176,"Late")+COUNTIFS(Tracker_Cleaned!$B$2:$B$176,A4,Tracker_Cleaned!$T$2:$T$176,"Overdue") -> 0 | J4: =COUNTIFS(Tracker_Cleaned!$B$2:$B$176,A4,Tracker_Cleaned!$T$2:$T$176,"No deadline") -> 0
A5: PRJ-004 | B5: Shoonya R&R | C5: Product | D5: Pradeep Thakur | E5: High | F5: =COUNTIF(Tracker_Cleaned!$B$2:$B$176,A5) -> 1 | G5: =COUNTIFS(Tracker_Cleaned!$B$2:$B$176,A5,Tracker_Cleaned!$S$2:$S$176,"Completed") -> 0 | H5: =COUNTIFS(Tracker_Cleaned!$B$2:$B$176,A5,Tracker_Cleaned!$S$2:$S$176,"Blocked") -> 0 | I5: =COUNTIFS(Tracker_Cleaned!$B$2:$B$176,A5,Tracker_Cleaned!$T$2:$T$176,"Late")+COUNTIFS(Tracker_Cleaned!$B$2:$B$176,A5,Tracker_Cleaned!$T$2:$T$176,"Overdue") -> 0 | J5: =COUNTIFS(Tracker_Cleaned!$B$2:$B$176,A5,Tracker_Cleaned!$T$2:$T$176,"No deadline") -> 0
A6: PRJ-005 | B6: Trade Shoonya: Dark theme | C6: Product | D6: Pradeep Thakur | E6: Medium | F6: =COUNTIF(Tracker_Cleaned!$B$2:$B$176,A6) -> 1 | G6: =COUNTIFS(Tracker_Cleaned!$B$2:$B$176,A6,Tracker_Cleaned!$S$2:$S$176,"Completed") -> 0 | H6: =COUNTIFS(Tracker_Cleaned!$B$2:$B$176,A6,Tracker_Cleaned!$S$2:$S$176,"Blocked") -> 0 | I6: =COUNTIFS(Tracker_Cleaned!$B$2:$B$176,A6,Tracker_Cleaned!$T$2:$T$176,"Late")+COUNTIFS(Tracker_Cleaned!$B$2:$B$176,A6,Tracker_Cleaned!$T$2:$T$176,"Overdue") -> 1 | J6: =COUNTIFS(Tracker_Cleaned!$B$2:$B$176,A6,Tracker_Cleaned!$T$2:$T$176,"No deadline") -> 0
A7: PRJ-006 | B7: Jumpp R&R | C7: Product | D7: Pradeep Thakur | E7: High | F7: =COUNTIF(Tracker_Cleaned!$B$2:$B$176,A7) -> 1 | G7: =COUNTIFS(Tracker_Cleaned!$B$2:$B$176,A7,Tracker_Cleaned!$S$2:$S$176,"Completed") -> 0 | H7: =COUNTIFS(Tracker_Cleaned!$B$2:$B$176,A7,Tracker_Cleaned!$S$2:$S$176,"Blocked") -> 0 | I7: =COUNTIFS(Tracker_Cleaned!$B$2:$B$176,A7,Tracker_Cleaned!$T$2:$T$176,"Late")+COUNTIFS(Tracker_Cleaned!$B$2:$B$176,A7,Tracker_Cleaned!$T$2:$T$176,"Overdue") -> 1 | J7: =COUNTIFS(Tracker_Cleaned!$B$2:$B$176,A7,Tracker_Cleaned!$T$2:$T$176,"No deadline") -> 0
A8: PRJ-007 | B8: Rewards Journey UI (Milestones or Campaign) | C8: Product | D8: Pradeep Thakur | E8: High | F8: =COUNTIF(Tracker_Cleaned!$B$2:$B$176,A8) -> 1 | G8: =COUNTIFS(Tracker_Cleaned!$B$2:$B$176,A8,Tracker_Cleaned!$S$2:$S$176,"Completed") -> 0 | H8: =COUNTIFS(Tracker_Cleaned!$B$2:$B$176,A8,Tracker_Cleaned!$S$2:$S$176,"Blocked") -> 0 | I8: =COUNTIFS(Tracker_Cleaned!$B$2:$B$176,A8,Tracker_Cleaned!$T$2:$T$176,"Late")+COUNTIFS(Tracker_Cleaned!$B$2:$B$176,A8,Tracker_Cleaned!$T$2:$T$176,"Overdue") -> 1 | J8: =COUNTIFS(Tracker_Cleaned!$B$2:$B$176,A8,Tracker_Cleaned!$T$2:$T$176,"No deadline") -> 0
A9: PRJ-008 | B9: Digital Silver | C9: Product | D9: Pradeep Thakur | E9: High | F9: =COUNTIF(Tracker_Cleaned!$B$2:$B$176,A9) -> 1 | G9: =COUNTIFS(Tracker_Cleaned!$B$2:$B$176,A9,Tracker_Cleaned!$S$2:$S$176,"Completed") -> 0 | H9: =COUNTIFS(Tracker_Cleaned!$B$2:$B$176,A9,Tracker_Cleaned!$S$2:$S$176,"Blocked") -> 0 | I9: =COUNTIFS(Tracker_Cleaned!$B$2:$B$176,A9,Tracker_Cleaned!$T$2:$T$176,"Late")+COUNTIFS(Tracker_Cleaned!$B$2:$B$176,A9,Tracker_Cleaned!$T$2:$T$176,"Overdue") -> 1 | J9: =COUNTIFS(Tracker_Cleaned!$B$2:$B$176,A9,Tracker_Cleaned!$T$2:$T$176,"No deadline") -> 0
A10: PRJ-009 | B10: Digital Silver SIP | C10: Product | D10: Pradeep Thakur | E10: High | F10: =COUNTIF(Tracker_Cleaned!$B$2:$B$176,A10) -> 1 | G10: =COUNTIFS(Tracker_Cleaned!$B$2:$B$176,A10,Tracker_Cleaned!$S$2:$S$176,"Completed") -> 0 | H10: =COUNTIFS(Tracker_Cleaned!$B$2:$B$176,A10,Tracker_Cleaned!$S$2:$S$176,"Blocked") -> 0 | I10: =COUNTIFS(Tracker_Cleaned!$B$2:$B$176,A10,Tracker_Cleaned!$T$2:$T$176,"Late")+COUNTIFS(Tracker_Cleaned!$B$2:$B$176,A10,Tracker_Cleaned!$T$2:$T$176,"Overdue") -> 1 | J10: =COUNTIFS(Tracker_Cleaned!$B$2:$B$176,A10,Tracker_Cleaned!$T$2:$T$176,"No deadline") -> 0
A11: PRJ-010 | B11: Digital Gold SIP | C11: Product | D11: Pradeep Thakur | E11: High | F11: =COUNTIF(Tracker_Cleaned!$B$2:$B$176,A11) -> 1 | G11: =COUNTIFS(Tracker_Cleaned!$B$2:$B$176,A11,Tracker_Cleaned!$S$2:$S$176,"Completed") -> 0 | H11: =COUNTIFS(Tracker_Cleaned!$B$2:$B$176,A11,Tracker_Cleaned!$S$2:$S$176,"Blocked") -> 0 | I11: =COUNTIFS(Tracker_Cleaned!$B$2:$B$176,A11,Tracker_Cleaned!$T$2:$T$176,"Late")+COUNTIFS(Tracker_Cleaned!$B$2:$B$176,A11,Tracker_Cleaned!$T$2:$T$176,"Overdue") -> 1 | J11: =COUNTIFS(Tracker_Cleaned!$B$2:$B$176,A11,Tracker_Cleaned!$T$2:$T$176,"No deadline") -> 0
A12: PRJ-011 | B12: Physical Silver | C12: Product | D12: Pradeep Thakur | E12: High | F12: =COUNTIF(Tracker_Cleaned!$B$2:$B$176,A12) -> 1 | G12: =COUNTIFS(Tracker_Cleaned!$B$2:$B$176,A12,Tracker_Cleaned!$S$2:$S$176,"Completed") -> 0 | H12: =COUNTIFS(Tracker_Cleaned!$B$2:$B$176,A12,Tracker_Cleaned!$S$2:$S$176,"Blocked") -> 0 | I12: =COUNTIFS(Tracker_Cleaned!$B$2:$B$176,A12,Tracker_Cleaned!$T$2:$T$176,"Late")+COUNTIFS(Tracker_Cleaned!$B$2:$B$176,A12,Tracker_Cleaned!$T$2:$T$176,"Overdue") -> 1 | J12: =COUNTIFS(Tracker_Cleaned!$B$2:$B$176,A12,Tracker_Cleaned!$T$2:$T$176,"No deadline") -> 0
A13: PRJ-012 | B13: Physical Gold | C13: Product | D13: Pradeep Thakur | E13: High | F13: =COUNTIF(Tracker_Cleaned!$B$2:$B$176,A13) -> 1 | G13: =COUNTIFS(Tracker_Cleaned!$B$2:$B$176,A13,Tracker_Cleaned!$S$2:$S$176,"Completed") -> 0 | H13: =COUNTIFS(Tracker_Cleaned!$B$2:$B$176,A13,Tracker_Cleaned!$S$2:$S$176,"Blocked") -> 0 | I13: =COUNTIFS(Tracker_Cleaned!$B$2:$B$176,A13,Tracker_Cleaned!$T$2:$T$176,"Late")+COUNTIFS(Tracker_Cleaned!$B$2:$B$176,A13,Tracker_Cleaned!$T$2:$T$176,"Overdue") -> 1 | J13: =COUNTIFS(Tracker_Cleaned!$B$2:$B$176,A13,Tracker_Cleaned!$T$2:$T$176,"No deadline") -> 0
... A30: PRJ-029 | B30: Buyback Feature Implementation | C30: Operations & BO | D30: Pawan | E30: Medium | F30: =COUNTIF(Tracker_Cleaned!$B$2:$B$176,A30) -> 2 | G30: =COUNTIFS(Tracker_Cleaned!$B$2:$B$176,A30,Tracker_Cleaned!$S$2:$S$176,"Completed") -> 0 | H30: =COUNTIFS(Tracker_Cleaned!$B$2:$B$176,A30,Tracker_Cleaned!$S$2:$S$176,"Blocked") -> 0 | I30: =COUNTIFS(Tracker_Cleaned!$B$2:$B$176,A30,Tracker_Cleaned!$T$2:$T$176,"Late")+COUNTIFS(Tracker_Cleaned!$B$2:$B$176,A30,Tracker_Cleaned!$T$2:$T$176,"Overdue") -> 0 | J30: =COUNTIFS(Tracker_Cleaned!$B$2:$B$176,A30,Tracker_Cleaned!$T$2:$T$176,"No deadline") -> 2
A31: PRJ-030 | B31: SenS-AI 1.1 Enhancement | C31: Product | E31: High | F31: =COUNTIF(Tracker_Cleaned!$B$2:$B$176,A31) -> 5 | G31: =COUNTIFS(Tracker_Cleaned!$B$2:$B$176,A31,Tracker_Cleaned!$S$2:$S$176,"Completed") -> 0 | H31: =COUNTIFS(Tracker_Cleaned!$B$2:$B$176,A31,Tracker_Cleaned!$S$2:$S$176,"Blocked") -> 5 | I31: =COUNTIFS(Tracker_Cleaned!$B$2:$B$176,A31,Tracker_Cleaned!$T$2:$T$176,"Late")+COUNTIFS(Tracker_Cleaned!$B$2:$B$176,A31,Tracker_Cleaned!$T$2:$T$176,"Overdue") -> 5 | J31: =COUNTIFS(Tracker_Cleaned!$B$2:$B$176,A31,Tracker_Cleaned!$T$2:$T$176,"No deadline") -> 0 | K31: Set owner
A32: PRJ-031 | B32: fno Edge | C32: Product | E32: High | F32: =COUNTIF(Tracker_Cleaned!$B$2:$B$176,A32) -> 4 | G32: =COUNTIFS(Tracker_Cleaned!$B$2:$B$176,A32,Tracker_Cleaned!$S$2:$S$176,"Completed") -> 0 | H32: =COUNTIFS(Tracker_Cleaned!$B$2:$B$176,A32,Tracker_Cleaned!$S$2:$S$176,"Blocked") -> 0 | I32: =COUNTIFS(Tracker_Cleaned!$B$2:$B$176,A32,Tracker_Cleaned!$T$2:$T$176,"Late")+COUNTIFS(Tracker_Cleaned!$B$2:$B$176,A32,Tracker_Cleaned!$T$2:$T$176,"Overdue") -> 4 | J32: =COUNTIFS(Tracker_Cleaned!$B$2:$B$176,A32,Tracker_Cleaned!$T$2:$T$176,"No deadline") -> 0 | K32: Set owner
A33: PRJ-032 | B33: Automating the current PRISM process | C33: Product | E33: Medium | F33: =COUNTIF(Tracker_Cleaned!$B$2:$B$176,A33) -> 3 | G33: =COUNTIFS(Tracker_Cleaned!$B$2:$B$176,A33,Tracker_Cleaned!$S$2:$S$176,"Completed") -> 0 | H33: =COUNTIFS(Tracker_Cleaned!$B$2:$B$176,A33,Tracker_Cleaned!$S$2:$S$176,"Blocked") -> 0 | I33: =COUNTIFS(Tracker_Cleaned!$B$2:$B$176,A33,Tracker_Cleaned!$T$2:$T$176,"Late")+COUNTIFS(Tracker_Cleaned!$B$2:$B$176,A33,Tracker_Cleaned!$T$2:$T$176,"Overdue") -> 0 | J33: =COUNTIFS(Tracker_Cleaned!$B$2:$B$176,A33,Tracker_Cleaned!$T$2:$T$176,"No deadline") -> 0 | K33: Set owner
A34: PRJ-033 | B34: MTF Margin increase | C34: Product | E34: High | F34: =COUNTIF(Tracker_Cleaned!$B$2:$B$176,A34) -> 3 | G34: =COUNTIFS(Tracker_Cleaned!$B$2:$B$176,A34,Tracker_Cleaned!$S$2:$S$176,"Completed") -> 0 | H34: =COUNTIFS(Tracker_Cleaned!$B$2:$B$176,A34,Tracker_Cleaned!$S$2:$S$176,"Blocked") -> 0 | I34: =COUNTIFS(Tracker_Cleaned!$B$2:$B$176,A34,Tracker_Cleaned!$T$2:$T$176,"Late")+COUNTIFS(Tracker_Cleaned!$B$2:$B$176,A34,Tracker_Cleaned!$T$2:$T$176,"Overdue") -> 3 | J34: =COUNTIFS(Tracker_Cleaned!$B$2:$B$176,A34,Tracker_Cleaned!$T$2:$T$176,"No deadline") -> 0 | K34: Set owner
A35: PRJ-034 | B35: Build API / Algo Trading landing page (Shoonya) | C35: Product | E35: High | F35: =COUNTIF(Tracker_Cleaned!$B$2:$B$176,A35) -> 2 | G35: =COUNTIFS(Tracker_Cleaned!$B$2:$B$176,A35,Tracker_Cleaned!$S$2:$S$176,"Completed") -> 0 | H35: =COUNTIFS(Tracker_Cleaned!$B$2:$B$176,A35,Tracker_Cleaned!$S$2:$S$176,"Blocked") -> 0 | I35: =COUNTIFS(Tracker_Cleaned!$B$2:$B$176,A35,Tracker_Cleaned!$T$2:$T$176,"Late")+COUNTIFS(Tracker_Cleaned!$B$2:$B$176,A35,Tracker_Cleaned!$T$2:$T$176,"Overdue") -> 2 | J35: =COUNTIFS(Tracker_Cleaned!$B$2:$B$176,A35,Tracker_Cleaned!$T$2:$T$176,"No deadline") -> 0 | K35: Set owner
A36: PRJ-035 | B36: Backend will push market data as user attributes for all users, updated 4 times daily, enabling automated and broadcast push notifications | C36: Product | E36: High | F36: =COUNTIF(Tracker_Cleaned!$B$2:$B$176,A36) -> 3 | G36: =COUNTIFS(Tracker_Cleaned!$B$2:$B$176,A36,Tracker_Cleaned!$S$2:$S$176,"Completed") -> 0 | H36: =COUNTIFS(Tracker_Cleaned!$B$2:$B$176,A36,Tracker_Cleaned!$S$2:$S$176,"Blocked") -> 0 | I36: =COUNTIFS(Tracker_Cleaned!$B$2:$B$176,A36,Tracker_Cleaned!$T$2:$T$176,"Late")+COUNTIFS(Tracker_Cleaned!$B$2:$B$176,A36,Tracker_Cleaned!$T$2:$T$176,"Overdue") -> 3 | J36: =COUNTIFS(Tracker_Cleaned!$B$2:$B$176,A36,Tracker_Cleaned!$T$2:$T$176,"No deadline") -> 0 | K36: Set owner
A37: PRJ-036 | B37: CRM Sourcing, Testing & Implementation | C37: Client Support | D37: Kapil Abrol | F37: =COUNTIF(Tracker_Cleaned!$B$2:$B$176,A37) -> 9 | G37: =COUNTIFS(Tracker_Cleaned!$B$2:$B$176,A37,Tracker_Cleaned!$S$2:$S$176,"Completed") -> 0 | H37: =COUNTIFS(Tracker_Cleaned!$B$2:$B$176,A37,Tracker_Cleaned!$S$2:$S$176,"Blocked") -> 0 | I37: =COUNTIFS(Tracker_Cleaned!$B$2:$B$176,A37,Tracker_Cleaned!$T$2:$T$176,"Late")+COUNTIFS(Tracker_Cleaned!$B$2:$B$176,A37,Tracker_Cleaned!$T$2:$T$176,"Overdue") -> 3 | J37: =COUNTIFS(Tracker_Cleaned!$B$2:$B$176,A37,Tracker_Cleaned!$T$2:$T$176,"No deadline") -> 6 | K37: Set priority
A38: PRJ-037 | B38: AI Bots Testing & Implementation | C38: Client Support | D38: Kapil Abrol | F38: =COUNTIF(Tracker_Cleaned!$B$2:$B$176,A38) -> 9 | G38: =COUNTIFS(Tracker_Cleaned!$B$2:$B$176,A38,Tracker_Cleaned!$S$2:$S$176,"Completed") -> 0 | H38: =COUNTIFS(Tracker_Cleaned!$B$2:$B$176,A38,Tracker_Cleaned!$S$2:$S$176,"Blocked") -> 0 | I38: =COUNTIFS(Tracker_Cleaned!$B$2:$B$176,A38,Tracker_Cleaned!$T$2:$T$176,"Late")+COUNTIFS(Tracker_Cleaned!$B$2:$B$176,A38,Tracker_Cleaned!$T$2:$T$176,"Overdue") -> 0 | J38: =COUNTIFS(Tracker_Cleaned!$B$2:$B$176,A38,Tracker_Cleaned!$T$2:$T$176,"No deadline") -> 9 | K38: Set priority
A39: PRJ-038 | B39: AI Triage Process | C39: Client Support | D39: Kapil Abrol | F39: =COUNTIF(Tracker_Cleaned!$B$2:$B$176,A39) -> 6 | G39: =COUNTIFS(Tracker_Cleaned!$B$2:$B$176,A39,Tracker_Cleaned!$S$2:$S$176,"Completed") -> 0 | H39: =COUNTIFS(Tracker_Cleaned!$B$2:$B$176,A39,Tracker_Cleaned!$S$2:$S$176,"Blocked") -> 0 | I39: =COUNTIFS(Tracker_Cleaned!$B$2:$B$176,A39,Tracker_Cleaned!$T$2:$T$176,"Late")+COUNTIFS(Tracker_Cleaned!$B$2:$B$176,A39,Tracker_Cleaned!$T$2:$T$176,"Overdue") -> 0 | J39: =COUNTIFS(Tracker_Cleaned!$B$2:$B$176,A39,Tracker_Cleaned!$T$2:$T$176,"No deadline") -> 6 | K39: Set priority
A40: PRJ-039 | B40: QA & ATA Audit Platform | C40: Client Support | D40: Kapil Abrol | F40: =COUNTIF(Tracker_Cleaned!$B$2:$B$176,A40) -> 6 | G40: =COUNTIFS(Tracker_Cleaned!$B$2:$B$176,A40,Tracker_Cleaned!$S$2:$S$176,"Completed") -> 0 | H40: =COUNTIFS(Tracker_Cleaned!$B$2:$B$176,A40,Tracker_Cleaned!$S$2:$S$176,"Blocked") -> 0 | I40: =COUNTIFS(Tracker_Cleaned!$B$2:$B$176,A40,Tracker_Cleaned!$T$2:$T$176,"Late")+COUNTIFS(Tracker_Cleaned!$B$2:$B$176,A40,Tracker_Cleaned!$T$2:$T$176,"Overdue") -> 0 | J40: =COUNTIFS(Tracker_Cleaned!$B$2:$B$176,A40,Tracker_Cleaned!$T$2:$T$176,"No deadline") -> 6 | K40: Set priority
A41: PRJ-040 | B41: CSAT & ACPT Audit and Reporting Platform | C41: Client Support | D41: Kapil Abrol | F41: =COUNTIF(Tracker_Cleaned!$B$2:$B$176,A41) -> 9 | G41: =COUNTIFS(Tracker_Cleaned!$B$2:$B$176,A41,Tracker_Cleaned!$S$2:$S$176,"Completed") -> 0 | H41: =COUNTIFS(Tracker_Cleaned!$B$2:$B$176,A41,Tracker_Cleaned!$S$2:$S$176,"Blocked") -> 0 | I41: =COUNTIFS(Tracker_Cleaned!$B$2:$B$176,A41,Tracker_Cleaned!$T$2:$T$176,"Late")+COUNTIFS(Tracker_Cleaned!$B$2:$B$176,A41,Tracker_Cleaned!$T$2:$T$176,"Overdue") -> 0 | J41: =COUNTIFS(Tracker_Cleaned!$B$2:$B$176,A41,Tracker_Cleaned!$T$2:$T$176,"No deadline") -> 9 | K41: Set priority
A42: PRJ-041 | B42: Training Portal & Executive CSAT Reporting | C42: Client Support | D42: Kapil Abrol | F42: =COUNTIF(Tracker_Cleaned!$B$2:$B$176,A42) -> 6 | G42: =COUNTIFS(Tracker_Cleaned!$B$2:$B$176,A42,Tracker_Cleaned!$S$2:$S$176,"Completed") -> 0 | H42: =COUNTIFS(Tracker_Cleaned!$B$2:$B$176,A42,Tracker_Cleaned!$S$2:$S$176,"Blocked") -> 0 | I42: =COUNTIFS(Tracker_Cleaned!$B$2:$B$176,A42,Tracker_Cleaned!$T$2:$T$176,"Late")+COUNTIFS(Tracker_Cleaned!$B$2:$B$176,A42,Tracker_Cleaned!$T$2:$T$176,"Overdue") -> 0 | J42: =COUNTIFS(Tracker_Cleaned!$B$2:$B$176,A42,Tracker_Cleaned!$T$2:$T$176,"No deadline") -> 6 | K42: Set priority
A43: PRJ-042 | B43: Mutual Fund mandate issue | C43: Client Support | D43: Kapil Abrol | F43: =COUNTIF(Tracker_Cleaned!$B$2:$B$176,A43) -> 3 | G43: =COUNTIFS(Tracker_Cleaned!$B$2:$B$176,A43,Tracker_Cleaned!$S$2:$S$176,"Completed") -> 0 | H43: =COUNTIFS(Tracker_Cleaned!$B$2:$B$176,A43,Tracker_Cleaned!$S$2:$S$176,"Blocked") -> 0 | I43: =COUNTIFS(Tracker_Cleaned!$B$2:$B$176,A43,Tracker_Cleaned!$T$2:$T$176,"Late")+COUNTIFS(Tracker_Cleaned!$B$2:$B$176,A43,Tracker_Cleaned!$T$2:$T$176,"Overdue") -> 0 | J43: =COUNTIFS(Tracker_Cleaned!$B$2:$B$176,A43,Tracker_Cleaned!$T$2:$T$176,"No deadline") -> 3 | K43: Set priority
A44: PRJ-043 | B44: Multiple Issues in Enable Exchange KYC | C44: Client Support | D44: Kapil Abrol | F44: =COUNTIF(Tracker_Cleaned!$B$2:$B$176,A44) -> 6 | G44: =COUNTIFS(Tracker_Cleaned!$B$2:$B$176,A44,Tracker_Cleaned!$S$2:$S$176,"Completed") -> 0 | H44: =COUNTIFS(Tracker_Cleaned!$B$2:$B$176,A44,Tracker_Cleaned!$S$2:$S$176,"Blocked") -> 0 | I44: =COUNTIFS(Tracker_Cleaned!$B$2:$B$176,A44,Tracker_Cleaned!$T$2:$T$176,"Late")+COUNTIFS(Tracker_Cleaned!$B$2:$B$176,A44,Tracker_Cleaned!$T$2:$T$176,"Overdue") -> 0 | J44: =COUNTIFS(Tracker_Cleaned!$B$2:$B$176,A44,Tracker_Cleaned!$T$2:$T$176,"No deadline") -> 6 | K44: Set priority
A45: PRJ-044 | B45: Chart issues | C45: Client Support | D45: Kapil Abrol | F45: =COUNTIF(Tracker_Cleaned!$B$2:$B$176,A45) -> 3 | G45: =COUNTIFS(Tracker_Cleaned!$B$2:$B$176,A45,Tracker_Cleaned!$S$2:$S$176,"Completed") -> 0 | H45: =COUNTIFS(Tracker_Cleaned!$B$2:$B$176,A45,Tracker_Cleaned!$S$2:$S$176,"Blocked") -> 0 | I45: =COUNTIFS(Tracker_Cleaned!$B$2:$B$176,A45,Tracker_Cleaned!$T$2:$T$176,"Late")+COUNTIFS(Tracker_Cleaned!$B$2:$B$176,A45,Tracker_Cleaned!$T$2:$T$176,"Overdue") -> 0 | J45: =COUNTIFS(Tracker_Cleaned!$B$2:$B$176,A45,Tracker_Cleaned!$T$2:$T$176,"No deadline") -> 3 | K45: Set priority
A46: PRJ-045 | B46: Introduction of Time-Based Validity Order Types | C46: Client Support | D46: Kapil Abrol | F46: =COUNTIF(Tracker_Cleaned!$B$2:$B$176,A46) -> 6 | G46: =COUNTIFS(Tracker_Cleaned!$B$2:$B$176,A46,Tracker_Cleaned!$S$2:$S$176,"Completed") -> 0 | H46: =COUNTIFS(Tracker_Cleaned!$B$2:$B$176,A46,Tracker_Cleaned!$S$2:$S$176,"Blocked") -> 6 | I46: =COUNTIFS(Tracker_Cleaned!$B$2:$B$176,A46,Tracker_Cleaned!$T$2:$T$176,"Late")+COUNTIFS(Tracker_Cleaned!$B$2:$B$176,A46,Tracker_Cleaned!$T$2:$T$176,"Overdue") -> 0 | J46: =COUNTIFS(Tracker_Cleaned!$B$2:$B$176,A46,Tracker_Cleaned!$T$2:$T$176,"No deadline") -> 6 | K46: Set priority
A47: PRJ-046 | B47: Incorrect update on App Store for Brokerage Charges | C47: Client Support | D47: Kapil Abrol | F47: =COUNTIF(Tracker_Cleaned!$B$2:$B$176,A47) -> 3 | G47: =COUNTIFS(Tracker_Cleaned!$B$2:$B$176,A47,Tracker_Cleaned!$S$2:$S$176,"Completed") -> 0 | H47: =COUNTIFS(Tracker_Cleaned!$B$2:$B$176,A47,Tracker_Cleaned!$S$2:$S$176,"Blocked") -> 0 | I47: =COUNTIFS(Tracker_Cleaned!$B$2:$B$176,A47,Tracker_Cleaned!$T$2:$T$176,"Late")+COUNTIFS(Tracker_Cleaned!$B$2:$B$176,A47,Tracker_Cleaned!$T$2:$T$176,"Overdue") -> 0 | J47: =COUNTIFS(Tracker_Cleaned!$B$2:$B$176,A47,Tracker_Cleaned!$T$2:$T$176,"No deadline") -> 3 | K47: Set priority
A48: PRJ-047 | B48: Daily & Monthly PNL Report | C48: Client Support | D48: Kapil Abrol | F48: =COUNTIF(Tracker_Cleaned!$B$2:$B$176,A48) -> 6 | G48: =COUNTIFS(Tracker_Cleaned!$B$2:$B$176,A48,Tracker_Cleaned!$S$2:$S$176,"Completed") -> 0 | H48: =COUNTIFS(Tracker_Cleaned!$B$2:$B$176,A48,Tracker_Cleaned!$S$2:$S$176,"Blocked") -> 0 | I48: =COUNTIFS(Tracker_Cleaned!$B$2:$B$176,A48,Tracker_Cleaned!$T$2:$T$176,"Late")+COUNTIFS(Tracker_Cleaned!$B$2:$B$176,A48,Tracker_Cleaned!$T$2:$T$176,"Overdue") -> 0 | J48: =COUNTIFS(Tracker_Cleaned!$B$2:$B$176,A48,Tracker_Cleaned!$T$2:$T$176,"No deadline") -> 6 | K48: Set priority
... A61: PRJ-060 | B61: MTF Activation Flow Revamp & User Journey Enhancement | C61: Client Support | D61: Kapil Abrol | F61: =COUNTIF(Tracker_Cleaned!$B$2:$B$176,A61) -> 6 | G61: =COUNTIFS(Tracker_Cleaned!$B$2:$B$176,A61,Tracker_Cleaned!$S$2:$S$176,"Completed") -> 0 | H61: =COUNTIFS(Tracker_Cleaned!$B$2:$B$176,A61,Tracker_Cleaned!$S$2:$S$176,"Blocked") -> 0 | I61: =COUNTIFS(Tracker_Cleaned!$B$2:$B$176,A61,Tracker_Cleaned!$T$2:$T$176,"Late")+COUNTIFS(Tracker_Cleaned!$B$2:$B$176,A61,Tracker_Cleaned!$T$2:$T$176,"Overdue") -> 0 | J61: =COUNTIFS(Tracker_Cleaned!$B$2:$B$176,A61,Tracker_Cleaned!$T$2:$T$176,"No deadline") -> 6 | K61: Set priority

Sheet OnTime_Recalc
A1: Emp ID | B1: Name | C1: Department | D1: Assignments | E1: Eligible Completed | F1: Completed On Time | G1: Late (counted) | H1: Excluded (validated delay) | I1: Corrected On-Time Rate | J1: On-Time Score (0-100) | K1: Old Sheet "SLA/TAT" Value | L1: Why it changed
A2: EMP-0082 | B2: Sachin Barnwal | C2: =IFERROR(INDEX(Employee_Master!$F:$F,MATCH(A2,Employee_Master!$A:$A,0)),"") -> Product | D2: =COUNTIF(Tracker_Cleaned!$G$2:$G$176,A2) -> 9 | E2: =COUNTIFS(Tracker_Cleaned!$G$2:$G$176,A2,Tracker_Cleaned!$Y$2:$Y$176,"Yes") -> 3 | F2: =COUNTIFS(Tracker_Cleaned!$G$2:$G$176,A2,Tracker_Cleaned!$Y$2:$Y$176,"Yes",Tracker_Cleaned!$T$2:$T$176,"On time") -> 3 | G2: =COUNTIFS(Tracker_Cleaned!$G$2:$G$176,A2,Tracker_Cleaned!$Y$2:$Y$176,"Yes",Tracker_Cleaned!$T$2:$T$176,"Late") -> 0 | H2: =COUNTIFS(Tracker_Cleaned!$G$2:$G$176,A2,Tracker_Cleaned!$Y$2:$Y$176,"Excluded (validated delay)") -> 0 | I2: =IF(E2<3,"Insufficient Data",F2/E2) -> 1 | J2: =IF(ISNUMBER(I2),MAX(0,MIN(100,IF(I2>=0.95,100,60+(I2-0.75)*200))),"Insufficient Data") -> 100 | K2: 0.6667 | L2: Old sheet counted On Hold / In Review tasks that had a completed date (SensAI, Shoonya MF, Shoonya R&R) and penalised the validated reprioritisation delay.
A3: EMP-0084 | B3: Harsh | C3: =IFERROR(INDEX(Employee_Master!$F:$F,MATCH(A3,Employee_Master!$A:$A,0)),"") -> Product | D3: =COUNTIF(Tracker_Cleaned!$G$2:$G$176,A3) -> 5 | E3: =COUNTIFS(Tracker_Cleaned!$G$2:$G$176,A3,Tracker_Cleaned!$Y$2:$Y$176,"Yes") -> 1 | F3: =COUNTIFS(Tracker_Cleaned!$G$2:$G$176,A3,Tracker_Cleaned!$Y$2:$Y$176,"Yes",Tracker_Cleaned!$T$2:$T$176,"On time") -> 1 | G3: =COUNTIFS(Tracker_Cleaned!$G$2:$G$176,A3,Tracker_Cleaned!$Y$2:$Y$176,"Yes",Tracker_Cleaned!$T$2:$T$176,"Late") -> 0 | H3: =COUNTIFS(Tracker_Cleaned!$G$2:$G$176,A3,Tracker_Cleaned!$Y$2:$Y$176,"Excluded (validated delay)") -> 0 | I3: =IF(E3<3,"Insufficient Data",F3/E3) -> Insufficient Data | J3: =IF(ISNUMBER(I3),MAX(0,MIN(100,IF(I3>=0.95,100,60+(I3-0.75)*200))),"Insufficient Data") -> Insufficient Data | K3: 0.5 | L3: Rewards Journey UI is still In Review, so it is not yet a completed task.
A4: EMP-0083 | B4: Maninder Singh | C4: =IFERROR(INDEX(Employee_Master!$F:$F,MATCH(A4,Employee_Master!$A:$A,0)),"") -> Product | D4: =COUNTIF(Tracker_Cleaned!$G$2:$G$176,A4) -> 8 | E4: =COUNTIFS(Tracker_Cleaned!$G$2:$G$176,A4,Tracker_Cleaned!$Y$2:$Y$176,"Yes") -> 0 | F4: =COUNTIFS(Tracker_Cleaned!$G$2:$G$176,A4,Tracker_Cleaned!$Y$2:$Y$176,"Yes",Tracker_Cleaned!$T$2:$T$176,"On time") -> 0 | G4: =COUNTIFS(Tracker_Cleaned!$G$2:$G$176,A4,Tracker_Cleaned!$Y$2:$Y$176,"Yes",Tracker_Cleaned!$T$2:$T$176,"Late") -> 0 | H4: =COUNTIFS(Tracker_Cleaned!$G$2:$G$176,A4,Tracker_Cleaned!$Y$2:$Y$176,"Excluded (validated delay)") -> 0 | I4: =IF(E4<3,"Insufficient Data",F4/E4) -> Insufficient Data | J4: =IF(ISNUMBER(I4),MAX(0,MIN(100,IF(I4>=0.95,100,60+(I4-0.75)*200))),"Insufficient Data") -> Insufficient Data | K4: 1 | L4: Jumpp Website 1.1 is On Hold; it was counted as an on-time completion. No completed tasks remain, so the metric is Insufficient Data.
A5: EMP-0170 | B5: Vinay Thakur | C5: =IFERROR(INDEX(Employee_Master!$F:$F,MATCH(A5,Employee_Master!$A:$A,0)),"") -> Operations & BO | D5: =COUNTIF(Tracker_Cleaned!$G$2:$G$176,A5) -> 1 | E5: =COUNTIFS(Tracker_Cleaned!$G$2:$G$176,A5,Tracker_Cleaned!$Y$2:$Y$176,"Yes") -> 0 | F5: =COUNTIFS(Tracker_Cleaned!$G$2:$G$176,A5,Tracker_Cleaned!$Y$2:$Y$176,"Yes",Tracker_Cleaned!$T$2:$T$176,"On time") -> 0 | G5: =COUNTIFS(Tracker_Cleaned!$G$2:$G$176,A5,Tracker_Cleaned!$Y$2:$Y$176,"Yes",Tracker_Cleaned!$T$2:$T$176,"Late") -> 0 | H5: =COUNTIFS(Tracker_Cleaned!$G$2:$G$176,A5,Tracker_Cleaned!$Y$2:$Y$176,"Excluded (validated delay)") -> 0 | I5: =IF(E5<3,"Insufficient Data",F5/E5) -> Insufficient Data | J5: =IF(ISNUMBER(I5),MAX(0,MIN(100,IF(I5>=0.95,100,60+(I5-0.75)*200))),"Insufficient Data") -> Insufficient Data
A6: EMP-0109 | B6: Pawan Kumar | C6: =IFERROR(INDEX(Employee_Master!$F:$F,MATCH(A6,Employee_Master!$A:$A,0)),"") -> Demat | D6: =COUNTIF(Tracker_Cleaned!$G$2:$G$176,A6) -> 2 | E6: =COUNTIFS(Tracker_Cleaned!$G$2:$G$176,A6,Tracker_Cleaned!$Y$2:$Y$176,"Yes") -> 0 | F6: =COUNTIFS(Tracker_Cleaned!$G$2:$G$176,A6,Tracker_Cleaned!$Y$2:$Y$176,"Yes",Tracker_Cleaned!$T$2:$T$176,"On time") -> 0 | G6: =COUNTIFS(Tracker_Cleaned!$G$2:$G$176,A6,Tracker_Cleaned!$Y$2:$Y$176,"Yes",Tracker_Cleaned!$T$2:$T$176,"Late") -> 0 | H6: =COUNTIFS(Tracker_Cleaned!$G$2:$G$176,A6,Tracker_Cleaned!$Y$2:$Y$176,"Excluded (validated delay)") -> 0 | I6: =IF(E6<3,"Insufficient Data",F6/E6) -> Insufficient Data | J6: =IF(ISNUMBER(I6),MAX(0,MIN(100,IF(I6>=0.95,100,60+(I6-0.75)*200))),"Insufficient Data") -> Insufficient Data
A7: EMP-0174 | B7: Vivek Sharma | C7: =IFERROR(INDEX(Employee_Master!$F:$F,MATCH(A7,Employee_Master!$A:$A,0)),"") -> Operations & BO | D7: =COUNTIF(Tracker_Cleaned!$G$2:$G$176,A7) -> 2 | E7: =COUNTIFS(Tracker_Cleaned!$G$2:$G$176,A7,Tracker_Cleaned!$Y$2:$Y$176,"Yes") -> 0 | F7: =COUNTIFS(Tracker_Cleaned!$G$2:$G$176,A7,Tracker_Cleaned!$Y$2:$Y$176,"Yes",Tracker_Cleaned!$T$2:$T$176,"On time") -> 0 | G7: =COUNTIFS(Tracker_Cleaned!$G$2:$G$176,A7,Tracker_Cleaned!$Y$2:$Y$176,"Yes",Tracker_Cleaned!$T$2:$T$176,"Late") -> 0 | H7: =COUNTIFS(Tracker_Cleaned!$G$2:$G$176,A7,Tracker_Cleaned!$Y$2:$Y$176,"Excluded (validated delay)") -> 0 | I7: =IF(E7<3,"Insufficient Data",F7/E7) -> Insufficient Data | J7: =IF(ISNUMBER(I7),MAX(0,MIN(100,IF(I7>=0.95,100,60+(I7-0.75)*200))),"Insufficient Data") -> Insufficient Data
A8: EMP-0181 | B8: Jai Dev Singh | C8: =IFERROR(INDEX(Employee_Master!$F:$F,MATCH(A8,Employee_Master!$A:$A,0)),"") -> Operations & BO | D8: =COUNTIF(Tracker_Cleaned!$G$2:$G$176,A8) -> 2 | E8: =COUNTIFS(Tracker_Cleaned!$G$2:$G$176,A8,Tracker_Cleaned!$Y$2:$Y$176,"Yes") -> 0 | F8: =COUNTIFS(Tracker_Cleaned!$G$2:$G$176,A8,Tracker_Cleaned!$Y$2:$Y$176,"Yes",Tracker_Cleaned!$T$2:$T$176,"On time") -> 0 | G8: =COUNTIFS(Tracker_Cleaned!$G$2:$G$176,A8,Tracker_Cleaned!$Y$2:$Y$176,"Yes",Tracker_Cleaned!$T$2:$T$176,"Late") -> 0 | H8: =COUNTIFS(Tracker_Cleaned!$G$2:$G$176,A8,Tracker_Cleaned!$Y$2:$Y$176,"Excluded (validated delay)") -> 0 | I8: =IF(E8<3,"Insufficient Data",F8/E8) -> Insufficient Data | J8: =IF(ISNUMBER(I8),MAX(0,MIN(100,IF(I8>=0.95,100,60+(I8-0.75)*200))),"Insufficient Data") -> Insufficient Data
A9: EMP-0175 | B9: Kanav Verma | C9: =IFERROR(INDEX(Employee_Master!$F:$F,MATCH(A9,Employee_Master!$A:$A,0)),"") -> Operations & BO | D9: =COUNTIF(Tracker_Cleaned!$G$2:$G$176,A9) -> 1 | E9: =COUNTIFS(Tracker_Cleaned!$G$2:$G$176,A9,Tracker_Cleaned!$Y$2:$Y$176,"Yes") -> 0 | F9: =COUNTIFS(Tracker_Cleaned!$G$2:$G$176,A9,Tracker_Cleaned!$Y$2:$Y$176,"Yes",Tracker_Cleaned!$T$2:$T$176,"On time") -> 0 | G9: =COUNTIFS(Tracker_Cleaned!$G$2:$G$176,A9,Tracker_Cleaned!$Y$2:$Y$176,"Yes",Tracker_Cleaned!$T$2:$T$176,"Late") -> 0 | H9: =COUNTIFS(Tracker_Cleaned!$G$2:$G$176,A9,Tracker_Cleaned!$Y$2:$Y$176,"Excluded (validated delay)") -> 0 | I9: =IF(E9<3,"Insufficient Data",F9/E9) -> Insufficient Data | J9: =IF(ISNUMBER(I9),MAX(0,MIN(100,IF(I9>=0.95,100,60+(I9-0.75)*200))),"Insufficient Data") -> Insufficient Data
A10: EMP-0187 | B10: Akashdeep | C10: =IFERROR(INDEX(Employee_Master!$F:$F,MATCH(A10,Employee_Master!$A:$A,0)),"") -> Operations & BO | D10: =COUNTIF(Tracker_Cleaned!$G$2:$G$176,A10) -> 1 | E10: =COUNTIFS(Tracker_Cleaned!$G$2:$G$176,A10,Tracker_Cleaned!$Y$2:$Y$176,"Yes") -> 0 | F10: =COUNTIFS(Tracker_Cleaned!$G$2:$G$176,A10,Tracker_Cleaned!$Y$2:$Y$176,"Yes",Tracker_Cleaned!$T$2:$T$176,"On time") -> 0 | G10: =COUNTIFS(Tracker_Cleaned!$G$2:$G$176,A10,Tracker_Cleaned!$Y$2:$Y$176,"Yes",Tracker_Cleaned!$T$2:$T$176,"Late") -> 0 | H10: =COUNTIFS(Tracker_Cleaned!$G$2:$G$176,A10,Tracker_Cleaned!$Y$2:$Y$176,"Excluded (validated delay)") -> 0 | I10: =IF(E10<3,"Insufficient Data",F10/E10) -> Insufficient Data | J10: =IF(ISNUMBER(I10),MAX(0,MIN(100,IF(I10>=0.95,100,60+(I10-0.75)*200))),"Insufficient Data") -> Insufficient Data
A11: EMP-0110 | B11: Yogesh | C11: =IFERROR(INDEX(Employee_Master!$F:$F,MATCH(A11,Employee_Master!$A:$A,0)),"") -> Demat | D11: =COUNTIF(Tracker_Cleaned!$G$2:$G$176,A11) -> 2 | E11: =COUNTIFS(Tracker_Cleaned!$G$2:$G$176,A11,Tracker_Cleaned!$Y$2:$Y$176,"Yes") -> 0 | F11: =COUNTIFS(Tracker_Cleaned!$G$2:$G$176,A11,Tracker_Cleaned!$Y$2:$Y$176,"Yes",Tracker_Cleaned!$T$2:$T$176,"On time") -> 0 | G11: =COUNTIFS(Tracker_Cleaned!$G$2:$G$176,A11,Tracker_Cleaned!$Y$2:$Y$176,"Yes",Tracker_Cleaned!$T$2:$T$176,"Late") -> 0 | H11: =COUNTIFS(Tracker_Cleaned!$G$2:$G$176,A11,Tracker_Cleaned!$Y$2:$Y$176,"Excluded (validated delay)") -> 0 | I11: =IF(E11<3,"Insufficient Data",F11/E11) -> Insufficient Data | J11: =IF(ISNUMBER(I11),MAX(0,MIN(100,IF(I11>=0.95,100,60+(I11-0.75)*200))),"Insufficient Data") -> Insufficient Data
A12: EMP-0112 | B12: Atul Kumar | C12: =IFERROR(INDEX(Employee_Master!$F:$F,MATCH(A12,Employee_Master!$A:$A,0)),"") -> Demat | D12: =COUNTIF(Tracker_Cleaned!$G$2:$G$176,A12) -> 2 | E12: =COUNTIFS(Tracker_Cleaned!$G$2:$G$176,A12,Tracker_Cleaned!$Y$2:$Y$176,"Yes") -> 0 | F12: =COUNTIFS(Tracker_Cleaned!$G$2:$G$176,A12,Tracker_Cleaned!$Y$2:$Y$176,"Yes",Tracker_Cleaned!$T$2:$T$176,"On time") -> 0 | G12: =COUNTIFS(Tracker_Cleaned!$G$2:$G$176,A12,Tracker_Cleaned!$Y$2:$Y$176,"Yes",Tracker_Cleaned!$T$2:$T$176,"Late") -> 0 | H12: =COUNTIFS(Tracker_Cleaned!$G$2:$G$176,A12,Tracker_Cleaned!$Y$2:$Y$176,"Excluded (validated delay)") -> 0 | I12: =IF(E12<3,"Insufficient Data",F12/E12) -> Insufficient Data | J12: =IF(ISNUMBER(I12),MAX(0,MIN(100,IF(I12>=0.95,100,60+(I12-0.75)*200))),"Insufficient Data") -> Insufficient Data
A13: EMP-0048 | B13: Saksham | C13: =IFERROR(INDEX(Employee_Master!$F:$F,MATCH(A13,Employee_Master!$A:$A,0)),"") -> Product | D13: =COUNTIF(Tracker_Cleaned!$G$2:$G$176,A13) -> 1 | E13: =COUNTIFS(Tracker_Cleaned!$G$2:$G$176,A13,Tracker_Cleaned!$Y$2:$Y$176,"Yes") -> 0 | F13: =COUNTIFS(Tracker_Cleaned!$G$2:$G$176,A13,Tracker_Cleaned!$Y$2:$Y$176,"Yes",Tracker_Cleaned!$T$2:$T$176,"On time") -> 0 | G13: =COUNTIFS(Tracker_Cleaned!$G$2:$G$176,A13,Tracker_Cleaned!$Y$2:$Y$176,"Yes",Tracker_Cleaned!$T$2:$T$176,"Late") -> 0 | H13: =COUNTIFS(Tracker_Cleaned!$G$2:$G$176,A13,Tracker_Cleaned!$Y$2:$Y$176,"Excluded (validated delay)") -> 0 | I13: =IF(E13<3,"Insufficient Data",F13/E13) -> Insufficient Data | J13: =IF(ISNUMBER(I13),MAX(0,MIN(100,IF(I13>=0.95,100,60+(I13-0.75)*200))),"Insufficient Data") -> Insufficient Data
A14: EMP-0058 | B14: Jaspreet Singh | C14: =IFERROR(INDEX(Employee_Master!$F:$F,MATCH(A14,Employee_Master!$A:$A,0)),"") -> Product | D14: =COUNTIF(Tracker_Cleaned!$G$2:$G$176,A14) -> 1 | E14: =COUNTIFS(Tracker_Cleaned!$G$2:$G$176,A14,Tracker_Cleaned!$Y$2:$Y$176,"Yes") -> 0 | F14: =COUNTIFS(Tracker_Cleaned!$G$2:$G$176,A14,Tracker_Cleaned!$Y$2:$Y$176,"Yes",Tracker_Cleaned!$T$2:$T$176,"On time") -> 0 | G14: =COUNTIFS(Tracker_Cleaned!$G$2:$G$176,A14,Tracker_Cleaned!$Y$2:$Y$176,"Yes",Tracker_Cleaned!$T$2:$T$176,"Late") -> 0 | H14: =COUNTIFS(Tracker_Cleaned!$G$2:$G$176,A14,Tracker_Cleaned!$Y$2:$Y$176,"Excluded (validated delay)") -> 0 | I14: =IF(E14<3,"Insufficient Data",F14/E14) -> Insufficient Data | J14: =IF(ISNUMBER(I14),MAX(0,MIN(100,IF(I14>=0.95,100,60+(I14-0.75)*200))),"Insufficient Data") -> Insufficient Data
A15: EMP-0046 | B15: Jatin Vashisht | C15: =IFERROR(INDEX(Employee_Master!$F:$F,MATCH(A15,Employee_Master!$A:$A,0)),"") -> Product | D15: =COUNTIF(Tracker_Cleaned!$G$2:$G$176,A15) -> 2 | E15: =COUNTIFS(Tracker_Cleaned!$G$2:$G$176,A15,Tracker_Cleaned!$Y$2:$Y$176,"Yes") -> 0 | F15: =COUNTIFS(Tracker_Cleaned!$G$2:$G$176,A15,Tracker_Cleaned!$Y$2:$Y$176,"Yes",Tracker_Cleaned!$T$2:$T$176,"On time") -> 0 | G15: =COUNTIFS(Tracker_Cleaned!$G$2:$G$176,A15,Tracker_Cleaned!$Y$2:$Y$176,"Yes",Tracker_Cleaned!$T$2:$T$176,"Late") -> 0 | H15: =COUNTIFS(Tracker_Cleaned!$G$2:$G$176,A15,Tracker_Cleaned!$Y$2:$Y$176,"Excluded (validated delay)") -> 0 | I15: =IF(E15<3,"Insufficient Data",F15/E15) -> Insufficient Data | J15: =IF(ISNUMBER(I15),MAX(0,MIN(100,IF(I15>=0.95,100,60+(I15-0.75)*200))),"Insufficient Data") -> Insufficient Data
A16: EMP-0027 | B16: Aryan Raj | C16: =IFERROR(INDEX(Employee_Master!$F:$F,MATCH(A16,Employee_Master!$A:$A,0)),"") -> Product | D16: =COUNTIF(Tracker_Cleaned!$G$2:$G$176,A16) -> 2 | E16: =COUNTIFS(Tracker_Cleaned!$G$2:$G$176,A16,Tracker_Cleaned!$Y$2:$Y$176,"Yes") -> 0 | F16: =COUNTIFS(Tracker_Cleaned!$G$2:$G$176,A16,Tracker_Cleaned!$Y$2:$Y$176,"Yes",Tracker_Cleaned!$T$2:$T$176,"On time") -> 0 | G16: =COUNTIFS(Tracker_Cleaned!$G$2:$G$176,A16,Tracker_Cleaned!$Y$2:$Y$176,"Yes",Tracker_Cleaned!$T$2:$T$176,"Late") -> 0 | H16: =COUNTIFS(Tracker_Cleaned!$G$2:$G$176,A16,Tracker_Cleaned!$Y$2:$Y$176,"Excluded (validated delay)") -> 0 | I16: =IF(E16<3,"Insufficient Data",F16/E16) -> Insufficient Data | J16: =IF(ISNUMBER(I16),MAX(0,MIN(100,IF(I16>=0.95,100,60+(I16-0.75)*200))),"Insufficient Data") -> Insufficient Data
... A29: EMP-0230 | B29: Jaspal | C29: =IFERROR(INDEX(Employee_Master!$F:$F,MATCH(A29,Employee_Master!$A:$A,0)),"") -> Client Support | D29: =COUNTIF(Tracker_Cleaned!$G$2:$G$176,A29) -> 3 | E29: =COUNTIFS(Tracker_Cleaned!$G$2:$G$176,A29,Tracker_Cleaned!$Y$2:$Y$176,"Yes") -> 0 | F29: =COUNTIFS(Tracker_Cleaned!$G$2:$G$176,A29,Tracker_Cleaned!$Y$2:$Y$176,"Yes",Tracker_Cleaned!$T$2:$T$176,"On time") -> 0 | G29: =COUNTIFS(Tracker_Cleaned!$G$2:$G$176,A29,Tracker_Cleaned!$Y$2:$Y$176,"Yes",Tracker_Cleaned!$T$2:$T$176,"Late") -> 0 | H29: =COUNTIFS(Tracker_Cleaned!$G$2:$G$176,A29,Tracker_Cleaned!$Y$2:$Y$176,"Excluded (validated delay)") -> 0 | I29: =IF(E29<3,"Insufficient Data",F29/E29) -> Insufficient Data | J29: =IF(ISNUMBER(I29),MAX(0,MIN(100,IF(I29>=0.95,100,60+(I29-0.75)*200))),"Insufficient Data") -> Insufficient Data
A31: Rules: eligible = Mapped Status Completed + target date + completed date. Late tasks with a validated, excludable blocker are removed from the denominator. Minimum 3 eligible tasks per period, else Insufficient Data (configurable). Score: 95%+ = 100; 75% = 60; linear between and below (floor 0) - replaces the old step bands where 74% scored 0.

Sheet Workflow_Templates
A1: Template | B1: Step | C1: Stage (task) | D1: Depends on step | E1: Responsible (R) role | F1: Default R person | G1: R Emp ID | H1: Accountable (A) - exactly one | I1: A Emp ID | J1: Consulted (C) | K1: Informed (I) | L1: Checklist (acceptance criteria) | M1: Reviewer (validation owner) | N1: Review criteria | O1: Required evidence before submit | P1: SLA as written | Q1: SLA target (business days) | R1: SLA max (business days) | S1: Effort min (hrs) | T1: Effort max (hrs) | U1: Mitigation | V1: Flags / to confirm
A2: Email campaign | B2: 1 | C2: Campaign request initiation | D2: - | E2: Requesting department (Sales / RMS / Back office / CS / Operations / IT) | F2: Manager of requesting department | G2: (per request) | H2: Marketing POC: Mukesh Thakur | J2: - | K2: Email execution: Naveen Kumar | L2: Define campaign objective; Specify target audience; Provide key messages; Share timeline requirements | M2: Manager of requesting department (sheet lists: Gurjot Sodhi - Sales, Kapil Abrol - CS, Pawan Kumar - Operations, Ayushman Dey - RMS, Vivek Sharma - Back office, Rajesh Gaddam - IT, Mukesh Thakur - Marketing) | N2: Request is complete; Fits the marketing calendar | O2: Email request form; Campaign brief document | P2: 2-3 business days | Q2: 2 | R2: 3 | S2: 2 | T2: 3 | U2: Assign a backup POC to avoid delays. | V2: Mukesh Thakur is not in the org chart. "Gurjot Sodhi" and "Rajesh Gaddam" do not match org-chart names (Gurjot Singh, AVP-Sales; Patel Rajesh, VP-IT) - confirm. Generic sheet lists Marketing POC as both A and I.
A3: Email campaign | B3: 2 | C3: Content creation | D3: 1 | E3: Content team | F3: Miteeksha | G3: EMP-0153 | H3: Marketing POC: Mukesh Thakur | J3: Requesting department | K3: Email execution: Naveen Kumar | L3: Write email copy; Create subject lines; Draft preview text; Include CTA | M3: Content Manager: Miteeksha | N3: Matches the brief; Follows brand guidelines; Proofread | O3: Draft content document; Revision history | P3: 2-3 business days | Q3: 2 | R3: 3 | S3: 4 | T3: 8 | U3: Use a content checklist to ensure all requirements are met. | V3: Miteeksha is both the default R and the reviewer - the platform blocks self-review, so assign a different reviewer.
A4: Email campaign | B4: 3 | C4: Content approval | D4: 2 | E4: Content team (routes for sign-off) | F4: Miteeksha | G4: EMP-0153 | H4: Head of requesting department (resolved per request) | I4: (per request) | J4: Compliance team (if needed) | K4: Marketing POC: Mukesh Thakur | L4: Review content accuracy; Check messaging alignment; Verify compliance | M4: Head of requesting department | N4: Department sign-off; Compliance / legal approval; Regulator approval (TRAI or WhatsApp) where needed | O4: Approval email; Change requests | P4: 1-2 business days | Q4: 1 | R4: 2 | S4: 2 | T4: 3 | U4: Include a pre-approval review to minimise changes. | V4: Versions disagree: generic sheet says R = Marketing POC and C = Legal team; named sheet says R = Content team and C = Compliance team. A was "Requesting department" (a team) - must be one named person.
A5: Email campaign | B5: 4 | C5: HTML development | D5: 3 | E5: HTML developer | F5: Naveen Kumar | G5: EMP-0118 | H5: Marketing POC: Mukesh Thakur (proposed) | J5: Email execution team | K5: Content team; Marketing POC | L5: Code email template; Test responsive design; Optimise for email clients; Include tracking parameters | M5: Proposed: Marketing POC (sheet says HTML developer: Naveen Kumar) | N5: Cross-client testing; Mobile check; Link verification | O5: HTML files; Test screenshots | P5: 1-2 business days | Q5: 1 | R5: 2 | S5: 4 | T5: 6 | U5: Test templates on multiple devices and email clients before final approval. | V5: Named sheet makes Naveen Kumar R, A and reviewer - no independent check. Naveen Kumar matches two employees (EMP-0118 Digital Marketing, EMP-0204 RMS) - EMP-0118 assumed.
A6: Email campaign | B6: 5 | C6: Campaign setup and launch | D6: 4 | E6: Email execution team | F6: Naveen Kumar | G6: EMP-0118 | H6: Marketing POC: Mukesh Thakur (proposed) | J6: HTML developer | K6: Requesting department; Marketing team | L6: Upload HTML; Import client list; Set up segmentation; Configure tracking; Schedule or launch campaign | M6: Proposed: Marketing POC (sheet says Campaign manager: Naveen Kumar) | N6: Test email send; Verify all links; Check personalisation; Validate list | O6: Test sends; Campaign settings; List verification report | P6: 1-2 business days | Q6: 1 | R6: 2 | S6: 3 | T6: 4 | U6: Conduct a dry run before the final launch to identify issues. | V6: Named sheet: Naveen Kumar is R, A, C and reviewer. Highest-risk step (Critical) has no independent check.
A7: Email campaign | B7: 6 | C7: Performance tracking | D7: 5 | E7: Email execution team | F7: Naveen Kumar | G7: EMP-0118 | H7: Marketing POC: Mukesh Thakur (proposed) | J7: Data analyst | K7: Requesting department; Marketing team; Stakeholders | L7: Monitor delivery rate; Track open rate; Analyse click rate; Record conversions | M7: Proposed: Data analyst or Marketing POC (sheet says Campaign manager: Naveen Kumar) | N7: Verify tracking setup; Check data accuracy | O7: Campaign analytics; Performance dashboard | P7: Ongoing (initial report 2 days post-launch) | Q7: 2 | R7: 2 | S7: 0.5 | T7: 1 | U7: Use automated tools for real-time tracking and reporting. | V7: SLA covers the first report only; the cadence of later reports is not defined. Effort is per report.
C8: End-to-end total (if no step waits) | Q8: =SUM(Q2:Q7) -> 9 | R8: =SUM(R2:R7) -> 14 | S8: =SUM(S2:S7) -> 15.5 | T8: =SUM(T2:T7) -> 25
A10: Source: RACI.xlsx (visible "RACI Matrix" sheet with generic roles, and hidden "Sheet3" with named people). Default people come from the named version; conflicts are in the Flags column. Blue numbers are SLA/effort values taken from the source ranges (target = lower bound, max = upper bound).

Sheet Risk_Register
A1: Risk ID | B1: Template | C1: Step | D1: Stage | E1: Risk | F1: Criticality | G1: Dependencies | H1: Assumptions | I1: Mitigation | J1: Risk owner (Emp ID) | K1: Status | L1: Next review date
A2: RSK-001 | B2: Email campaign | C2: 1 | D2: Campaign request initiation | E2: Incomplete requirements | F2: Medium | G2: Marketing calendar available; Clear business objectives | H2: Requesting team has identified the target audience; Business case is justified | I2: Assign a backup POC to avoid delays. | K2: Open
A3: RSK-002 | B3: Email campaign | C3: 1 | D3: Campaign request initiation | E3: Unrealistic timelines | F3: Medium | G3: Marketing calendar available; Clear business objectives | H3: Requesting team has identified the target audience; Business case is justified | I3: Assign a backup POC to avoid delays. | K3: Open
A4: RSK-003 | B4: Email campaign | C4: 2 | D4: Content creation | E4: Misalignment with brand voice | F4: High | G4: Complete brief from requesting department; Updated brand guidelines | H4: Content team has capacity; Brand guidelines are current | I4: Use a content checklist to ensure all requirements are met. | K4: Open
A5: RSK-004 | B5: Email campaign | C5: 2 | D5: Content creation | E5: Subject-matter expertise gaps | F5: High | G5: Complete brief from requesting department; Updated brand guidelines | H5: Content team has capacity; Brand guidelines are current | I5: Use a content checklist to ensure all requirements are met. | K5: Open
A6: RSK-005 | B6: Email campaign | C6: 3 | D6: Content approval | E6: Delayed approvals | F6: High | G6: Content creation completed; Approvers available | H6: Department head has final say; Legal review not always required | I6: Include a pre-approval review to minimise changes. | K6: Open
A7: RSK-006 | B7: Email campaign | C7: 3 | D7: Content approval | E7: Multiple revision cycles | F7: High | G7: Content creation completed; Approvers available | H7: Department head has final say; Legal review not always required | I7: Include a pre-approval review to minimise changes. | K7: Open
A8: RSK-007 | B8: Email campaign | C8: 4 | D8: HTML development | E8: Rendering issues in email clients | F8: Medium | G8: Final approved content; Email template available | H8: HTML developer has required skills; Email-client list is up to date | I8: Test templates on multiple devices and email clients before final approval. | K8: Open
A9: RSK-008 | B9: Email campaign | C9: 4 | D9: HTML development | E9: Broken links or tracking | F9: Medium | G9: Final approved content; Email template available | H9: HTML developer has required skills; Email-client list is up to date | I9: Test templates on multiple devices and email clients before final approval. | K9: Open
A10: RSK-009 | B10: Email campaign | C10: 5 | D10: Campaign setup and launch | E10: List quality issues | F10: Critical | G10: Completed HTML; Clean contact list; Approved content | H10: Email platform is functioning; Contact list is up to date | I10: Conduct a dry run before the final launch to identify issues. | K10: Open
A11: RSK-010 | B11: Email campaign | C11: 5 | D11: Campaign setup and launch | E11: Technical platform errors | F11: Critical | G11: Completed HTML; Clean contact list; Approved content | H11: Email platform is functioning; Contact list is up to date | I11: Conduct a dry run before the final launch to identify issues. | K11: Open
A12: RSK-011 | B12: Email campaign | C12: 6 | D12: Performance tracking | E12: Tracking failures | F12: Low | G12: Tracking implemented correctly; Analytics platform working | H12: Tracking parameters are set correctly; Baseline metrics are established | I12: Use automated tools for real-time tracking and reporting. | K12: Open
A13: RSK-012 | B13: Email campaign | C13: 6 | D13: Performance tracking | E13: Data interpretation errors | F13: Low | G13: Tracking implemented correctly; Analytics platform working | H13: Tracking parameters are set correctly; Baseline metrics are established | I13: Use automated tools for real-time tracking and reporting. | K13: Open
A15: Source: RACI.xlsx "Risks & Mitigation Strategies". That sheet has no stage column, so risks are mapped to stages by row order (6 rows, 6 stages) - confirm. Each cell held two risks; they are split into one row each. Owner and review date are new fields to fill.

Sheet RCA_Register
A1: RCA ID | B1: Incident title | C1: Product / system | D1: Incident date | E1: Received date | F1: Reported by | G1: Severity | H1: Clients impacted | I1: Orders impacted | J1: Root cause | K1: Root cause category | L1: Gap identified | M1: Correction action taken | N1: Correction completed on | O1: Preventive action | P1: Preventive action owner (Emp ID) | Q1: Preventive action due date | R1: Responsible department | S1: Responsible stakeholder (Emp ID) | T1: Expected closure date | U1: Actual closure date | V1: Status | W1: Closure verified by (Emp ID) | X1: Repeat of RCA ID | Y1: Individual attribution validated? | Z1: Days open (auto) | AA1: Closed on time? (auto)
A2: =IF(B2="","","RCA-"&TEXT(ROW()-1,"000")) -> RCA-001 | B2: EXAMPLE - replace or delete: [incident title] | C2: [product / system] | D2: 46280 | E2: 46280 | F2: [name or Emp ID] | G2: Medium | H2: [number] | I2: [number] | J2: [what actually caused it] | K2: Process | L2: [which control or check was missing] | M2: [what was done to restore service] | N2: 46281 | O2: [what will stop it happening again] | P2: [Emp ID] | Q2: 46295 | R2: Client Support | S2: [Emp ID] | T2: 46295 | V2: Preventive action in progress | Y2: No | Z2: =IF(E2="","",IF(U2<>"",U2-E2,README!$B$4-E2)) -> 14 | AA2: =IF(OR(T2="",U2=""),"",IF(U2<=T2,"Yes","No"))
A3: =IF(B3="","","RCA-"&TEXT(ROW()-1,"000")) | Z3: =IF(E3="","",IF(U3<>"",U3-E3,README!$B$4-E3)) | AA3: =IF(OR(T3="",U3=""),"",IF(U3<=T3,"Yes","No"))
A4: =IF(B4="","","RCA-"&TEXT(ROW()-1,"000")) | Z4: =IF(E4="","",IF(U4<>"",U4-E4,README!$B$4-E4)) | AA4: =IF(OR(T4="",U4=""),"",IF(U4<=T4,"Yes","No"))
A5: =IF(B5="","","RCA-"&TEXT(ROW()-1,"000")) | Z5: =IF(E5="","",IF(U5<>"",U5-E5,README!$B$4-E5)) | AA5: =IF(OR(T5="",U5=""),"",IF(U5<=T5,"Yes","No"))
A6: =IF(B6="","","RCA-"&TEXT(ROW()-1,"000")) | Z6: =IF(E6="","",IF(U6<>"",U6-E6,README!$B$4-E6)) | AA6: =IF(OR(T6="",U6=""),"",IF(U6<=T6,"Yes","No"))
A7: =IF(B7="","","RCA-"&TEXT(ROW()-1,"000")) | Z7: =IF(E7="","",IF(U7<>"",U7-E7,README!$B$4-E7)) | AA7: =IF(OR(T7="",U7=""),"",IF(U7<=T7,"Yes","No"))
A8: =IF(B8="","","RCA-"&TEXT(ROW()-1,"000")) | Z8: =IF(E8="","",IF(U8<>"",U8-E8,README!$B$4-E8)) | AA8: =IF(OR(T8="",U8=""),"",IF(U8<=T8,"Yes","No"))
A9: =IF(B9="","","RCA-"&TEXT(ROW()-1,"000")) | Z9: =IF(E9="","",IF(U9<>"",U9-E9,README!$B$4-E9)) | AA9: =IF(OR(T9="",U9=""),"",IF(U9<=T9,"Yes","No"))
A10: =IF(B10="","","RCA-"&TEXT(ROW()-1,"000")) | Z10: =IF(E10="","",IF(U10<>"",U10-E10,README!$B$4-E10)) | AA10: =IF(OR(T10="",U10=""),"",IF(U10<=T10,"Yes","No"))
A11: =IF(B11="","","RCA-"&TEXT(ROW()-1,"000")) | Z11: =IF(E11="","",IF(U11<>"",U11-E11,README!$B$4-E11)) | AA11: =IF(OR(T11="",U11=""),"",IF(U11<=T11,"Yes","No"))
A12: =IF(B12="","","RCA-"&TEXT(ROW()-1,"000")) | Z12: =IF(E12="","",IF(U12<>"",U12-E12,README!$B$4-E12)) | AA12: =IF(OR(T12="",U12=""),"",IF(U12<=T12,"Yes","No"))
A13: =IF(B13="","","RCA-"&TEXT(ROW()-1,"000")) | Z13: =IF(E13="","",IF(U13<>"",U13-E13,README!$B$4-E13)) | AA13: =IF(OR(T13="",U13=""),"",IF(U13<=T13,"Yes","No"))
A14: =IF(B14="","","RCA-"&TEXT(ROW()-1,"000")) | Z14: =IF(E14="","",IF(U14<>"",U14-E14,README!$B$4-E14)) | AA14: =IF(OR(T14="",U14=""),"",IF(U14<=T14,"Yes","No"))
... A201: =IF(B201="","","RCA-"&TEXT(ROW()-1,"000")) | Z201: =IF(E201="","",IF(U201<>"",U201-E201,README!$B$4-E201)) | AA201: =IF(OR(T201="",U201=""),"",IF(U201<=T201,"Yes","No"))

Sheet Issue_Register
A1: # | B1: Source | C1: Area | D1: Issue | E1: Severity | F1: Fix Applied / Rule Adopted | G1: Where Fixed
A2: 1 | B2: R&R Parameters | C2: Weights | D2: Quantifiable group stated as 60% but its sub-weights sum to 75-100%; Qualitative stated as 40% but sums to 50-65%. | E2: High | F2: 60/40 split retired. Team-category weights are the only weighting model; every category must total exactly 100% (validated on save). | G2: Spec 5.3; Category_Weights
A3: 2 | B3: R&R Parameters | C3: Metrics | D3: Core Revenue uses "Culture (10%)", which is not one of the 8 defined metrics. | E3: High | F3: Culture mapped to the Collaboration metric (teamwork, knowledge sharing, conduct). Rubric in Spec 5.2.7. | G3: Spec 5.2.7; Category_Weights
A4: 3 | B4: R&R Parameters | C4: Metrics | D4: Productivity is defined but has 0% weight in every category; Innovation appears only in Support. | E4: Medium | F4: Kept as configurable metrics. Productivity is used as an R&R tie-breaker and award input until management assigns it a weight. | G4: Spec 5.3, 7.3
A5: 4 | B5: R&R Parameters | C5: Metrics | D5: CSAT has no column in the column definitions; it is folded into "Quality". | E5: Medium | F5: CSAT is a separate metric with its own data source and minimum sample size; Quality no longer contains customer satisfaction. | G5: Spec 5.2.4
A6: 5 | B6: R&R Parameters | C6: Categories | D6: Client Support is measured mainly on CSAT, but CSAT is weighted only in Core Revenue. | E6: High | F6: Proposed 4th category "Customer Service" (CSAT 30, Quality 25, On-Time 20, Achievement 15, Compliance 10) - pending approval. | G6: Spec 5.3; Departments
A7: 6 | B7: R&R Parameters | C7: Scoring | D7: On-Time bands have a cliff: 75-84% = 3.0 but 74% = 0. | E7: High | F7: Continuous scoring: 95%+ = 100, 85% = 80, 75% = 60, linear between and below (floor 0). Matches every original anchor with no cliff. | G7: Spec 5.2.1; OnTime_Recalc
A8: 7 | B8: R&R Parameters | C8: Scoring | D8: Achievement: 100%+ already scores 5.0, so the 150% cap has no effect. | E8: Medium | F8: Meeting target (100%) = 90; over-achievement earns the last 10 points up to the 150% cap = 100. | G8: Spec 5.2.2
A9: 8 | B9: R&R Parameters | C9: Scoring | D9: Productivity formula (Output / Team Avg x 5) gives 6.0 at 120%, contradicting its own band (120%+ = 5.0). | E9: Medium | F9: Ratio-based curve capped at 100; weighted by task complexity and adjusted for available capacity; minimum team size 3. | G9: Spec 5.2.6
A10: 9 | B10: R&R Parameters | C10: Scoring | D10: Compliance scale stops at 3.0 (one medium incident); multiple or major incidents undefined. | E10: Medium | F10: Deduction model: start 100, Minor -20, Medium -40, Major -100 per validated incident (floor 0). | G10: Spec 5.2.3
A11: 10 | B11: R&R Parameters | C11: Scoring | D11: Collaboration and Innovation rubrics define only levels 5 and 3. | E11: Medium | F11: All five levels defined with evidence requirements; scores of 1, 2 and 5 need written evidence. | G11: Spec 5.2.7-5.2.8
A12: 11 | B12: R&R Parameters | C12: Scale | D12: Framework scores 1-5; master prompt specifies a 0-100 final score. | E12: Medium | F12: Every metric is computed natively on 0-100. A 1-5 display equivalent = score / 20 is shown for continuity. | G12: Spec 5.1
A13: 12 | B13: R&R Parameters | C13: Identity | D13: Framework expects an Emp. ID column; no source file contains employee IDs. | E13: High | F13: Placeholder IDs (EMP-xxxx) issued so records can be linked; HRMS code column added for replacement before go-live. | G13: Employee_Master
... A59: 58 | B59: RCA | C59: Formatting | D59: Sheet is formatted to W983 for 10 header cells (73 KB). | E59: Low | F59: Ignored on import. | G59: RCA_Register
